Workbook

Sheet transaction
A1: Account Holder: | B1: SASA PAY
A2: Short Code: | B2: 756756
A3: Account: | B3: MMF Account for Organization
A4: Time Period: | B4: From | C4: 02-09-2026 00:00:00 | D4: To | E4: 02-09-2026 23:59:59
A5: Operator: | B5: Muthoni | C5: Organization: | D5: SASA PAY | E5: Date of Report: | F5: 10-09-2026 11:42:06
A6: Opening Balance: | B6: 28661758 | C6: Closing Balance: | D6: 8341383.6 | E6: Available Balance: | G6: Total Paid In: | H6: 18632763 | I6: Total Withdrawn: | J6: -38954918
A7: Receipt No. | B7: Completion Time | C7: Initiation Time | D7: Details | E7: Transaction Status | F7: Paid In | G7: Withdrawn | H7: Balance | I7: Balance Confirmed | J7: Reason Type | K7: Other Party Info | L7: Linked Transaction ID | M7: A/C No. | N7: Currency
A8: UI2SB4Y11C | B8: 02-09-2026 23:35:58 | C8: 02-09-2026 23:35:58 | D8: Business Buy Goods Charge | E8: Completed | G8: -18 | H8: 8341383.6 | I8: true | J8: Business Buy Goods via API | K8: SP | N8: KES
A9: UI2SB4Y11C | B9: 02-09-2026 23:35:58 | C9: 02-09-2026 23:35:58 | D9: Business Buy Goods at 686775 - NEW TAFRIJA RESTAURANT via API REF Bill Payment 254723836614 to 727654 | E9: Completed | G9: -1450 | H9: 8341401.6 | I9: true | J9: Business Buy Goods via API | K9: 686775 - NEW TAFRIJA RESTAURANT | N9: KES
A10: UI2SB4XZP4 | B10: 02-09-2026 22:11:30 | C10: 02-09-2026 22:11:30 | D10: Business Pay Bill Charge | E10: Completed | G10: -13 | H10: 8342851.6 | I10: true | J10: Business Pay Bill via API | K10: SP | N10: KES
A11: UI2SB4XZP4 | B11: 02-09-2026 22:11:30 | C11: 02-09-2026 22:11:30 | D11: Business Pay Bill via API to 714888 - LOOP BIZ Acc. 323989 | E11: Completed | G11: -750 | H11: 8342864.6 | I11: true | J11: Business Pay Bill via API | K11: 714888 - LOOP BIZ | M11: 323989 | N11: KES
A12: UI2SB4XY6A | B12: 02-09-2026 22:11:16 | C12: 02-09-2026 22:11:16 | D12: Business Buy Goods Charge | E12: Completed | G12: -39 | H12: 8343614.6 | I12: true | J12: Business Buy Goods via API | K12: SP | N12: KES
A13: UI2SB4XY6A | B13: 02-09-2026 22:11:16 | C13: 02-09-2026 22:11:16 | D13: Business Buy Goods at 871036 - OILIBYA TOM MBOYA via API REF Bill Payment 15115 to 871046 | E13: Completed | G13: -5000 | H13: 8343653.6 | I13: true | J13: Business Buy Goods via API | K13: 871036 - OILIBYA TOM MBOYA | N13: KES
A14: UI2SB4XV62 | B14: 02-09-2026 22:10:16 | C14: 02-09-2026 22:10:16 | D14: Business Buy Goods Charge | E14: Completed | G14: -39 | H14: 8348653.6 | I14: true | J14: Business Buy Goods via API | K14: SP | N14: KES
A15: UI2SB4XV62 | B15: 02-09-2026 22:10:16 | C15: 02-09-2026 22:10:16 | D15: Business Buy Goods at 871036 - OILIBYA TOM MBOYA via API REF Bill Payment 15111 to 871046 | E15: Completed | G15: -5000 | H15: 8348692.6 | I15: true | J15: Business Buy Goods via API | K15: 871036 - OILIBYA TOM MBOYA | N15: KES
A16: UI2SB4XR95 | B16: 02-09-2026 22:09:53 | C16: 02-09-2026 22:09:53 | D16: Business Buy Goods Charge | E16: Completed | G16: -39 | H16: 8353692.6 | I16: true | J16: Business Buy Goods via API | K16: SP | N16: KES
A17: UI2SB4XR95 | B17: 02-09-2026 22:09:53 | C17: 02-09-2026 22:09:53 | D17: Business Buy Goods at 5967480 - KENNEDY WAITHAKA MBURU via API REF Bill Payment 1625943 to 3564672 | E17: Completed | G17: -4300 | H17: 8353731.6 | I17: true | J17: Business Buy Goods via API | K17: 5967480 - KENNEDY WAITHAKA MBURU | N17: KES
A18: UI2SB4XWNW | B18: 02-09-2026 22:07:39 | C18: 02-09-2026 22:07:39 | D18: Business Buy Goods Charge | E18: Completed | G18: -39 | H18: 8358031.6 | I18: true | J18: Business Buy Goods via API | K18: SP | N18: KES
A19: UI2SB4XWNW | B19: 02-09-2026 22:07:39 | C19: 02-09-2026 22:07:39 | D19: Business Buy Goods at 871036 - OILIBYA TOM MBOYA via API REF Bill Payment 15112 to 871046 | E19: Completed | G19: -5000 | H19: 8358070.6 | I19: true | J19: Business Buy Goods via API | K19: 871036 - OILIBYA TOM MBOYA | N19: KES
A20: UI2SB4XZOC | B20: 02-09-2026 22:06:32 | C20: 02-09-2026 22:06:32 | D20: Business Buy Goods Charge | E20: Completed | G20: -39 | H20: 8363070.6 | I20: true | J20: Business Buy Goods via API | K20: SP | N20: KES
A21: UI2SB4XZOC | B21: 02-09-2026 22:06:32 | C21: 02-09-2026 22:06:32 | D21: Business Buy Goods at 871036 - OILIBYA TOM MBOYA via API REF Bill Payment 15109 to 871046 | E21: Completed | G21: -5000 | H21: 8363109.6 | I21: true | J21: Business Buy Goods via API | K21: 871036 - OILIBYA TOM MBOYA | N21: KES
A22: UI2SB4XWNB | B22: 02-09-2026 22:05:20 | C22: 02-09-2026 22:05:20 | D22: Business Buy Goods Charge | E22: Completed | G22: -54 | H22: 8368109.6 | I22: true | J22: Business Buy Goods via API | K22: SP | N22: KES
A23: UI2SB4XWNB | B23: 02-09-2026 22:05:20 | C23: 02-09-2026 22:05:20 | D23: Business Buy Goods at 5285574 - National Oil Githunguri 1 via API REF Bill Payment 17941 to 4906008 | E23: Completed | G23: -7900 | H23: 8368163.6 | I23: true | J23: Business Buy Goods via API | K23: 5285574 - National Oil Githunguri 1 | N23: KES
A24: UI2SB4XWKN | B24: 02-09-2026 21:58:43 | C24: 02-09-2026 21:58:43 | D24: Business Pay Bill Charge | E24: Completed | G24: -8 | H24: 8376063.6 | I24: true | J24: Business Pay Bill via API | K24: SP | N24: KES
A25: UI2SB4XWKN | B25: 02-09-2026 21:58:43 | C25: 02-09-2026 21:58:43 | D25: Business Pay Bill via API to 880100 - NCBA BANK KENYA PLC. Acc. 999810 | E25: Completed | G25: -150 | H25: 8376071.6 | I25: true | J25: Business Pay Bill via API | K25: 880100 - NCBA BANK KENYA PLC. | M25: 999810 | N25: KES
A26: UI2SB4XUYP | B26: 02-09-2026 21:48:00 | C26: 02-09-2026 21:48:00 | D26: Business Buy Goods Charge | E26: Completed | G26: -48 | H26: 8376221.6 | I26: true | J26: Business Buy Goods via API | K26: SP | N26: KES
A27: UI2SB4XUYP | B27: 02-09-2026 21:48:00 | C27: 02-09-2026 21:48:00 | D27: Business Buy Goods at 7248058 - RUBIS KOMAROCK via API REF Bill Payment 77483 to 9246253 | E27: Completed | G27: -5550 | H27: 8376269.6 | I27: true | J27: Business Buy Goods via API | K27: 7248058 - RUBIS KOMAROCK | N27: KES
A28: UI2SB4XR2E | B28: 02-09-2026 21:45:41 | C28: 02-09-2026 21:45:41 | D28: Business Pay Bill Charge | E28: Completed | G28: -25 | H28: 8381819.6 | I28: true | J28: Business Pay Bill via API | K28: SP | N28: KES
A29: UI2SB4XR2E | B29: 02-09-2026 21:45:41 | C29: 02-09-2026 21:45:41 | D29: Business Pay Bill via API to 4062755 - VILCOM NETWORKS LTD Acc. 2168789 | E29: Completed | G29: -2000 | H29: 8381844.6 | I29: true | J29: Business Pay Bill via API | K29: 4062755 - VILCOM NETWORKS LTD | M29: 2168789 | N29: KES
A30: UI2SB4XR0O | B30: 02-09-2026 21:40:13 | C30: 02-09-2026 21:40:13 | D30: Business Buy Goods Charge | E30: Completed | G30: -48 | H30: 8383844.6 | I30: true | J30: Business Buy Goods via API | K30: SP | N30: KES
A31: UI2SB4XR0O | B31: 02-09-2026 21:40:13 | C31: 02-09-2026 21:40:13 | D31: Business Buy Goods at 7248058 - RUBIS KOMAROCK via API REF Bill Payment 80420 to 9246253 | E31: Completed | G31: -6700 | H31: 8383892.6 | I31: true | J31: Business Buy Goods via API | K31: 7248058 - RUBIS KOMAROCK | N31: KES
A32: UI2SB4XQ20 | B32: 02-09-2026 21:28:00 | C32: 02-09-2026 21:27:59 | D32: Business Pay Bill via API to 400222 - Co-operative Bank Collection Account Acc. 1118738# | E32: Completed | G32: -8650 | H32: 8390592.6 | I32: true | J32: Business Pay Bill via API | K32: 400222 - Co-operative Bank Collection Account | M32: 1118738# | N32: KES
A33: UI2SB4XQ20 | B33: 02-09-2026 21:28:00 | C33: 02-09-2026 21:27:59 | D33: Business Pay Bill Charge | E33: Completed | G33: -54 | H33: 8399242.6 | I33: true | J33: Business Pay Bill via API | K33: SP | N33: KES
A34: UI2SB4XOIF | B34: 02-09-2026 21:21:15 | C34: 02-09-2026 21:21:15 | D34: Business Buy Goods Charge | E34: Completed | G34: -39 | H34: 8399296.6 | I34: true | J34: Business Buy Goods via API | K34: SP | N34: KES
A35: UI2SB4XOIF | B35: 02-09-2026 21:21:15 | C35: 02-09-2026 21:21:15 | D35: Business Buy Goods at 5504520 - GSE TRADERS LIMITED via API REF Bill Payment 77475 to 4998256 | E35: Completed | G35: -3700 | H35: 8399335.6 | I35: true | J35: Business Buy Goods via API | K35: 5504520 - GSE TRADERS LIMITED | N35: KES
A36: UI2SB4XLF1 | B36: 02-09-2026 21:13:48 | C36: 02-09-2026 21:13:48 | D36: Business Buy Goods Charge | E36: Completed | G36: -48 | H36: 8403035.6 | I36: true | J36: Business Buy Goods via API | K36: SP | N36: KES
A37: UI2SB4XLF1 | B37: 02-09-2026 21:13:48 | C37: 02-09-2026 21:13:48 | D37: Business Buy Goods at 836548 - Be Energy Kayole Petrol station via API REF Bill Payment 77487 to 821697 | E37: Completed | G37: -5750 | H37: 8403083.6 | I37: true | J37: Business Buy Goods via API | K37: 836548 - Be Energy Kayole Petrol station | N37: KES
A38: UI2SB4XS7Z | B38: 02-09-2026 21:13:37 | C38: 02-09-2026 21:13:37 | D38: Business Buy Goods Charge | E38: Completed | G38: -63 | H38: 8408833.6 | I38: true | J38: Business Buy Goods via API | K38: SP | N38: KES
A39: UI2SB4XS7Z | B39: 02-09-2026 21:13:37 | C39: 02-09-2026 21:13:37 | D39: Business Buy Goods at 968511 - Shell Machakos Service Station via API REF Bill Payment 15115 to 968512 | E39: Completed | G39: -12415 | H39: 8408896.6 | I39: true | J39: Business Buy Goods via API | K39: 968511 - Shell Machakos Service Station | N39: KES
A40: UI2SB4XOGR | B40: 02-09-2026 21:12:37 | C40: 02-09-2026 21:12:37 | D40: Business Buy Goods Charge | E40: Completed | G40: -63 | H40: 8421311.6 | I40: true | J40: Business Buy Goods via API | K40: SP | N40: KES
A41: UI2SB4XOGR | B41: 02-09-2026 21:12:37 | C41: 02-09-2026 21:12:37 | D41: Business Buy Goods at 968511 - Shell Machakos Service Station via API REF Bill Payment 15108 to 968512 | E41: Completed | G41: -14400 | H41: 8421374.6 | I41: true | J41: Business Buy Goods via API | K41: 968511 - Shell Machakos Service Station | N41: KES
A42: UI2SB4XPX9 | B42: 02-09-2026 21:10:28 | C42: 02-09-2026 21:10:28 | D42: Business Buy Goods Charge | E42: Completed | G42: -8 | H42: 8435774.6 | I42: true | J42: Business Buy Goods via API | K42: SP | N42: KES
A43: UI2SB4XPX9 | B43: 02-09-2026 21:10:28 | C43: 02-09-2026 21:10:28 | D43: Business Buy Goods at 6262597 - THE FOREST VIEW RESORT LIMITED via API REF Bill Payment 254725682509 to 8234036 | E43: Completed | G43: -300 | H43: 8435782.6 | I43: true | J43: Business Buy Goods via API | K43: 6262597 - THE FOREST VIEW RESORT LIMITED | N43: KES
A44: UI2SB4XPX7 | B44: 02-09-2026 21:10:26 | C44: 02-09-2026 21:10:25 | D44: Business Buy Goods Charge | E44: Completed | G44: -63 | H44: 8436082.6 | I44: true | J44: Business Buy Goods via API | K44: SP | N44: KES
... A58: UI2SB4XLA0 | B58: 02-09-2026 21:00:07 | C58: 02-09-2026 21:00:07 | D58: Business Pay Bill Charge | E58: Completed | G58: -25 | H58: 8487536.6 | I58: true | J58: Business Pay Bill via API | K58: SP | N58: KES
A59: UI2SB4XLA0 | B59: 02-09-2026 21:00:07 | C59: 02-09-2026 21:00:07 | D59: Business Pay Bill via API to 444174 - CHOICE MICROFINANCE BANK. Acc. 46013001326841 | E59: Completed | G59: -1700 | H59: 8487561.6 | I59: true | J59: Business Pay Bill via API | K59: 444174 - CHOICE MICROFINANCE BANK. | M59: 46013001326841 | N59: KES
A60: UI2SB4XS2G | B60: 02-09-2026 21:00:06 | C60: 02-09-2026 21:00:06 | D60: Business Pay Bill Charge | E60: Completed | G60: -79 | H60: 8489261.6 | I60: true | J60: Business Pay Bill via API | K60: SP | N60: KES
A61: UI2SB4XS2G | B61: 02-09-2026 21:00:06 | C61: 02-09-2026 21:00:06 | D61: Business Pay Bill via API to 444174 - CHOICE MICROFINANCE BANK. Acc. 46013001319812 | E61: Completed | G61: -27800 | H61: 8489340.6 | I61: true | J61: Business Pay Bill via API | K61: 444174 - CHOICE MICROFINANCE BANK. | M61: 46013001319812 | N61: KES
A62: UI2SB4XQMO | B62: 02-09-2026 21:00:05 | C62: 02-09-2026 21:00:05 | D62: Business Pay Bill Charge | E62: Completed | G62: -63 | H62: 8517140.6 | I62: true | J62: Business Pay Bill via API | K62: SP | N62: KES
A63: UI2SB4XQMO | B63: 02-09-2026 21:00:05 | C63: 02-09-2026 21:00:05 | D63: Business Pay Bill via API to 444174 - CHOICE MICROFINANCE BANK. Acc. 46011000008774 | E63: Completed | G63: -10200 | H63: 8517203.6 | I63: true | J63: Business Pay Bill via API | K63: 444174 - CHOICE MICROFINANCE BANK. | M63: 46011000008774 | N63: KES
A64: UI2SB4XQMD | B64: 02-09-2026 20:59:30 | C64: 02-09-2026 20:59:30 | D64: Funds Transfer from Utility Account to Working Account | E64: Completed | F64: 5000000 | H64: 8527403.6 | I64: true | J64: Business Transfer From Utility Account To MMF Account via API | K64: 756756 - SASA PAY | N64: KES
A65: UI2SB4XL58 | B65: 02-09-2026 20:42:54 | C65: 02-09-2026 20:42:53 | D65: Business Pay Bill via API to 4298298 - AMICA SACCO LIMITED Acc. 008108000000040 | E65: Completed | G65: -4810 | H65: 3527403.6 | I65: true | J65: Business Pay Bill via API | K65: 4298298 - AMICA SACCO LIMITED | M65: 008108000000040 | N65: KES
A66: UI2SB4XL58 | B66: 02-09-2026 20:42:54 | C66: 02-09-2026 20:42:53 | D66: Business Pay Bill Charge | E66: Completed | G66: -39 | H66: 3532213.6 | I66: true | J66: Business Pay Bill via API | K66: SP | N66: KES
A67: UI2SB4XPKG | B67: 02-09-2026 20:37:36 | C67: 02-09-2026 20:37:36 | D67: Business Buy Goods Charge | E67: Completed | G67: -3 | H67: 3532252.6 | I67: true | J67: Business Buy Goods via API | K67: SP | N67: KES
A68: UI2SB4XPKG | B68: 02-09-2026 20:37:36 | C68: 02-09-2026 20:37:36 | D68: Business Buy Goods at 8425475 - DENNIS MWATHE MIRITI via API REF Bill Payment 1667632 to 6096903 | E68: Completed | G68: -50 | H68: 3532255.6 | I68: true | J68: Business Buy Goods via API | K68: 8425475 - DENNIS MWATHE MIRITI | N68: KES
A69: UI2SB4XJN2 | B69: 02-09-2026 20:20:12 | C69: 02-09-2026 20:20:12 | D69: Business Buy Goods Charge | E69: Completed | G69: -48 | H69: 3532305.6 | I69: true | J69: Business Buy Goods via API | K69: SP | N69: KES
A70: UI2SB4XJN2 | B70: 02-09-2026 20:20:12 | C70: 02-09-2026 20:20:12 | D70: Business Buy Goods at 836548 - Be Energy Kayole Petrol station via API REF Bill Payment 77480 to 821697 | E70: Completed | G70: -6300 | H70: 3532353.6 | I70: true | J70: Business Buy Goods via API | K70: 836548 - Be Energy Kayole Petrol station | N70: KES
A71: UI2SB4XQ87 | B71: 02-09-2026 20:16:48 | C71: 02-09-2026 20:16:47 | D71: Business Pay Bill Charge | E71: Completed | G71: -48 | H71: 3538653.6 | I71: true | J71: Business Pay Bill via API | K71: SP | N71: KES
A72: UI2SB4XQ87 | B72: 02-09-2026 20:16:48 | C72: 02-09-2026 20:16:47 | D72: Business Pay Bill via API to 793174 - BRANCH MICROFINANCE BANK LIMITED Acc. 0112549551 | E72: Completed | G72: -6000 | H72: 3538701.6 | I72: true | J72: Business Pay Bill via API | K72: 793174 - BRANCH MICROFINANCE BANK LIMITED | M72: 0112549551 | N72: KES
A73: UI2SB4XKVI | B73: 02-09-2026 20:10:09 | C73: 02-09-2026 20:10:08 | D73: Business Buy Goods Charge | E73: Completed | G73: -8 | H73: 3544701.6 | I73: true | J73: Business Buy Goods via API | K73: SP | N73: KES
A74: UI2SB4XKVI | B74: 02-09-2026 20:10:09 | C74: 02-09-2026 20:10:08 | D74: Business Buy Goods at 6276261 - MINIMALISTIC ENTERPRISES LIMITED via API REF Bill Payment 445424 to 8383472 | E74: Completed | G74: -500 | H74: 3544709.6 | I74: true | J74: Business Buy Goods via API | K74: 6276261 - MINIMALISTIC ENTERPRISES LIMITED | N74: KES
A75: UI2SB4XNVI | B75: 02-09-2026 20:07:31 | C75: 02-09-2026 20:07:31 | D75: Business Buy Goods Charge | E75: Completed | G75: -2 | H75: 3545209.6 | I75: true | J75: Business Buy Goods via API | K75: SP | N75: KES
A76: UI2SB4XNVI | B76: 02-09-2026 20:07:31 | C76: 02-09-2026 20:07:31 | D76: Business Buy Goods at 7193269 - ANNE MBULWA KIARIE via API REF Bill Payment 254711665578 to 5185173 | E76: Completed | G76: -15 | H76: 3545211.6 | I76: true | J76: Business Buy Goods via API | K76: 7193269 - ANNE MBULWA KIARIE | N76: KES
A77: UI2SB4XKUS | B77: 02-09-2026 20:06:19 | C77: 02-09-2026 20:06:19 | D77: Business Pay Bill Charge | E77: Completed | G77: -68 | H77: 3545226.6 | I77: true | J77: Business Pay Bill via API | K77: SP | N77: KES
A78: UI2SB4XKUS | B78: 02-09-2026 20:06:19 | C78: 02-09-2026 20:06:19 | D78: Business Pay Bill via API to 985050 - Gulf African Bank-Paybill Acc. 0900282601 | E78: Completed | G78: -18000 | H78: 3545294.6 | I78: true | J78: Business Pay Bill via API | K78: 985050 - Gulf African Bank-Paybill | M78: 0900282601 | N78: KES
A79: UI2SB4XPAH | B79: 02-09-2026 20:04:37 | C79: 02-09-2026 20:04:35 | D79: Business Pay Bill via API to 982100 - IMARISHA SACCO Acc. 5046291201 | E79: Completed | G79: -17366 | H79: 3563294.6 | I79: true | J79: Business Pay Bill via API | K79: 982100 - IMARISHA SACCO | M79: 5046291201 | N79: KES
A80: UI2SB4XPAH | B80: 02-09-2026 20:04:37 | C80: 02-09-2026 20:04:35 | D80: Business Pay Bill Charge | E80: Completed | G80: -68 | H80: 3580660.6 | I80: true | J80: Business Pay Bill via API | K80: SP | N80: KES
A81: UI2SB4XP9B | B81: 02-09-2026 20:01:38 | C81: 02-09-2026 20:01:38 | D81: Business Buy Goods Charge | E81: Completed | G81: -8 | H81: 3580728.6 | I81: true | J81: Business Buy Goods via API | K81: SP | N81: KES
A82: UI2SB4XP9B | B82: 02-09-2026 20:01:38 | C82: 02-09-2026 20:01:38 | D82: Business Buy Goods at 9138752 - Samuel Mungai Muriithi via API REF Bill Payment 164621 to 4885582 | E82: Completed | G82: -450 | H82: 3580736.6 | I82: true | J82: Business Buy Goods via API | K82: 9138752 - Samuel Mungai Muriithi | N82: KES
A83: UI2SB4XKL3 | B83: 02-09-2026 19:40:10 | C83: 02-09-2026 19:40:09 | D83: Business Pay Bill Charge | E83: Completed | G83: -8 | H83: 3581186.6 | I83: true | J83: Business Pay Bill via API | K83: SP | N83: KES
A84: UI2SB4XKL3 | B84: 02-09-2026 19:40:10 | C84: 02-09-2026 19:40:09 | D84: Business Pay Bill via API to 400222 - Co-operative Bank Collection Account Acc. 1118738# | E84: Completed | G84: -300 | H84: 3581194.6 | I84: true | J84: Business Pay Bill via API | K84: 400222 - Co-operative Bank Collection Account | M84: 1118738# | N84: KES
A85: UI2SB4XKKC | B85: 02-09-2026 19:38:14 | C85: 02-09-2026 19:38:13 | D85: Business Pay Bill via API to 400222 - Co-operative Bank Collection Account Acc. 1118738# | E85: Completed | G85: -8000 | H85: 3581494.6 | I85: true | J85: Business Pay Bill via API | K85: 400222 - Co-operative Bank Collection Account | M85: 1118738# | N85: KES
A86: UI2SB4XKKC | B86: 02-09-2026 19:38:14 | C86: 02-09-2026 19:38:13 | D86: Business Pay Bill Charge | E86: Completed | G86: -54 | H86: 3589494.6 | I86: true | J86: Business Pay Bill via API | K86: SP | N86: KES
A87: UI2SB4XJ44 | B87: 02-09-2026 19:24:24 | C87: 02-09-2026 19:24:24 | D87: Business Buy Goods Charge | E87: Completed | G87: -3 | H87: 3589548.6 | I87: true | J87: Business Buy Goods via API | K87: SP | N87: KES
A88: UI2SB4XJ44 | B88: 02-09-2026 19:24:24 | C88: 02-09-2026 19:24:24 | D88: Business Buy Goods at 8561779 - FELIX ONYANGO ODUOR via API REF Bill Payment 254797413147 to 6721699 | E88: Completed | G88: -100 | H88: 3589551.6 | I88: true | J88: Business Buy Goods via API | K88: 8561779 - FELIX ONYANGO ODUOR | N88: KES
A89: UI2SB4XHU2 | B89: 02-09-2026 19:19:31 | C89: 02-09-2026 19:19:31 | D89: Business Buy Goods Charge | E89: Completed | G89: -3 | H89: 3589651.6 | I89: true | J89: Business Buy Goods via API | K89: SP | N89: KES
A90: UI2SB4XHU2 | B90: 02-09-2026 19:19:31 | C90: 02-09-2026 19:19:31 | D90: Business Buy Goods at 8561779 - FELIX ONYANGO ODUOR via API REF Bill Payment 254797413147 to 6721699 | E90: Completed | G90: -50 | H90: 3589654.6 | I90: true | J90: Business Buy Goods via API | K90: 8561779 - FELIX ONYANGO ODUOR | N90: KES
A91: UI2SB4XFA2 | B91: 02-09-2026 18:51:10 | C91: 02-09-2026 18:51:09 | D91: Business Pay Bill via API to 400222 - Co-operative Bank Collection Account Acc. 1118738# | E91: Completed | G91: -750 | H91: 3589704.6 | I91: true | J91: Business Pay Bill via API | K91: 400222 - Co-operative Bank Collection Account | M91: 1118738# | N91: KES
A92: UI2SB4XFA2 | B92: 02-09-2026 18:51:10 | C92: 02-09-2026 18:51:09 | D92: Business Pay Bill Charge | E92: Completed | G92: -13 | H92: 3590454.6 | I92: true | J92: Business Pay Bill via API | K92: SP | N92: KES
A93: UI2SB4XN4M | B93: 02-09-2026 18:50:46 | C93: 02-09-2026 18:50:45 | D93: Business Pay Bill via API to 247247 - Equity Paybill Account Acc. 0890195415435 | E93: Completed | G93: -67400 | H93: 3590467.6 | I93: true | J93: Business Pay Bill via API | K93: 247247 - Equity Paybill Account | M93: 0890195415435 | N93: KES
A94: UI2SB4XN4M | B94: 02-09-2026 18:50:46 | C94: 02-09-2026 18:50:45 | D94: Business Pay Bill Charge | E94: Completed | G94: -115 | H94: 3657867.6 | I94: true | J94: Business Pay Bill via API | K94: SP | N94: KES
A95: UI2SB4XLK0 | B95: 02-09-2026 18:47:56 | C95: 02-09-2026 18:47:55 | D95: Business Pay Bill Charge | E95: Completed | G95: -63 | H95: 3657982.6 | I95: true | J95: Business Pay Bill via API | K95: SP | N95: KES
A96: UI2SB4XLK0 | B96: 02-09-2026 18:47:56 | C96: 02-09-2026 18:47:55 | D96: Business Pay Bill via API to 400222 - Co-operative Bank Collection Account Acc. 1118738# | E96: Completed | G96: -12000 | H96: 3658045.6 | I96: true | J96: Business Pay Bill via API | K96: 400222 - Co-operative Bank Collection Account | M96: 1118738# | N96: KES
A97: UI2SB4XHJ8 | B97: 02-09-2026 18:45:11 | C97: 02-09-2026 18:45:11 | D97: Business Pay Bill Charge | E97: Completed | G97: -8 | H97: 3670045.6 | I97: true | J97: Business Pay Bill via API | K97: SP | N97: KES
A98: UI2SB4XHJ8 | B98: 02-09-2026 18:45:11 | C98: 02-09-2026 18:45:11 | D98: Business Pay Bill via API to 542542 - IM BANK C2B Acc. 940721 | E98: Completed | G98: -500 | H98: 3670053.6 | I98: true | J98: Business Pay Bill via API | K98: 542542 - IM BANK C2B | M98: 940721 | N98: KES
A99: UI2SB4XHJ7 | B99: 02-09-2026 18:45:08 | C99: 02-09-2026 18:45:08 | D99: Business Pay Bill Charge | E99: Completed | G99: -110 | H99: 3670553.6 | I99: true | J99: Business Pay Bill via API | K99: SP | N99: KES
A100: UI2SB4XHJ7 | B100: 02-09-2026 18:45:08 | C100: 02-09-2026 18:45:08 | D100: Business Pay Bill via API to 542542 - IM BANK C2B Acc. 940721 | E100: Completed | G100: -42000 | H100: 3670663.6 | I100: true | J100: Business Pay Bill via API | K100: 542542 - IM BANK C2B | M100: 940721 | N100: KES
A101: UI2SB4XC86 | B101: 02-09-2026 18:41:33 | C101: 02-09-2026 18:41:33 | D101: Business Buy Goods Charge | E101: Completed | G101: -25 | H101: 3712663.6 | I101: true | J101: Business Buy Goods via API | K101: SP | N101: KES
A102: UI2SB4XC86 | B102: 02-09-2026 18:41:33 | C102: 02-09-2026 18:41:33 | D102: Business Buy Goods at 7526456 - Quick Mart Thome via API REF Bill Payment 254708582465 to 9481423 | E102: Completed | G102: -1663 | H102: 3712688.6 | I102: true | J102: Business Buy Goods via API | K102: 7526456 - Quick Mart Thome | N102: KES
A103: UI2SB4XABB | B103: 02-09-2026 17:51:37 | C103: 02-09-2026 17:51:37 | D103: Business Buy Goods Charge | E103: Completed | G103: -13 | H103: 3714351.6 | I103: true | J103: Business Buy Goods via API | K103: SP | N103: KES
A104: UI2SB4XABB | B104: 02-09-2026 17:51:37 | C104: 02-09-2026 17:51:37 | D104: Business Buy Goods at 6818183 - Galana Energies Station - Runda Mall via API REF Bill Payment 469005 to 4293700 | E104: Completed | G104: -1000 | H104: 3714364.6 | I104: true | J104: Business Buy Goods via API | K104: 6818183 - Galana Energies Station - Runda Mall | N104: KES
A105: UI2SB4XBPP | B105: 02-09-2026 17:46:17 | C105: 02-09-2026 17:46:17 | D105: Business Pay Bill Charge | E105: Completed | G105: -68 | H105: 3715364.6 | I105: true | J105: Business Pay Bill via API | K105: SP | N105: KES
A106: UI2SB4XBPP | B106: 02-09-2026 17:46:17 | C106: 02-09-2026 17:46:17 | D106: Business Pay Bill via API to 4113485 - Liquid Telecommunications (K) LTD 2 Acc. LHK-19700-0001 | E106: Completed | G106: -19999 | H106: 3715432.6 | I106: true | J106: Business Pay Bill via API | K106: 4113485 - Liquid Telecommunications (K) LTD 2 | M106: LHK-19700-0001 | N106: KES
A107: UI2SB4XGZG | B107: 02-09-2026 17:44:19 | C107: 02-09-2026 17:44:19 | D107: Business Pay Bill Charge | E107: Completed | G107: -8 | H107: 3735431.6 | I107: true | J107: Business Pay Bill via API | K107: SP | N107: KES
A108: UI2SB4XGZG | B108: 02-09-2026 17:44:19 | C108: 02-09-2026 17:44:19 | D108: Business Pay Bill via API to 542542 - IM BANK C2B Acc. 940721 | E108: Completed | G108: -500 | H108: 3735439.6 | I108: true | J108: Business Pay Bill via API | K108: 542542 - IM BANK C2B | M108: 940721 | N108: KES
A109: UI2SB4XFKF | B109: 02-09-2026 17:44:17 | C109: 02-09-2026 17:44:17 | D109: Business Pay Bill Charge | E109: Completed | G109: -74 | H109: 3735939.6 | I109: true | J109: Business Pay Bill via API | K109: SP | N109: KES
A110: UI2SB4XFKF | B110: 02-09-2026 17:44:17 | C110: 02-09-2026 17:44:17 | D110: Business Pay Bill via API to 542542 - IM BANK C2B Acc. 940721 | E110: Completed | G110: -24000 | H110: 3736013.6 | I110: true | J110: Business Pay Bill via API | K110: 542542 - IM BANK C2B | M110: 940721 | N110: KES
A111: UI2SB4X8W8 | B111: 02-09-2026 17:39:58 | C111: 02-09-2026 17:39:58 | D111: Business Buy Goods Charge | E111: Completed | G111: -30 | H111: 3760013.6 | I111: true | J111: Business Buy Goods via API | K111: SP | N111: KES
A112: UI2SB4X8W8 | B112: 02-09-2026 17:39:58 | C112: 02-09-2026 17:39:58 | D112: Business Buy Goods at 7212915 - GOODLIFE PHARMACY LIMITED - NAIROBI MEGA via API REF Bill Payment 784176 to 5198107 | E112: Completed | G112: -2990 | H112: 3760043.6 | I112: true | J112: Business Buy Goods via API | K112: 7212915 - GOODLIFE PHARMACY LIMITED - NAIROBI MEGA | N112: KES
A113: UI2SB4XBLV | B113: 02-09-2026 17:34:13 | C113: 02-09-2026 17:34:12 | D113: Business Buy Goods Charge | E113: Completed | G113: -30 | H113: 3763033.6 | I113: true | J113: Business Buy Goods via API | K113: SP | N113: KES
...

Sheet Sasapay stm
A1: Business Short Code | B1: Account Number | C1: Account Name | D1: Product Type | E1: Industry | F1: Transaction Type | G1: Debit | H1: Credit | I1: Charge Amount | J1: Service Fee | K1: SMS Charge Amount | L1: Collection Charge Amount | M1: Running Balance | N1: Transaction Date | O1: Transaction Code | P1: Third Party Transaction Code | Q1: Reversal Transaction Code | R1: Original Transaction Code | S1: Client Name | T1: From Channel | U1: To Channel | V1: Party B | W1: Party B Name | X1: Provider | Y1: Transaction Reference | Z1: Merchant Reference | AA1: Initiation Time | AB1: Reversal Status | AC1: Transaction Status | AD1: Platform | AE1: Result Code | AF1: Result Description
B2: 784176 | C2: Hizo Technology Limited | D2: Till | E2: Organisation | F2: Transaction Out | G2: 1780 | H2: 0 | I2: 10 | J2: 0 | K2: 1 | L2: 0 | M2: 120551.14 | N2: 46267 | O2: SWEJ7U8MQ4Z1O1F | P2: UI2SB4VYS8 | T2: SasaPay | U2: ThirdPartyBillPayment | V2: 4999930 | X2: Safaricom | Y2: W13841171 | Z2: 3fb92da8-1d57-43ce-b7ed-b97dfe3a649c | AA2: 46267.043 | AB2: Not Reversed | AC2: api | AD2: SUCCESS | AE2: SP00000 | AF2: Transaction completed successfully
B3: 80421 | C3: KBQ 732J | D3: Matatu | E3: Organisation | F3: Transaction Out | G3: 5650 | H3: 0 | I3: 15 | J3: 0 | K3: 1 | L3: 0 | M3: 36.934 | N3: 46267 | O3: SWEJ7U8M9TVRVWD | P3: UI2SB4W3H4 | T3: SasaPay | U3: ThirdPartyBillPayment | V3: 9246253 | X3: Safaricom | Y3: W13841941 | Z3: Fuel | AA3: 46267.215 | AB3: Not Reversed | AD3: SUCCESS | AE3: SP00000 | AF3: Transaction completed successfully
B4: 77489 | C4: KBU 351C | D4: Matatu | E4: Organisation | F4: Transaction Out | G4: 13650 | H4: 0 | I4: 15 | J4: 0 | K4: 1 | L4: 0 | M4: 11.15 | N4: 46267 | O4: SWEJ7U8NFFSX7WE | P4: UI2SB4WG3Q | T4: SasaPay | U4: ThirdPartyBillPayment | V4: 821697 | X4: Safaricom | Y4: W13842249 | Z4: Fuel | AA4: 46267.272 | AB4: Not Reversed | AD4: SUCCESS | AE4: SP00000 | AF4: Transaction completed successfully
B5: 77480 | C5: KBR 244Y | D5: Matatu | E5: Organisation | F5: Transaction Out | G5: 6700 | H5: 0 | I5: 15 | J5: 0 | K5: 1 | L5: 0 | M5: 21.98 | N5: 46267 | O5: SWEJ7U8NFHFDX44 | P5: UI2SB4WBNX | T5: SasaPay | U5: ThirdPartyBillPayment | V5: 821697 | X5: Safaricom | Y5: W13842255 | Z5: Fuel | AA5: 46267.272 | AB5: Not Reversed | AD5: SUCCESS | AE5: SP00000 | AF5: Transaction completed successfully
B6: 77487 | C6: KBY 456V | D6: Matatu | E6: Organisation | F6: Transaction Out | G6: 5400 | H6: 0 | I6: 15 | J6: 0 | K6: 1 | L6: 0 | M6: 33.796 | N6: 46267 | O6: SWEJ7U8NFI1398Z | P6: UI2SB4WHIQ | T6: SasaPay | U6: ThirdPartyBillPayment | V6: 821697 | X6: Safaricom | Y6: W13842259 | Z6: Fuel | AA6: 46267.273 | AB6: Not Reversed | AD6: SUCCESS | AE6: SP00000 | AF6: Transaction completed successfully
B7: 1586202 | C7: purity - Twiddle Pips | D7: Limited Personal Wallet | F7: Transaction Out | G7: 97486 | H7: 0 | I7: 15 | J7: 15 | K7: 0 | L7: 0 | M7: 3455 | N7: 46267 | O7: SWEJ7U8NKTMRLE3 | P7: UI2SB4WHX9 | T7: SasaPay | U7: ThirdPartyBillPayment | V7: 1586202 | X7: Safaricom | Y7: W13842697 | Z7: RZV9HXBQ | AA7: 46267.325 | AB7: Not Reversed | AD7: SUCCESS | AE7: SP00000 | AF7: Transaction completed successfully
A8: 756756 | B8: 254720233020 | C8: ALFRED GATONGA | D8: Limited Personal Wallet | F8: Transaction Out | G8: 1500 | H8: 0 | I8: 10 | J8: 0 | K8: 0 | L8: 0 | M8: 7232 | N8: 46267 | O8: SWEJ7U8NN8376XL | P8: UI2SB4WF8C | T8: SasaPay | U8: ThirdPartyBillPayment | V8: 634264 | X8: Safaricom | Y8: W13842961 | Z8: W13842961 | AA8: 46267.349 | AB8: Not Reversed | AC8: user_app | AD8: SUCCESS | AE8: SP00000 | AF8: Transaction completed successfully
A9: 756756 | B9: 254797413147 | C9: FELIX ODUOR | D9: Limited Personal Wallet | F9: Transaction Out | G9: 140 | H9: 0 | I9: 10 | J9: 0 | K9: 0 | L9: 0 | M9: 351 | N9: 46267 | O9: SWEJ7U8NOXUAGUH | P9: UI2SB4WJ6V | T9: SasaPay | U9: ThirdPartyBillPayment | V9: 6721699 | X9: Safaricom | Y9: W13843086 | Z9: W13843086 | AA9: 46267.36 | AB9: Not Reversed | AC9: user_app | AD9: SUCCESS | AE9: SP00000 | AF9: Transaction completed successfully
A10: 455555 | B10: 343884 | C10: Michael Mboya | D10: Limited Personal Wallet | F10: Transaction Out | G10: 3465 | H10: 0 | I10: 10 | J10: 0 | K10: 0 | L10: 0 | M10: 5794 | N10: 46267 | O10: SWEJ7U8NO3GU1SL | P10: UI2SN2T1MB | T10: SasaPay | U10: ThirdPartyBillPayment | V10: 9053691 | X10: Safaricom | Y10: W13843135 | Z10: W13843135 | AA10: 46267.362 | AB10: Not Reversed | AC10: user_app | AD10: SUCCESS | AE10: SP00000 | AF10: Transaction completed successfully
B11: 293009 | C11: Adeline Munguti | D11: Till | F11: Transaction Out | G11: 7363 | H11: 0 | I11: 57 | J11: 0 | K11: 0 | L11: 0 | M11: 389832 | N11: 46267 | O11: SWEJ7U8NPR9X7CR | P11: UI2SB4WKRW | S11: DAVIS AND SHIRTLIFF LIMITED | T11: SasaPay | U11: ThirdPartyBillPayment | V11: 293009 | W11: DAVIS AND SHIRTLIFF LIMITED | X11: Safaricom | Y11: W13843325 | Z11: a499805a-4877-47ee-8311-9d2500b53dbd | AA11: 46267.372 | AB11: Not Reversed | AD11: SUCCESS | AE11: SP00000 | AF11: Transaction completed successfully
B12: 15114 | C12: Umowa Sacco - KDY 537B | D12: Matatu | E12: Organisation | F12: Transaction Out | G12: 6000 | H12: 0 | I12: 15 | J12: 0 | K12: 1 | L12: 0 | M12: 13608.612 | N12: 46267 | O12: SWEJ7U8NPVAOAI8 | P12: UI2SB4WFJ7 | T12: SasaPay | U12: ThirdPartyBillPayment | V12: 968512 | X12: Safaricom | Y12: W13843347 | Z12: fuel | AA12: 46267.374 | AB12: Not Reversed | AD12: SUCCESS | AE12: SP00000 | AF12: Transaction completed successfully
B13: 414936 | C13: John Slater | D13: Limited Personal Wallet | F13: Transaction Out | G13: 1500 | H13: 0 | I13: 25 | J13: 2 | K13: 0 | L13: 0 | M13: 21326 | N13: 46267 | O13: SWEJ7U8NSU29DL3 | P13: UI2SB4WKYX | S13: KCB Paybill AC | T13: SasaPay | U13: ThirdPartyBillPayment | V13: 414936 | W13: KCB Paybill AC | X13: Safaricom | Y13: W13843684 | Z13: ACWTGA9V | AA13: 46267.391 | AB13: Not Reversed | AD13: SUCCESS | AE13: SP00000 | AF13: Transaction completed successfully
B14: 15111 | C14: Umowa Sacco - KDY 586B | D14: Matatu | E14: Organisation | F14: Transaction Out | G14: 10000 | H14: 0 | I14: 15 | J14: 0 | K14: 1 | L14: 0 | M14: 1124.458 | N14: 46267 | O14: SWEJ7U8NTA6RA6Y | P14: UI2SB4WHAH | T14: SasaPay | U14: ThirdPartyBillPayment | V14: 9926197 | X14: Safaricom | Y14: W13843802 | Z14: vincent recovery | AA14: 46267.398 | AB14: Not Reversed | AD14: SUCCESS | AE14: SP00000 | AF14: Transaction completed successfully
A15: 756756 | B15: 1625943 | C15: Kennedy - Kennedy waithaka mburu | D15: Biashara Wallet | F15: Transaction Out | G15: 2700 | H15: 0 | I15: 40 | J15: 0 | K15: 0 | L15: 0 | M15: 1305.23 | N15: 46267 | O15: SWEJ7U8NTKW9JJ2 | P15: UI2SB4WIRN | S15: Rubis Energy Kenya PLc | T15: SasaPay | U15: ThirdPartyBillPayment | V15: 485111 | W15: Rubis Energy Kenya PLc | X15: Safaricom | Y15: W13843860 | Z15: 6500090405 | AA15: 46267.402 | AB15: Not Reversed | AC15: user_app | AD15: SUCCESS | AE15: SP00000 | AF15: Transaction completed successfully
B16: 1484 | C16: VLC- OFFICE PETTY CASH | D16: Till | E16: Organisation | F16: Transaction Out | G16: 900 | H16: 0 | I16: 20 | J16: 0 | K16: 1 | L16: 0 | M16: 1328.674 | N16: 46267 | O16: SWEJ7U8NTTD3W0C | P16: UI2SB4WP5U | S16: Equity Paybill Account | T16: SasaPay | U16: ThirdPartyBillPayment | V16: 247247 | W16: Equity Paybill Account | X16: Safaricom | Y16: W13843926 | Z16: 116700 | AA16: 46267.406 | AB16: Not Reversed | AD16: SUCCESS | AE16: SP00000 | AF16: Transaction completed successfully
A17: 756756 | B17: 254795093834 | C17: Victor Omondi | D17: Limited Personal Wallet | F17: Transaction Out | G17: 20 | H17: 0 | I17: 0 | J17: 0 | K17: 0 | L17: 0 | M17: 56 | N17: 46267 | O17: SWEJ7U8NWDUY7OU | P17: UI2SB4WQSQ | S17: Pharmaplus Pharmaceuticals_23 | T17: SasaPay | U17: ThirdPartyBillPayment | V17: 4131085 | W17: Pharmaplus Pharmaceuticals_23 | X17: Safaricom | Y17: W13844095 | Z17: n | AA17: 46267.417 | AB17: Not Reversed | AC17: user_app | AD17: SUCCESS | AE17: SP00000 | AF17: Transaction completed successfully
B18: 458445 | C18: BUYSIMU TECHNOLOGIES LIMITED | D18: Till | E18: Organisation | F18: Transaction Out | G18: 22500 | H18: 0 | I18: 87 | J18: 0 | K18: 1 | L18: 0 | M18: 810922.69 | N18: 46267 | O18: SWEJ7U8NW2RW18S | P18: UI2SB4WMJ0 | S18: LOOP BIZ | T18: SasaPay | U18: ThirdPartyBillPayment | V18: 714888 | W18: LOOP BIZ | X18: Safaricom | Y18: W13844344 | Z18: 18738 | AA18: 46267.427 | AB18: Not Reversed | AC18: api | AD18: SUCCESS | AE18: SP00000 | AF18: Transaction completed successfully
A19: 756756 | B19: 254711592002 | C19: Leonard Gitachu | D19: Limited Personal Wallet | F19: Transaction Out | G19: 1500 | H19: 0 | I19: 10 | J19: 0 | K19: 0 | L19: 0 | M19: 11723 | N19: 46267 | O19: SWEJ7U8NW7XCO14 | P19: UI2SB4WK05 | T19: SasaPay | U19: ThirdPartyBillPayment | V19: 5555550 | X19: Safaricom | Y19: W13844375 | Z19: W13844375 | AA19: 46267.429 | AB19: Not Reversed | AC19: user_app | AD19: SUCCESS | AE19: SP00000 | AF19: Transaction completed successfully
B20: 225544 | C20: Absolute Shop | D20: AgencyShop | E20: Wholesale and Retail trade | F20: Transaction Out | G20: 10 | H20: 0 | I20: 0 | J20: 0 | K20: 0 | L20: 0 | M20: 148.16 | N20: 46267 | O20: SWEJ7U8NX2VAZD4 | Q20: RVHGT0KB61V | T20: SasaPay | U20: ThirdPartyBillPayment | V20: 479068 | X20: Safaricom | Y20: W13844597 | Z20: 301210 | AA20: 46267.442 | AB20: Reversed | AD20: FAILED | AE20: SP01002 | AF20: 1:The balance is insufficient for the transaction.
B21: 1552342 | C21: Monica jematia chemuna | D21: Limited Personal Wallet | F21: Transaction Out | G21: 15900 | H21: 0 | I21: 82 | J21: 18 | K21: 0 | L21: 0 | M21: 50 | N21: 46267 | O21: SWEJ7U8NYA5FJ4W | P21: UI2SB4WK79 | S21: Equity Paybill Account | T21: SasaPay | U21: ThirdPartyBillPayment | V21: 1552342 | W21: Equity Paybill Account | X21: Safaricom | Y21: W13844676 | Z21: N5H4LRSL | AA21: 46267.446 | AB21: Not Reversed | AD21: SUCCESS | AE21: SP00000 | AF21: Transaction completed successfully
A22: 455555 | B22: 334660 | C22: GRACE MBERA | D22: Limited Personal Wallet | F22: Transaction Out | G22: 2400 | H22: 0 | I22: 34 | J22: 0 | K22: 0 | L22: 0 | M22: 3509 | N22: 46267 | O22: SWEJ7U8NYY8KFWM | P22: UI2SN2T4NH | S22: CIC Money Market Fund | T22: SasaPay | U22: ThirdPartyBillPayment | V22: 600118 | W22: CIC Money Market Fund | X22: Safaricom | Y22: W13844792 | Z22: 182779 | AA22: 46267.456 | AB22: Not Reversed | AC22: user_app | AD22: SUCCESS | AE22: SP00000 | AF22: Transaction completed successfully
B23: 1326697 | C23: Kenneth Njoroge Nganga | D23: Limited Personal Wallet | F23: Transaction Out | G23: 60 | H23: 0 | I23: 0 | J23: 0 | K23: 0 | L23: 0 | M23: 13461 | N23: 46267 | O23: SWEJ7U8NY0SR33K | P23: UI2SB4WMW0 | T23: SasaPay | U23: ThirdPartyBillPayment | V23: 1326697 | X23: Safaricom | Y23: W13844799 | Z23: I0VE48YU | AA23: 46267.456 | AB23: Not Reversed | AD23: SUCCESS | AE23: SP00000 | AF23: Transaction completed successfully
B24: 276585 | C24: HEAVENLY WINGS FOODS LIMITED | D24: Till | E24: Organisation | F24: Transaction Out | G24: 9450 | H24: 0 | I24: 15 | J24: 0 | K24: 1 | L24: 0 | M24: 23525.36 | N24: 46267 | O24: SWEJ7U8NY2FVS9C | P24: UI2SB4WPQ8 | T24: SasaPay | U24: ThirdPartyBillPayment | V24: 3586381 | X24: Safaricom | Y24: W13844809 | Z24: Dry Goods purchase | AA24: 46267.457 | AB24: Not Reversed | AD24: SUCCESS | AE24: SP00000 | AF24: Transaction completed successfully
B25: 276585 | C25: HEAVENLY WINGS FOODS LIMITED | D25: Till | E25: Organisation | F25: Transaction Out | G25: 8120 | H25: 0 | I25: 15 | J25: 0 | K25: 1 | L25: 0 | M25: 13769.36 | N25: 46267 | O25: SWEJ7U8N0ZQK5EZ | P25: UI2SB4WSPF | T25: SasaPay | U25: ThirdPartyBillPayment | V25: 5775191 | X25: Safaricom | Y25: W13844860 | Z25: Purchase of sausages, bacon | AA25: 46267.458 | AB25: Not Reversed | AD25: SUCCESS | AE25: SP00000 | AF25: Transaction completed successfully
B26: 458445 | C26: BUYSIMU TECHNOLOGIES LIMITED | D26: Till | E26: Organisation | F26: Transaction Out | G26: 20000 | H26: 0 | I26: 82 | J26: 0 | K26: 1 | L26: 0 | M26: 761775.69 | N26: 46267 | O26: SWEJ7U8N0ZU2KWQ | P26: UI2SB4WPR0 | S26: Africastalking Ltd | T26: SasaPay | U26: ThirdPartyBillPayment | V26: 525900 | W26: Africastalking Ltd | X26: Safaricom | Y26: W13844863 | Z26: ASFASMS | AA26: 46267.458 | AB26: Not Reversed | AD26: SUCCESS | AE26: SP00000 | AF26: Transaction completed successfully
B27: 276585 | C27: HEAVENLY WINGS FOODS LIMITED | D27: Till | E27: Organisation | F27: Transaction Out | G27: 650 | H27: 0 | I27: 10 | J27: 0 | K27: 1 | L27: 0 | M27: 13108.36 | N27: 46267 | O27: SWEJ7U8N02X9DQO | P27: UI2SB4WMXS | T27: SasaPay | U27: ThirdPartyBillPayment | V27: 331711 | X27: Safaricom | Y27: W13844880 | Z27: Purchase of packaging bags | AA27: 46267.46 | AB27: Not Reversed | AD27: SUCCESS | AE27: SP00000 | AF27: Transaction completed successfully
A28: 756756 | B28: 358222 | C28: Dunwell - TUMAINI SHOP | D28: Matatu | F28: Transaction Out | G28: 3720 | H28: 0 | I28: 49 | J28: 0 | K28: 0 | L28: 0 | M28: 850.22 | N28: 46267 | O28: SWEJ7U8N1UWPKWF | P28: UI2SB4WRFJ | S28: HAWKERS PRIDE ENTERPRISES LIMITED | T28: SasaPay | U28: ThirdPartyBillPayment | V28: 4107991 | W28: HAWKERS PRIDE ENTERPRISES LIMITED | X28: Safaricom | Y28: W13845063 | Z28: 3 | AA28: 46267.472 | AB28: Not Reversed | AC28: user_app | AD28: SUCCESS | AE28: SP00000 | AF28: Transaction completed successfully
B29: 1003020 | C29: Stephen - Viewtech Afya | D29: Till-CustomerOption | F29: Transaction Out | G29: 3860 | H29: 0 | I29: 49 | J29: 38.6 | K29: 0 | L29: 0 | M29: 41918.93 | N29: 46267 | O29: SWEJ7U8N2JVF3NG | P29: UI2SB4WSYZ | S29: GURU NANAK RAMGARHIA SIKH HOSPITAL | T29: SasaPay | U29: ThirdPartyBillPayment | V29: 1003020 | W29: GURU NANAK RAMGARHIA SIKH HOSPITAL | X29: Safaricom | Y29: W13845310 | Z29: MF166661 | AA29: 46267.482 | AB29: Not Reversed | AD29: SUCCESS | AE29: SP00000 | AF29: Transaction completed successfully
A30: 756756 | B30: 254708619405 | C30: Dennis Mwangi | D30: Wallet-Personal | F30: Transaction Out | G30: 150 | H30: 0 | I30: 10 | J30: 0 | K30: 0 | L30: 0 | M30: 1272 | N30: 46267 | O30: SWEJ7U8N2NDOM1Y | P30: UI2SB4WN6Z | T30: SasaPay | U30: ThirdPartyBillPayment | V30: 9981521 | X30: Safaricom | Y30: W13845341 | Z30: W13845341 | AA30: 46267.483 | AB30: Not Reversed | AC30: user_app | AD30: SUCCESS | AE30: SP00000 | AF30: Transaction completed successfully
A31: 756756 | B31: 205756 | C31: Erick - erick | D31: Biashara Wallet | F31: Transaction Out | G31: 100 | H31: 0 | I31: 0 | J31: 0 | K31: 0 | L31: 0 | M31: 364.59 | N31: 46267 | O31: SWEJ7U8N2YBIDU7 | P31: UI2SB4WN9Q | T31: SasaPay | U31: ThirdPartyBillPayment | V31: 5047675 | X31: Safaricom | Y31: W13845433 | Z31: W13845433 | AA31: 46267.488 | AB31: Not Reversed | AC31: user_app | AD31: SUCCESS | AE31: SP00000 | AF31: Transaction completed successfully
B32: 520420 | C32: Cynthia Tiany | D32: Limited Personal Wallet | F32: Transaction Out | G32: 49350 | H32: 0 | I32: 15 | J32: 15 | K32: 0 | L32: 0 | M32: 90985.224 | N32: 46267 | O32: SWEJ7U8N2YWPBE6 | P32: UI2SB4WTY4 | T32: SasaPay | U32: ThirdPartyBillPayment | V32: 520420 | X32: Safaricom | Y32: W13845440 | Z32: JL1H1FGF | AA32: 46267.488 | AB32: Not Reversed | AD32: SUCCESS | AE32: SP00000 | AF32: Transaction completed successfully
B33: 118594 | C33: Petty Cash | D33: Till | E33: Financial and Insurance activities | F33: Transaction Out | G33: 960 | H33: 0 | I33: 20 | J33: 0 | K33: 1 | L33: 0 | M33: 42846.58 | N33: 46267 | O33: SWEJ7U8N2ZYXT3W | P33: UI2SB4WT29 | S33: Lipa na KCB | T33: SasaPay | U33: ThirdPartyBillPayment | V33: 522533 | W33: Lipa na KCB | X33: Safaricom | Y33: W13845447 | Z33: 7881524 | AA33: 46267.489 | AB33: Not Reversed | AD33: SUCCESS | AE33: SP00000 | AF33: Transaction completed successfully
B34: 1606341 | C34: Beldina - Beldina | D34: Limited Personal Wallet | F34: Transaction Out | G34: 675 | H34: 0 | I34: 10 | J34: 2 | K34: 0 | L34: 0 | M34: 312 | N34: 46267 | O34: SWEJ7U8N27CT8EP | P34: UI2SB4WQ67 | T34: SasaPay | U34: ThirdPartyBillPayment | V34: 1606341 | X34: Safaricom | Y34: W13845498 | Z34: NRNYDA0Q | AA34: 46267.492 | AB34: Not Reversed | AD34: SUCCESS | AE34: SP00000 | AF34: Transaction completed successfully
A35: 756756 | B35: 254742451519 | C35: Bethwel Ogot | D35: Limited Personal Wallet | F35: Transaction Out | G35: 18000 | H35: 0 | I35: 80 | J35: 0 | K35: 0 | L35: 0 | M35: 49363 | N35: 46267 | O35: SWEJ7U8N5V19CC9 | P35: UI2SB4WU5B | S35: Co | T35: SasaPay | U35: ThirdPartyBillPayment | V35: 400200 | W35: Co | X35: Safaricom | Y35: W13845825 | Z35: 01116560460900 | AA35: 46267.505 | AB35: Not Reversed | AC35: user_app | AD35: SUCCESS | AE35: SP00000 | AF35: Transaction completed successfully
A36: 756756 | B36: 254742451519 | C36: Bethwel Ogot | D36: Limited Personal Wallet | F36: Transaction Out | G36: 25000 | H36: 0 | I36: 87 | J36: 0 | K36: 0 | L36: 0 | M36: 21756 | N36: 46267 | O36: SWEJ7U8N51OWDOF | P36: UI2SB4WU5V | S36: Stima SACCO Society ltd | T36: SasaPay | U36: ThirdPartyBillPayment | V36: 823244 | W36: Stima SACCO Society ltd | X36: Safaricom | Y36: W13845914 | Z36: 801047054501 | AA36: 46267.507 | AB36: Not Reversed | AC36: user_app | AD36: SUCCESS | AE36: SP00000 | AF36: Transaction completed successfully
A37: 756756 | B37: 1116456 | C37: SIMON - SIMON KATUMO MUTINDA | D37: Biashara Wallet | F37: Transaction Out | G37: 500 | H37: 0 | I37: 10 | J37: 0 | K37: 0 | L37: 0 | M37: 61160.02 | N37: 46267 | O37: SWEJ7U8N6EVPUST | P37: UI2SB4WQDX | T37: SasaPay | U37: ThirdPartyBillPayment | V37: 4106574 | X37: Safaricom | Y37: W13846034 | Z37: W13846034 | AA37: 46267.512 | AB37: Not Reversed | AC37: user_app | AD37: SUCCESS | AE37: SP00000 | AF37: Transaction completed successfully
B38: 110311 | C38: Bag Ware Limited | D38: PayBill-CustomerOption | E38: Organisation | F38: Transaction Out | G38: 20000 | H38: 0 | I38: 80 | J38: 0 | K38: 1 | L38: 0 | M38: 828713 | N38: 46267 | O38: SWEJ7U8N6LMWRA1 | P38: UI2SB4WNKB | S38: Guaranty Trust Bank Ltd | T38: SasaPay | U38: ThirdPartyBillPayment | V38: 910200 | W38: Guaranty Trust Bank Ltd | X38: Safaricom | Y38: W13846110 | Z38: 2210003653 | AA38: 46267.515 | AB38: Not Reversed | AD38: SUCCESS | AE38: SP00000 | AF38: Transaction completed successfully
B39: 453498 | C39: Alex ian Madara | D39: Limited Personal Wallet | F39: Transaction Out | G39: 300 | H39: 0 | I39: 10 | J39: 2 | K39: 0 | L39: 0 | M39: 10003 | N39: 46267 | O39: SWEJ7U8N6R2KDGU | P39: UI2SB4WVP2 | T39: SasaPay | U39: ThirdPartyBillPayment | V39: 453498 | X39: Safaricom | Y39: W13846166 | Z39: C7K5CXRC | AA39: 46267.518 | AB39: Not Reversed | AD39: SUCCESS | AE39: SP00000 | AF39: Transaction completed successfully
B40: 9235 | C40: Wimssy | D40: Till | E40: Organisation | F40: Transaction Out | G40: 8060 | H40: 0 | I40: 63 | J40: 0 | K40: 1 | L40: 0 | M40: 360317 | N40: 46267 | O40: SWEJ7U8N6TSA69H | P40: UI2SB4WVPJ | S40: GDC SACCO SOCIETY LTD | T40: SasaPay | U40: ThirdPartyBillPayment | V40: 639498 | W40: GDC SACCO SOCIETY LTD | X40: Safaricom | Y40: W13846185 | Z40: HtAZvGWUlerLT6OI40kr | AA40: 46267.519 | AB40: Not Reversed | AC40: api | AD40: SUCCESS | AE40: SP00000 | AF40: Transaction completed successfully
B41: 9235 | C41: Wimssy | D41: Till | E41: Organisation | F41: Transaction Out | G41: 6290 | H41: 0 | I41: 57 | J41: 0 | K41: 1 | L41: 0 | M41: 353969 | N41: 46267 | O41: SWEJ7U8N6TSEIWI | P41: UI2SB4WUA6 | S41: GDC SACCO SOCIETY LTD | T41: SasaPay | U41: ThirdPartyBillPayment | V41: 639498 | W41: GDC SACCO SOCIETY LTD | X41: Safaricom | Y41: W13846184 | Z41: Sv2NxYr0cf9zwrcrcIxh | AA41: 46267.519 | AB41: Not Reversed | AC41: api | AD41: SUCCESS | AE41: SP00000 | AF41: Transaction completed successfully
B42: 9235 | C42: Wimssy | D42: Till | E42: Organisation | F42: Transaction Out | G42: 82390 | H42: 0 | I42: 136 | J42: 0 | K42: 1 | L42: 0 | M42: 262223.8 | N42: 46267 | O42: SWEJ7U8N6TSR19K | P42: UI2SB4WWVH | S42: GDC SACCO SOCIETY LTD | T42: SasaPay | U42: ThirdPartyBillPayment | V42: 639498 | W42: GDC SACCO SOCIETY LTD | X42: Safaricom | Y42: W13846187 | Z42: VWDgWMUYuIvypd6DXdl1 | AA42: 46267.519 | AB42: Not Reversed | AC42: api | AD42: SUCCESS | AE42: SP00000 | AF42: Transaction completed successfully
B43: 9235 | C43: Wimssy | D43: Till | E43: Organisation | F43: Transaction Out | G43: 37690 | H43: 0 | I43: 125 | J43: 0 | K43: 1 | L43: 0 | M43: 224407.8 | N43: 46267 | O43: SWEJ7U8N6TSVOOP | P43: UI2SB4WWVI | S43: GDC SACCO SOCIETY LTD | T43: SasaPay | U43: ThirdPartyBillPayment | V43: 639498 | W43: GDC SACCO SOCIETY LTD | X43: Safaricom | Y43: W13846189 | Z43: OQaJazMHW4yAGHd61wIa | AA43: 46267.519 | AB43: Not Reversed | AC43: api | AD43: SUCCESS | AE43: SP00000 | AF43: Transaction completed successfully
B44: 9235 | C44: Wimssy | D44: Till | E44: Organisation | F44: Transaction Out | G44: 13927 | H44: 0 | I44: 72 | J44: 0 | K44: 1 | L44: 0 | M44: 210407.8 | N44: 46267 | O44: SWEJ7U8N6TTD9GG | P44: UI2SB4WVPL | S44: GDC SACCO SOCIETY LTD | T44: SasaPay | U44: ThirdPartyBillPayment | V44: 639498 | W44: GDC SACCO SOCIETY LTD | X44: Safaricom | Y44: W13846190 | Z44: gFf7DYaKyKI8oYukw1Hd | AA44: 46267.519 | AB44: Not Reversed | AC44: api | AD44: SUCCESS | AE44: SP00000 | AF44: Transaction completed successfully
B45: 9235 | C45: Wimssy | D45: Till | E45: Organisation | F45: Transaction Out | G45: 1765 | H45: 0 | I45: 35 | J45: 0 | K45: 1 | L45: 0 | M45: 208606.8 | N45: 46267 | O45: SWEJ7U8N6TTWH4M | P45: UI2SB4WWVJ | S45: GDC SACCO SOCIETY LTD | T45: SasaPay | U45: ThirdPartyBillPayment | V45: 639498 | W45: GDC SACCO SOCIETY LTD | X45: Safaricom | Y45: W13846188 | Z45: ejaa1UcYSqsPKEBROinM | AA45: 46267.519 | AB45: Not Reversed | AC45: api | AD45: SUCCESS | AE45: SP00000 | AF45: Transaction completed successfully
B46: 9235 | C46: Wimssy | D46: Till | E46: Organisation | F46: Transaction Out | G46: 13001 | H46: 0 | I46: 72 | J46: 0 | K46: 1 | L46: 0 | M46: 195532.8 | N46: 46267 | O46: SWEJ7U8N6TTZMHA | P46: UI2SB4WVPM | S46: GDC SACCO SOCIETY LTD | T46: SasaPay | U46: ThirdPartyBillPayment | V46: 639498 | W46: GDC SACCO SOCIETY LTD | X46: Safaricom | Y46: W13846192 | Z46: GgRwl2pVCk6GNtmoEZyX | AA46: 46267.519 | AB46: Not Reversed | AC46: api | AD46: SUCCESS | AE46: SP00000 | AF46: Transaction completed successfully
B47: 9235 | C47: Wimssy | D47: Till | E47: Organisation | F47: Transaction Out | G47: 7408 | H47: 0 | I47: 57 | J47: 0 | K47: 1 | L47: 0 | M47: 188066.8 | N47: 46267 | O47: SWEJ7U8N6TT24GB | P47: UI2SB4WS0S | S47: GDC SACCO SOCIETY LTD | T47: SasaPay | U47: ThirdPartyBillPayment | V47: 639498 | W47: GDC SACCO SOCIETY LTD | X47: Safaricom | Y47: W13846191 | Z47: Bov4xnQYTVKJpZ9cI0lG | AA47: 46267.519 | AB47: Not Reversed | AC47: api | AD47: SUCCESS | AE47: SP00000 | AF47: Transaction completed successfully
B48: 9235 | C48: Wimssy | D48: Till | E48: Organisation | F48: Transaction Out | G48: 6935 | H48: 0 | I48: 57 | J48: 0 | K48: 1 | L48: 0 | M48: 181073.8 | N48: 46267 | O48: SWEJ7U8N6TT55R3 | P48: UI2SB4WVPP | S48: TAI SACCO SOCIETY LIMITED | T48: SasaPay | U48: ThirdPartyBillPayment | V48: 644700 | W48: TAI SACCO SOCIETY LIMITED | X48: Safaricom | Y48: W13846193 | Z48: E6BrJP3lKWBF1dLtC8Lf | AA48: 46267.519 | AB48: Not Reversed | AC48: api | AD48: SUCCESS | AE48: SP00000 | AF48: Transaction completed successfully
B49: 9235 | C49: Wimssy | D49: Till | E49: Organisation | F49: Transaction Out | G49: 6784 | H49: 0 | I49: 57 | J49: 0 | K49: 1 | L49: 0 | M49: 174231.8 | N49: 46267 | O49: SWEJ7U8N6TT9QK3 | P49: UI2SB4WTFG | S49: GDC SACCO SOCIETY LTD | T49: SasaPay | U49: ThirdPartyBillPayment | V49: 639498 | W49: GDC SACCO SOCIETY LTD | X49: Safaricom | Y49: W13846195 | Z49: H0b5UCAKY0DjhQoLS5KT | AA49: 46267.519 | AB49: Not Reversed | AC49: api | AD49: SUCCESS | AE49: SP00000 | AF49: Transaction completed successfully
B50: 9235 | C50: Wimssy | D50: Till | E50: Organisation | F50: Transaction Out | G50: 7503 | H50: 0 | I50: 63 | J50: 0 | K50: 1 | L50: 0 | M50: 166664.8 | N50: 46267 | O50: SWEJ7U8N6TUCYEA | P50: UI2SB4WTFF | S50: GDC SACCO SOCIETY LTD | T50: SasaPay | U50: ThirdPartyBillPayment | V50: 639498 | W50: GDC SACCO SOCIETY LTD | X50: Safaricom | Y50: W13846194 | Z50: aYPl6RiHfXN2vruqgLUT | AA50: 46267.519 | AB50: Not Reversed | AC50: api | AD50: SUCCESS | AE50: SP00000 | AF50: Transaction completed successfully
B51: 9235 | C51: Wimssy | D51: Till | E51: Organisation | F51: Transaction Out | G51: 7076 | H51: 0 | I51: 57 | J51: 0 | K51: 1 | L51: 0 | M51: 159530.8 | N51: 46267 | O51: SWEJ7U8N6TUF9BL | P51: UI2SB4WVPN | S51: GDC SACCO SOCIETY LTD | T51: SasaPay | U51: ThirdPartyBillPayment | V51: 639498 | W51: GDC SACCO SOCIETY LTD | X51: Safaricom | Y51: W13846197 | Z51: ynZSqMJlSM3O6dQQ9xxi | AA51: 46267.519 | AB51: Not Reversed | AC51: api | AD51: SUCCESS | AE51: SP00000 | AF51: Transaction completed successfully
... B60: 9235 | C60: Wimssy | D60: Till | E60: Organisation | F60: Transaction Out | G60: 2763 | H60: 0 | I60: 40 | J60: 0 | K60: 1 | L60: 0 | M60: 31245.6 | N60: 46267 | O60: SWEJ7U8N6TWVFDV | P60: UI2SB4WOXE | S60: GDC SACCO SOCIETY LTD | T60: SasaPay | U60: ThirdPartyBillPayment | V60: 639498 | W60: GDC SACCO SOCIETY LTD | X60: Safaricom | Y60: W13846212 | Z60: Ay8wdAWUfcAIvILjmR7r | AA60: 46267.519 | AB60: Not Reversed | AC60: api | AD60: SUCCESS | AE60: SP00000 | AF60: Transaction completed successfully
B61: 1391815 | C61: MORINE ONGERI | D61: Limited Personal Wallet | F61: Transaction Out | G61: 15300 | H61: 0 | I61: 15 | J61: 18 | K61: 0 | L61: 0 | M61: 49549.18 | N61: 46267 | O61: SWEJ7U8N61QWISS | P61: UI2SB4WQIS | T61: SasaPay | U61: ThirdPartyBillPayment | V61: 1391815 | X61: Safaricom | Y61: W13846311 | Z61: GAWOCJ4B | AA61: 46267.522 | AB61: Not Reversed | AD61: SUCCESS | AE61: SP00000 | AF61: Transaction completed successfully
B62: 1483 | C62: VLC-PROPERTY PETTY CASH | D62: Till | E62: Organisation | F62: Transaction Out | G62: 5920 | H62: 0 | I62: 15 | J62: 0 | K62: 1 | L62: 0 | M62: 19695.578 | N62: 46267 | O62: SWEJ7U8N625YWZZ | P62: UI2SB4WOZA | T62: SasaPay | U62: ThirdPartyBillPayment | V62: 5228737 | X62: Safaricom | Y62: W13846323 | Z62: Purchase of construction materials - Richland Pointe | AA62: 46267.523 | AB62: Not Reversed | AD62: SUCCESS | AE62: SP00000 | AF62: Transaction completed successfully
B63: 1662340 | C63: Alex - Alex enterprise | D63: Limited Personal Wallet | F63: Transaction Out | G63: 100 | H63: 0 | I63: 0 | J63: 0 | K63: 0 | L63: 0 | M63: 7 | N63: 46267 | O63: SWEJ7U8N77MJ9AF | P63: UI2SB4WTP5 | S63: Equity Paybill Account | T63: SasaPay | U63: ThirdPartyBillPayment | V63: 1662340 | W63: Equity Paybill Account | X63: Safaricom | Y63: W13846707 | Z63: AWR9BCPJ | AA63: 46267.54 | AB63: Not Reversed | AD63: SUCCESS | AE63: SP00000 | AF63: Transaction completed successfully
B64: 36302 | C64: Genem international Holdings Limited | D64: Till | E64: Organisation | F64: Transaction Out | G64: 2000 | H64: 0 | I64: 10 | J64: 0 | K64: 1 | L64: 0 | M64: 323601 | N64: 46267 | O64: SWEJ7U8N78O2BJW | P64: UI2SB4WX5P | T64: SasaPay | U64: ThirdPartyBillPayment | V64: 4961328 | X64: Safaricom | Y64: W13846714 | Z64: nyeri van fuel | AA64: 46267.54 | AB64: Not Reversed | AD64: SUCCESS | AE64: SP00000 | AF64: Transaction completed successfully
B65: 36302 | C65: Genem international Holdings Limited | D65: Till | E65: Organisation | F65: Transaction Out | G65: 4000 | H65: 0 | I65: 49 | J65: 0 | K65: 1 | L65: 0 | M65: 319551 | N65: 46267 | O65: SWEJ7U8N97PS7WK | P65: UI2SB4WTQ8 | S65: Co | T65: SasaPay | U65: ThirdPartyBillPayment | V65: 400200 | W65: Co | X65: Safaricom | Y65: W13846766 | Z65: 797900 | AA65: 46267.542 | AB65: Not Reversed | AD65: SUCCESS | AE65: SP00000 | AF65: Transaction completed successfully
B66: 413570 | C66: Sheldon Onzere | D66: Limited Personal Wallet | F66: Transaction Out | G66: 65 | H66: 0 | I66: 0 | J66: 0 | K66: 0 | L66: 0 | M66: 121 | N66: 46267 | O66: SWEJ7U8OAS8PSI1 | P66: UI2SB4WXB3 | T66: SasaPay | U66: ThirdPartyBillPayment | V66: 413570 | X66: Safaricom | Y66: W13847021 | Z66: ZYV2VOLH | AA66: 46267.551 | AB66: Not Reversed | AD66: SUCCESS | AE66: SP00000 | AF66: Transaction completed successfully
B67: 110311 | C67: Bag Ware Limited | D67: PayBill-CustomerOption | E67: Organisation | F67: Transaction Out | G67: 17688 | H67: 0 | I67: 15 | J67: 0 | K67: 1 | L67: 0 | M67: 627712 | N67: 46267 | O67: SWEJ7U8OBDLNR96 | P67: UI2SB4WW8H | T67: SasaPay | U67: ThirdPartyBillPayment | V67: 9481425 | X67: Safaricom | Y67: W13847227 | Z67: GENERAL SUPPLIES-W/SHOP SHOPPING | AA67: 46267.56 | AB67: Not Reversed | AD67: SUCCESS | AE67: SP00000 | AF67: Transaction completed successfully
A68: 756756 | B68: 254757455384 | C68: John Wasonga | D68: Limited Personal Wallet | F68: Transaction Out | G68: 450 | H68: 0 | I68: 10 | J68: 0 | K68: 0 | L68: 0 | M68: 23 | N68: 46267 | O68: SWEJ7U8OBNLYLPT | P68: UI2SB4WYS1 | S68: LOOP C2B | T68: SasaPay | U68: ThirdPartyBillPayment | V68: 714777 | W68: LOOP C2B | X68: Safaricom | Y68: W13847347 | Z68: 0757455384 | AA68: 46267.564 | AB68: Not Reversed | AC68: user_app | AD68: SUCCESS | AE68: SP00000 | AF68: Transaction completed successfully
A69: 756756 | B69: 164621 | C69: Faith - Tasty treats | D69: Biashara Wallet | F69: Transaction Out | G69: 80 | H69: 0 | I69: 0 | J69: 0 | K69: 0 | L69: 0 | M69: 7235.94 | N69: 46267 | O69: SWEJ7U8OBVITCVQ | P69: UI2SB4WYTQ | T69: SasaPay | U69: ThirdPartyBillPayment | V69: 3510637 | X69: Safaricom | Y69: W13847411 | Z69: W13847411 | AA69: 46267.567 | AB69: Not Reversed | AC69: user_app | AD69: SUCCESS | AE69: SP00000 | AF69: Transaction completed successfully
A70: 756756 | B70: 164621 | C70: Faith - Tasty treats | D70: Biashara Wallet | F70: Transaction Out | G70: 875 | H70: 0 | I70: 10 | J70: 0 | K70: 0 | L70: 0 | M70: 6350.94 | N70: 46267 | O70: SWEJ7U8OBYIG965 | P70: UI2SB4X3BX | T70: SasaPay | U70: ThirdPartyBillPayment | V70: 9362497 | X70: Safaricom | Y70: W13847439 | Z70: W13847439 | AA70: 46267.569 | AB70: Not Reversed | AC70: user_app | AD70: SUCCESS | AE70: SP00000 | AF70: Transaction completed successfully
B71: 379411 | C71: XWIFT | D71: Till | F71: Transaction Out | G71: 38999 | H71: 0 | I71: 125 | J71: 0 | K71: 1 | L71: 0 | M71: 176460.87 | N71: 46267 | O71: SWEJ7U8OE23VSQ4 | P71: UI2SB4X23C | S71: Co | T71: SasaPay | U71: ThirdPartyBillPayment | V71: 400200 | W71: Co | X71: Safaricom | Y71: W13847738 | Z71: f538e064-b42b-4f5b-bf17-5230e9543bcb | AA71: 46267.588 | AB71: Not Reversed | AC71: api | AD71: SUCCESS | AE71: SP00000 | AF71: Transaction completed successfully
B72: 469005 | C72: German Experts- Petty cash | D72: Till | E72: Organisation | F72: Transaction Out | G72: 2176 | H72: 0 | I72: 10 | J72: 0 | K72: 1 | L72: 0 | M72: 3283.2 | N72: 46267 | O72: SWEJ7U8OE4IFA0V | P72: UI2SB4WZ35 | T72: SasaPay | U72: ThirdPartyBillPayment | V72: 4699876 | X72: Safaricom | Y72: W13847742 | Z72: W13847742 | AA72: 46267.589 | AB72: Not Reversed | AC72: merchant_portal | AD72: SUCCESS | AE72: SP00000 | AF72: Transaction completed successfully
B73: 1003020 | C73: Stephen - Viewtech Afya | D73: Till-CustomerOption | F73: Transaction Out | G73: 1000 | H73: 0 | I73: 20 | J73: 10 | K73: 0 | L73: 0 | M73: 40888.93 | N73: 46267 | O73: SWEJ7U8OE9T6GNB | P73: UI2SB4WXT7 | S73: GURU NANAK RAMGARHIA SIKH HOSPITAL | T73: SasaPay | U73: ThirdPartyBillPayment | V73: 1003020 | W73: GURU NANAK RAMGARHIA SIKH HOSPITAL | X73: Safaricom | Y73: W13847792 | Z73: MF750834 | AA73: 46267.591 | AB73: Not Reversed | AD73: SUCCESS | AE73: SP00000 | AF73: Transaction completed successfully
B74: 80417 | C74: KBQ 188C | D74: Matatu | E74: Organisation | F74: Transaction Out | G74: 3900 | H74: 0 | I74: 15 | J74: 0 | K74: 1 | L74: 0 | M74: 3013.814 | N74: 46267 | O74: SWEJ7U8OFH7I1GQ | P74: UI2SB4WWNG | T74: SasaPay | U74: ThirdPartyBillPayment | V74: 9246253 | X74: Safaricom | Y74: W13847836 | Z74: Fuel | AA74: 46267.594 | AB74: Not Reversed | AD74: SUCCESS | AE74: SP00000 | AF74: Transaction completed successfully
A75: 756756 | B75: 254748897486 | C75: Moses Otieno | D75: Limited Personal Wallet | F75: Transaction Out | G75: 100 | H75: 0 | I75: 0 | J75: 0 | K75: 0 | L75: 0 | M75: 100 | N75: 46267 | O75: SWEJ7U8OFOYLWNK | P75: UI2SB4X3NJ | T75: SasaPay | U75: ThirdPartyBillPayment | V75: 3253086 | X75: Safaricom | Y75: W13847903 | Z75: W13847903 | AA75: 46267.597 | AB75: Not Reversed | AC75: user_app | AD75: SUCCESS | AE75: SP00000 | AF75: Transaction completed successfully
A76: 455555 | B76: 314127 | C76: edwin kiptoo | D76: Limited Personal Wallet | F76: Transaction Out | G76: 170 | H76: 0 | I76: 10 | J76: 0 | K76: 0 | L76: 0 | M76: 3868 | N76: 46267 | O76: SWEJ7U8OF0KGXRT | P76: UI2SN2TE19 | S76: ONFON MEDIA 1. | T76: SasaPay | U76: ThirdPartyBillPayment | V76: 622645 | W76: ONFON MEDIA 1. | X76: Safaricom | Y76: W13847967 | Z76: 30348505 | AA76: 46267.602 | AB76: Not Reversed | AC76: user_app | AD76: SUCCESS | AE76: SP00000 | AF76: Transaction completed successfully
B77: 458445 | C77: BUYSIMU TECHNOLOGIES LIMITED | D77: Till | E77: Organisation | F77: Transaction Out | G77: 87000 | H77: 0 | I77: 136 | J77: 0 | K77: 1 | L77: 0 | M77: 308219.69 | N77: 46267 | O77: SWEJ7U8OF27J3PQ | P77: UI2SB4X3QM | S77: Absa Bank Kenya PLC | T77: SasaPay | U77: ThirdPartyBillPayment | V77: 303030 | W77: Absa Bank Kenya PLC | X77: Safaricom | Y77: W13847982 | Z77: 18757 | AA77: 46267.603 | AB77: Not Reversed | AC77: api | AD77: SUCCESS | AE77: SP00000 | AF77: Transaction completed successfully
B78: 1592688 | C78: EVERLYN TIANY | D78: Limited Personal Wallet | F78: Transaction Out | G78: 6500 | H78: 0 | I78: 57 | J78: 16 | K78: 0 | L78: 0 | M78: 457 | N78: 46267 | O78: SWEJ7U8OF7D21VV | P78: UI2SB4WWT1 | S78: Family Bank Pesa Pap | T78: SasaPay | U78: ThirdPartyBillPayment | V78: 1592688 | W78: Family Bank Pesa Pap | X78: Safaricom | Y78: W13848025 | Z78: WGGXZA1P | AA78: 46267.605 | AB78: Not Reversed | AD78: SUCCESS | AE78: SP00000 | AF78: Transaction completed successfully
B79: 414936 | C79: John Slater | D79: Limited Personal Wallet | F79: Transaction Out | G79: 10000 | H79: 0 | I79: 15 | J79: 22 | K79: 0 | L79: 0 | M79: 11289 | N79: 46267 | O79: SWEJ7U8OGM0UAAH | P79: UI2SB4X4NK | T79: SasaPay | U79: ThirdPartyBillPayment | V79: 414936 | X79: Safaricom | Y79: W13848119 | Z79: F6FWVFSR | AA79: 46267.612 | AB79: Not Reversed | AD79: SUCCESS | AE79: SP00000 | AF79: Transaction completed successfully
A80: 756756 | B80: 254714726804 | C80: Abed Muroki | D80: Limited Personal Wallet | F80: Transaction Out | G80: 200 | H80: 0 | I80: 10 | J80: 0 | K80: 0 | L80: 0 | M80: 14873 | N80: 46267 | O80: SWEJ7U8OG35ULJE | Q80: RVHGT0KB64M | T80: SasaPay | U80: ThirdPartyBillPayment | V80: 3144083 | X80: Safaricom | Y80: W13848217 | Z80: W13848217 | AA80: 46267.619 | AB80: Reversed | AC80: user_app | AD80: FAILED | AE80: SP01002 | AF80: Receiver party is invalid
A81: 756756 | B81: 254706564824 | C81: Nicholas Omondi | D81: Limited Personal Wallet | F81: Transaction Out | G81: 1170 | H81: 0 | I81: 25 | J81: 0 | K81: 0 | L81: 0 | M81: 52892 | N81: 46267 | O81: SWEJ7U8OHBZXOI4 | P81: UI2SB4X2HV | S81: FORTUNE SACCO C2B | T81: SasaPay | U81: ThirdPartyBillPayment | V81: 852648 | W81: FORTUNE SACCO C2B | X81: Safaricom | Y81: W13848260 | Z81: 66950 | AA81: 46267.622 | AB81: Not Reversed | AC81: user_app | AD81: SUCCESS | AE81: SP00000 | AF81: Transaction completed successfully
B82: 469005 | C82: German Experts- Petty cash | D82: Till | E82: Organisation | F82: Transaction Out | G82: 1500 | H82: 0 | I82: 10 | J82: 0 | K82: 1 | L82: 0 | M82: 1772.2 | N82: 46267 | O82: SWEJ7U8OJTTVY99 | P82: UI2SB4X2M3 | T82: SasaPay | U82: ThirdPartyBillPayment | V82: 4293700 | X82: Safaricom | Y82: W13848498 | Z82: W13848498 | AA82: 46267.632 | AB82: Not Reversed | AC82: merchant_portal | AD82: SUCCESS | AE82: SP00000 | AF82: Transaction completed successfully
A83: 756756 | B83: 70737 | C83: Savings | D83: Personal Sub Wallet | F83: Transaction Out | G83: 500 | H83: 0 | I83: 10 | J83: 0 | K83: 0 | L83: 0 | M83: 4875 | N83: 46267 | O83: SWEJ7U8OJX9UHO4 | P83: UI2SB4X15B | S83: CASH N CARRY ESSENTIALS LIMITED | T83: SasaPay | U83: ThirdPartyBillPayment | V83: 4004309 | W83: CASH N CARRY ESSENTIALS LIMITED | X83: Safaricom | Y83: W13848523 | Z83: C | AA83: 46267.634 | AB83: Not Reversed | AC83: user_app | AD83: SUCCESS | AE83: SP00000 | AF83: Transaction completed successfully
B84: 520420 | C84: Cynthia Tiany | D84: Limited Personal Wallet | F84: Transaction Out | G84: 6000 | H84: 0 | I84: 15 | J84: 16 | K84: 0 | L84: 0 | M84: 82419.224 | N84: 46267 | O84: SWEJ7U8OKIKW4NF | P84: UI2SB4X18B | T84: SasaPay | U84: ThirdPartyBillPayment | V84: 520420 | X84: Safaricom | Y84: W13848706 | Z84: KKWCGKN0 | AA84: 46267.642 | AB84: Not Reversed | AD84: SUCCESS | AE84: SP00000 | AF84: Transaction completed successfully
B85: 706931 | C85: Forward Airtime Limited | D85: Till | E85: Organisation | F85: Transaction Out | G85: 200000 | H85: 0 | I85: 15 | J85: 0 | K85: 1 | L85: 0 | M85: 195628.96 | N85: 46267 | O85: SWEJ7U8OKOR1SKU | P85: UI2SB4X2RH | T85: SasaPay | U85: ThirdPartyBillPayment | V85: 519025 | X85: Safaricom | Y85: W13848751 | Z85: lines | AA85: 46267.645 | AB85: Not Reversed | AD85: SUCCESS | AE85: SP00000 | AF85: Transaction completed successfully
B86: 706931 | C86: Forward Airtime Limited | D86: Till | E86: Organisation | F86: Transaction Out | G86: 100000 | H86: 0 | I86: 15 | J86: 0 | K86: 1 | L86: 0 | M86: 95612.96 | N86: 46267 | O86: SWEJ7U8OKO2NRQ8 | P86: UI2SB4X7QE | T86: SasaPay | U86: ThirdPartyBillPayment | V86: 519025 | X86: Safaricom | Y86: W13848757 | Z86: lines purchase | AA86: 46267.645 | AB86: Not Reversed | AD86: SUCCESS | AE86: SP00000 | AF86: Transaction completed successfully
A87: 756756 | B87: 254795390620 | C87: Caleb Wekesa | D87: Wallet-Personal | F87: Transaction Out | G87: 600 | H87: 0 | I87: 10 | J87: 0 | K87: 0 | L87: 0 | M87: 28619 | N87: 46267 | O87: SWEJ7U8OKO5NYAV | P87: UI2SB4WZQJ | T87: SasaPay | U87: ThirdPartyBillPayment | V87: 5291253 | X87: Safaricom | Y87: W13848758 | Z87: W13848758 | AA87: 46267.645 | AB87: Not Reversed | AC87: user_app | AD87: SUCCESS | AE87: SP00000 | AF87: Transaction completed successfully
A88: 756756 | B88: 254703822239 | C88: Joan Nyamongo | D88: Limited Personal Wallet | F88: Transaction Out | G88: 11500 | H88: 0 | I88: 70 | J88: 0 | K88: 0 | L88: 0 | M88: 10669 | N88: 46267 | O88: SWEJ7U8OKZEDZ1B | P88: UI2SB4X7SP | S88: Stanbic Bank | T88: SasaPay | U88: ThirdPartyBillPayment | V88: 600100 | W88: Stanbic Bank | X88: Safaricom | Y88: W13848841 | Z88: 106547 | AA88: 46267.649 | AB88: Not Reversed | AC88: user_app | AD88: SUCCESS | AE88: SP00000 | AF88: Transaction completed successfully
A89: 756756 | B89: 254746383172 | C89: Esther Nganga | D89: Limited Personal Wallet | F89: Transaction Out | G89: 1500 | H89: 0 | I89: 10 | J89: 0 | K89: 0 | L89: 0 | M89: 15179 | N89: 46267 | O89: SWEJ7U8OK5OJN1I | P89: UI2SB4X2UU | T89: SasaPay | U89: ThirdPartyBillPayment | V89: 4788768 | X89: Safaricom | Y89: W13848918 | Z89: W13848918 | AA89: 46267.652 | AB89: Not Reversed | AC89: user_app | AD89: SUCCESS | AE89: SP00000 | AF89: Transaction completed successfully
A90: 756756 | B90: 254795390620 | C90: Caleb Wekesa | D90: Wallet-Personal | F90: Transaction Out | G90: 12000 | H90: 0 | I90: 15 | J90: 0 | K90: 0 | L90: 0 | M90: 16604 | N90: 46267 | O90: SWEJ7U8OK8UXQJC | P90: UI2SB4X7U7 | T90: SasaPay | U90: ThirdPartyBillPayment | V90: 5291253 | X90: Safaricom | Y90: W13848958 | Z90: W13848958 | AA90: 46267.653 | AB90: Not Reversed | AC90: user_app | AD90: SUCCESS | AE90: SP00000 | AF90: Transaction completed successfully
B91: 520420 | C91: Cynthia Tiany | D91: Limited Personal Wallet | F91: Transaction Out | G91: 13470 | H91: 0 | I91: 72 | J91: 23 | K91: 0 | L91: 0 | M91: 51753.224 | N91: 46267 | O91: SWEJ7U8ON0I5XMR | P91: UI2SB4X9AY | S91: VAGHELA SCHOOL CENTRE LTD | T91: SasaPay | U91: ThirdPartyBillPayment | V91: 520420 | W91: VAGHELA SCHOOL CENTRE LTD | X91: Safaricom | Y91: W13849368 | Z91: X0U0P3C5 | AA91: 46267.667 | AB91: Not Reversed | AD91: SUCCESS | AE91: SP00000 | AF91: Transaction completed successfully
B92: 1371424 | C92: Josphine Oyabi Moraa | D92: Limited Personal Wallet | F92: Transaction Out | G92: 30000 | H92: 0 | I92: 92 | J92: 120 | K92: 0 | L92: 0 | M92: 25581 | N92: 46267 | O92: SWEJ7U8OOBL2HGY | P92: UI2SB4XCCO | S92: Co | T92: SasaPay | U92: ThirdPartyBillPayment | V92: 1371424 | W92: Co | X92: Safaricom | Y92: W13849485 | Z92: A5MV01LK | AA92: 46267.672 | AB92: Not Reversed | AD92: SUCCESS | AE92: SP00000 | AF92: Transaction completed successfully
B93: 110311 | C93: Bag Ware Limited | D93: PayBill-CustomerOption | E93: Organisation | F93: Transaction Out | G93: 46115 | H93: 0 | I93: 136 | J93: 0 | K93: 1 | L93: 0 | M93: 438682 | N93: 46267 | O93: SWEJ7U8OOSNAHPD | P93: UI2SB4XDXI | S93: NCBA BANK KENYA PLC. | T93: SasaPay | U93: ThirdPartyBillPayment | V93: 880100 | W93: NCBA BANK KENYA PLC. | X93: Safaricom | Y93: W13849787 | Z93: PAYKAPUSH | AA93: 46267.679 | AB93: Not Reversed | AD93: SUCCESS | AE93: SP00000 | AF93: Transaction completed successfully
B94: 379411 | C94: XWIFT | D94: Till | F94: Transaction Out | G94: 21500 | H94: 0 | I94: 87 | J94: 0 | K94: 1 | L94: 0 | M94: 1063177.9 | N94: 46267 | O94: SWEJ7U8OOT2MO74 | P94: UI2SB4X85X | S94: Equity Paybill Account | T94: SasaPay | U94: ThirdPartyBillPayment | V94: 247247 | W94: Equity Paybill Account | X94: Safaricom | Y94: W13849800 | Z94: a9317806-3092-4db5-a805-5e66438e7253 | AA94: 46267.68 | AB94: Not Reversed | AC94: api | AD94: SUCCESS | AE94: SP00000 | AF94: Transaction completed successfully
B95: 395390 | C95: Rwama FCS | D95: Till | E95: Organisation | F95: Transaction Out | G95: 6483 | H95: 0 | I95: 57 | J95: 0 | K95: 0 | L95: 0 | M95: 4427902 | N95: 46267 | O95: SWEJ7U8OO3FKO4R | P95: UI2SB4X701 | S95: FORTUNE SACCO C2B | T95: SasaPay | U95: ThirdPartyBillPayment | V95: 852648 | W95: FORTUNE SACCO C2B | X95: Safaricom | Y95: W13849914 | Z95: JEhzu5OwDT7MBmim7Rke | AA95: 46267.684 | AB95: Not Reversed | AC95: api | AD95: SUCCESS | AE95: SP00000 | AF95: Transaction completed successfully
B96: 395390 | C96: Rwama FCS | D96: Till | E96: Organisation | F96: Transaction Out | G96: 12537 | H96: 0 | I96: 72 | J96: 0 | K96: 0 | L96: 0 | M96: 4394280 | N96: 46267 | O96: SWEJ7U8OO3G8895 | P96: UI2SB4X9J1 | S96: Bingwa Sacco Society Ltd C2B | T96: SasaPay | U96: ThirdPartyBillPayment | V96: 765244 | W96: Bingwa Sacco Society Ltd C2B | X96: Safaricom | Y96: W13849922 | Z96: Yuiu1LugkaTYeU5lQvmA | AA96: 46267.684 | AB96: Not Reversed | AC96: api | AD96: SUCCESS | AE96: SP00000 | AF96: Transaction completed successfully
B97: 395390 | C97: Rwama FCS | D97: Till | E97: Organisation | F97: Transaction Out | G97: 5260 | H97: 0 | I97: 57 | J97: 0 | K97: 0 | L97: 0 | M97: 4388963 | N97: 46267 | O97: SWEJ7U8OO3HB84W | P97: UI2SB4XAZ1 | S97: Bingwa Sacco Society Ltd C2B | T97: SasaPay | U97: ThirdPartyBillPayment | V97: 765244 | W97: Bingwa Sacco Society Ltd C2B | X97: Safaricom | Y97: W13849921 | Z97: 1sV8KZtH3LdziY3uKG2m | AA97: 46267.684 | AB97: Not Reversed | AC97: api | AD97: SUCCESS | AE97: SP00000 | AF97: Transaction completed successfully
B98: 395390 | C98: Rwama FCS | D98: Till | E98: Organisation | F98: Transaction Out | G98: 3640 | H98: 0 | I98: 49 | J98: 0 | K98: 0 | L98: 0 | M98: 4339636 | N98: 46267 | O98: SWEJ7U8OO3H7P8T | P98: UI2SB4XDZO | S98: Bingwa Sacco Society Ltd C2B | T98: SasaPay | U98: ThirdPartyBillPayment | V98: 765244 | W98: Bingwa Sacco Society Ltd C2B | X98: Safaricom | Y98: W13849937 | Z98: fu4b0SSNGXYgoR08ufg2 | AA98: 46267.684 | AB98: Not Reversed | AC98: api | AD98: SUCCESS | AE98: SP00000 | AF98: Transaction completed successfully
B99: 395390 | C99: Rwama FCS | D99: Till | E99: Organisation | F99: Transaction Out | G99: 10346 | H99: 0 | I99: 72 | J99: 0 | K99: 0 | L99: 0 | M99: 4281723 | N99: 46267 | O99: SWEJ7U8OO3J3GLE | P99: UI2SB4X5L3 | S99: Bingwa Sacco Society Ltd C2B | T99: SasaPay | U99: ThirdPartyBillPayment | V99: 765244 | W99: Bingwa Sacco Society Ltd C2B | X99: Safaricom | Y99: W13849942 | Z99: 9iiakyQAHJKcMM5U7SGh | AA99: 46267.684 | AB99: Not Reversed | AC99: api | AD99: SUCCESS | AE99: SP00000 | AF99: Transaction completed successfully
B100: 395390 | C100: Rwama FCS | D100: Till | E100: Organisation | F100: Transaction Out | G100: 6870 | H100: 0 | I100: 57 | J100: 0 | K100: 0 | L100: 0 | M100: 4274796 | N100: 46267 | O100: SWEJ7U8OO3KDF5O | P100: UI2SB4X705 | S100: SPOTCASH | T100: SasaPay | U100: ThirdPartyBillPayment | V100: 350050 | W100: SPOTCASH | X100: Safaricom | Y100: W13849940 | Z100: kSbuLtPI68GclSrIzeho | AA100: 46267.684 | AB100: Not Reversed | AC100: api | AD100: SUCCESS | AE100: SP00000 | AF100: Transaction completed successfully
B101: 395390 | C101: Rwama FCS | D101: Till | E101: Organisation | F101: Transaction Out | G101: 2527 | H101: 0 | I101: 40 | J101: 0 | K101: 0 | L101: 0 | M101: 4264024 | N101: 46267 | O101: SWEJ7U8OO3KUNWJ | P101: UI2SB4X706 | S101: Bingwa Sacco Society Ltd C2B | T101: SasaPay | U101: ThirdPartyBillPayment | V101: 765244 | W101: Bingwa Sacco Society Ltd C2B | X101: Safaricom | Y101: W13849952 | Z101: 1Uwf4dILeiqF9ItvHmT9 | AA101: 46267.684 | AB101: Not Reversed | AC101: api | AD101: SUCCESS | AE101: SP00000 | AF101: Transaction completed successfully
B102: 395390 | C102: Rwama FCS | D102: Till | E102: Organisation | F102: Transaction Out | G102: 13682 | H102: 0 | I102: 72 | J102: 0 | K102: 0 | L102: 0 | M102: 4250270 | N102: 46267 | O102: SWEJ7U8OO3KZODI | P102: UI2SB4X5L5 | S102: Bingwa Sacco Society Ltd C2B | T102: SasaPay | U102: ThirdPartyBillPayment | V102: 765244 | W102: Bingwa Sacco Society Ltd C2B | X102: Safaricom | Y102: W13849941 | Z102: BtZC1QJIgtnpOY0Dq1z5 | AA102: 46267.684 | AB102: Not Reversed | AC102: api | AD102: SUCCESS | AE102: SP00000 | AF102: Transaction completed successfully
B103: 395390 | C103: Rwama FCS | D103: Till | E103: Organisation | F103: Transaction Out | G103: 3653 | H103: 0 | I103: 49 | J103: 0 | K103: 0 | L103: 0 | M103: 4242663 | N103: 46267 | O103: SWEJ7U8OO3LBEMA | P103: UI2SB4X9J4 | S103: Bingwa Sacco Society Ltd C2B | T103: SasaPay | U103: ThirdPartyBillPayment | V103: 765244 | W103: Bingwa Sacco Society Ltd C2B | X103: Safaricom | Y103: W13849943 | Z103: 4IuKrlbhliRWwQP9NDEz | AA103: 46267.684 | AB103: Not Reversed | AC103: api | AD103: SUCCESS | AE103: SP00000 | AF103: Transaction completed successfully
B104: 395390 | C104: Rwama FCS | D104: Till | E104: Organisation | F104: Transaction Out | G104: 4389 | H104: 0 | I104: 49 | J104: 0 | K104: 0 | L104: 0 | M104: 4238225 | N104: 46267 | O104: SWEJ7U8OO3LFKGI | P104: UI2SB4X889 | S104: FORTUNE SACCO C2B | T104: SasaPay | U104: ThirdPartyBillPayment | V104: 852648 | W104: FORTUNE SACCO C2B | X104: Safaricom | Y104: W13849944 | Z104: ISFwmqWJvPoWgzN8OLJm | AA104: 46267.684 | AB104: Not Reversed | AC104: api | AD104: SUCCESS | AE104: SP00000 | AF104: Transaction completed successfully
B105: 395390 | C105: Rwama FCS | D105: Till | E105: Organisation | F105: Transaction Out | G105: 6275 | H105: 0 | I105: 57 | J105: 0 | K105: 0 | L105: 0 | M105: 4223926 | N105: 46267 | O105: SWEJ7U8OO3LR18Q | P105: UI2SB4XCID | S105: Bingwa Sacco Society Ltd C2B | T105: SasaPay | U105: ThirdPartyBillPayment | V105: 765244 | W105: Bingwa Sacco Society Ltd C2B | X105: Safaricom | Y105: W13849945 | Z105: VKkSYHPu2IFgaiiw94NJ | AA105: 46267.684 | AB105: Not Reversed | AC105: api | AD105: SUCCESS | AE105: SP00000 | AF105: Transaction completed successfully
B106: 395390 | C106: Rwama FCS | D106: Till | E106: Organisation | F106: Transaction Out | G106: 2434 | H106: 0 | I106: 35 | J106: 0 | K106: 0 | L106: 0 | M106: 4155852 | N106: 46267 | O106: SWEJ7U8OO3NBA39 | P106: UI2SB4XAZ7 | S106: FORTUNE SACCO C2B | T106: SasaPay | U106: ThirdPartyBillPayment | V106: 852648 | W106: FORTUNE SACCO C2B | X106: Safaricom | Y106: W13849970 | Z106: m3HCXAySP77nikH6yJbi | AA106: 46267.684 | AB106: Not Reversed | AC106: api | AD106: SUCCESS | AE106: SP00000 | AF106: Transaction completed successfully
... B127: 395390 | C127: Rwama FCS | D127: Till | E127: Organisation | F127: Transaction Out | G127: 410 | H127: 0 | I127: 10 | J127: 0 | K127: 0 | L127: 0 | M127: 3653014.8 | N127: 46267 | O127: SWEJ7U8OO4W9M19 | P127: UI2SB4X70J | S127: FORTUNE SACCO C2B | T127: SasaPay | U127: ThirdPartyBillPayment | V127: 852648 | W127: FORTUNE SACCO C2B | X127: Safaricom | Y127: W13850097 | Z127: Pn4mzBx7dEgzMSRZjNjd | AA127: 46267.685 | AB127: Not Reversed | AC127: api | AD127: SUCCESS | AE127: SP00000 | AF127: Transaction completed successfully
B128: 1440382 | C128: Ian - Holmes | D128: Limited Personal Wallet | F128: Transaction Out | G128: 140 | H128: 0 | I128: 10 | J128: 2 | K128: 0 | L128: 0 | M128: 1674 | N128: 46267 | O128: SWEJ7U8OO6PZ0JG | P128: UI2SB4X5M1 | S128: Lipa na KCB | T128: SasaPay | U128: ThirdPartyBillPayment | V128: 1440382 | W128: Lipa na KCB | X128: Safaricom | Y128: W13850128 | Z128: VE858A8K | AA128: 46267.685 | AB128: Not Reversed | AD128: SUCCESS | AE128: SP00000 | AF128: Transaction completed successfully
...

Sheet Working
A1: Receipt No. | B1: Completion Time | C1: Initiation Time | D1: Details | E1: Transaction Status | F1: Paid In | G1: Withdrawn | H1: Balance | I1: Balance Confirmed | J1: Reason Type | K1: Other Party Info | L1: Linked Transaction ID | M1: A/C No. | O1: Business Short Code | P1: Account Number | Q1: Account Name | R1: Product Type | S1: Industry | T1: Transaction Type | U1: Debit | W1: Credit | X1: Charge Amount | Y1: Service Fee | Z1: SMS Charge Amount | AA1: Collection Charge Amount | AB1: Running Balance | AC1: Transaction Date | AD1: Transaction Code | AE1: Third Party Transaction Code | AF1: Reversal Transaction Code | AG1: Original Transaction Code | AH1: Client Name | AI1: From Channel | AJ1: To Channel | AK1: Party B | AL1: Party B Name | AM1: Provider | AN1: Transaction Reference | AO1: Merchant Reference | AP1: Initiation Time | AQ1: Reversal Status | AR1: Transaction Status | AS1: Platform | AT1: Result Code | AU1: Result Description
A2: UI2SB4VYS8 | B2: 02-09-2026 01:02:30 | C2: 02-09-2026 01:02:30 | D2: Business Buy Goods at 3554057 - CHICKING - LAVINGTON via API REF Bill Payment 784176 to 4999930 | E2: Completed | G2: -1780 | H2: 28661758 | I2: true | J2: Business Buy Goods via API | K2: 3554057 - CHICKING - LAVINGTON | P2: 784176 | Q2: Hizo Technology Limited | R2: Till | S2: Organisation | T2: Transaction Out | U2: 1780 | V2: =G2+U2 -> 0 | W2: 0 | X2: 10 | Y2: 0 | Z2: 1 | AA2: 0 | AB2: 120551.14 | AC2: 46267 | AD2: SWEJ7U8MQ4Z1O1F | AE2: UI2SB4VYS8 | AI2: SasaPay | AJ2: ThirdPartyBillPayment | AK2: 4999930 | AM2: Safaricom | AN2: W13841171 | AO2: 3fb92da8-1d57-43ce-b7ed-b97dfe3a649c | AP2: 46267.043 | AQ2: Not Reversed | AR2: api | AS2: SUCCESS | AT2: SP00000 | AU2: Transaction completed successfully
A3: UI2SB4W3H4 | B3: 02-09-2026 05:09:17 | C3: 02-09-2026 05:09:16 | D3: Business Buy Goods at 7248058 - RUBIS KOMAROCK via API REF Bill Payment 80421 to 9246253 | E3: Completed | G3: -5650 | H3: 28656083 | I3: true | J3: Business Buy Goods via API | K3: 7248058 - RUBIS KOMAROCK | P3: 80421 | Q3: KBQ 732J | R3: Matatu | S3: Organisation | T3: Transaction Out | U3: 5650 | V3: =G3+U3 -> 0 | W3: 0 | X3: 15 | Y3: 0 | Z3: 1 | AA3: 0 | AB3: 36.934 | AC3: 46267 | AD3: SWEJ7U8M9TVRVWD | AE3: UI2SB4W3H4 | AI3: SasaPay | AJ3: ThirdPartyBillPayment | AK3: 9246253 | AM3: Safaricom | AN3: W13841941 | AO3: Fuel | AP3: 46267.215 | AQ3: Not Reversed | AS3: SUCCESS | AT3: SP00000 | AU3: Transaction completed successfully
A4: UI2SB4WBNX | B4: 02-09-2026 06:32:24 | C4: 02-09-2026 06:32:24 | D4: Business Buy Goods at 836548 - Be Energy Kayole Petrol station via API REF Bill Payment 77480 to 821697 | E4: Completed | G4: -6700 | H4: 28635622 | I4: true | J4: Business Buy Goods via API | K4: 836548 - Be Energy Kayole Petrol station | P4: 77480 | Q4: KBR 244Y | R4: Matatu | S4: Organisation | T4: Transaction Out | U4: 6700 | V4: =G4+U4 -> 0 | W4: 0 | X4: 15 | Y4: 0 | Z4: 1 | AA4: 0 | AB4: 21.98 | AC4: 46267 | AD4: SWEJ7U8NFHFDX44 | AE4: UI2SB4WBNX | AI4: SasaPay | AJ4: ThirdPartyBillPayment | AK4: 821697 | AM4: Safaricom | AN4: W13842255 | AO4: Fuel | AP4: 46267.272 | AQ4: Not Reversed | AS4: SUCCESS | AT4: SP00000 | AU4: Transaction completed successfully
A5: UI2SB4WF8C | B5: 02-09-2026 08:23:14 | C5: 02-09-2026 08:23:14 | D5: Business Buy Goods at 634263 - TotalEnergies Lexo Utawala Junction via API REF Bill Payment 254720233020 to 634264 | E5: Completed | G5: -1500 | H5: 28531025 | I5: true | J5: Business Buy Goods via API | K5: 634263 - TotalEnergies Lexo Utawala Junction | O5: 756756 | P5: 254720233020 | Q5: ALFRED GATONGA | R5: Limited Personal Wallet | T5: Transaction Out | U5: 1500 | V5: =G5+U5 -> 0 | W5: 0 | X5: 10 | Y5: 0 | Z5: 0 | AA5: 0 | AB5: 7232 | AC5: 46267 | AD5: SWEJ7U8NN8376XL | AE5: UI2SB4WF8C | AI5: SasaPay | AJ5: ThirdPartyBillPayment | AK5: 634264 | AM5: Safaricom | AN5: W13842961 | AO5: W13842961 | AP5: 46267.349 | AQ5: Not Reversed | AR5: user_app | AS5: SUCCESS | AT5: SP00000 | AU5: Transaction completed successfully
A6: UI2SB4WFJ7 | B6: 02-09-2026 08:58:31 | C6: 02-09-2026 08:58:30 | D6: Business Buy Goods at 968511 - Shell Machakos Service Station via API REF Bill Payment 15114 to 968512 | E6: Completed | G6: -6000 | H6: 28517448 | I6: true | J6: Business Buy Goods via API | K6: 968511 - Shell Machakos Service Station | P6: 15114 | Q6: Umowa Sacco - KDY 537B | R6: Matatu | S6: Organisation | T6: Transaction Out | U6: 6000 | V6: =G6+U6 -> 0 | W6: 0 | X6: 15 | Y6: 0 | Z6: 1 | AA6: 0 | AB6: 13608.612 | AC6: 46267 | AD6: SWEJ7U8NPVAOAI8 | AE6: UI2SB4WFJ7 | AI6: SasaPay | AJ6: ThirdPartyBillPayment | AK6: 968512 | AM6: Safaricom | AN6: W13843347 | AO6: fuel | AP6: 46267.374 | AQ6: Not Reversed | AS6: SUCCESS | AT6: SP00000 | AU6: Transaction completed successfully
A7: UI2SB4WG3Q | B7: 02-09-2026 06:31:26 | C7: 02-09-2026 06:31:26 | D7: Business Buy Goods at 836548 - Be Energy Kayole Petrol station via API REF Bill Payment 77489 to 821697 | E7: Completed | G7: -13650 | H7: 28642385 | I7: true | J7: Business Buy Goods via API | K7: 836548 - Be Energy Kayole Petrol station | P7: 77489 | Q7: KBU 351C | R7: Matatu | S7: Organisation | T7: Transaction Out | U7: 13650 | V7: =G7+U7 -> 0 | W7: 0 | X7: 15 | Y7: 0 | Z7: 1 | AA7: 0 | AB7: 11.15 | AC7: 46267 | AD7: SWEJ7U8NFFSX7WE | AE7: UI2SB4WG3Q | AI7: SasaPay | AJ7: ThirdPartyBillPayment | AK7: 821697 | AM7: Safaricom | AN7: W13842249 | AO7: Fuel | AP7: 46267.272 | AQ7: Not Reversed | AS7: SUCCESS | AT7: SP00000 | AU7: Transaction completed successfully
A8: UI2SB4WHAH | B8: 02-09-2026 09:33:22 | C8: 02-09-2026 09:33:22 | D8: Business Buy Goods at 6014631 - MERCY MUNYIVA KIOKO via API REF Bill Payment 15111 to 9926197 | E8: Completed | G8: -10000 | H8: 28505882 | I8: true | J8: Business Buy Goods via API | K8: 6014631 - MERCY MUNYIVA KIOKO | P8: 15111 | Q8: Umowa Sacco - KDY 586B | R8: Matatu | S8: Organisation | T8: Transaction Out | U8: 10000 | V8: =G8+U8 -> 0 | W8: 0 | X8: 15 | Y8: 0 | Z8: 1 | AA8: 0 | AB8: 1124.458 | AC8: 46267 | AD8: SWEJ7U8NTA6RA6Y | AE8: UI2SB4WHAH | AI8: SasaPay | AJ8: ThirdPartyBillPayment | AK8: 9926197 | AM8: Safaricom | AN8: W13843802 | AO8: vincent recovery | AP8: 46267.398 | AQ8: Not Reversed | AS8: SUCCESS | AT8: SP00000 | AU8: Transaction completed successfully
A9: UI2SB4WHIQ | B9: 02-09-2026 06:33:23 | C9: 02-09-2026 06:33:23 | D9: Business Buy Goods at 836548 - Be Energy Kayole Petrol station via API REF Bill Payment 77487 to 821697 | E9: Completed | G9: -5400 | H9: 28630174 | I9: true | J9: Business Buy Goods via API | K9: 836548 - Be Energy Kayole Petrol station | P9: 77487 | Q9: KBY 456V | R9: Matatu | S9: Organisation | T9: Transaction Out | U9: 5400 | V9: =G9+U9 -> 0 | W9: 0 | X9: 15 | Y9: 0 | Z9: 1 | AA9: 0 | AB9: 33.796 | AC9: 46267 | AD9: SWEJ7U8NFI1398Z | AE9: UI2SB4WHIQ | AI9: SasaPay | AJ9: ThirdPartyBillPayment | AK9: 821697 | AM9: Safaricom | AN9: W13842259 | AO9: Fuel | AP9: 46267.273 | AQ9: Not Reversed | AS9: SUCCESS | AT9: SP00000 | AU9: Transaction completed successfully
A10: UI2SB4WHX9 | B10: 02-09-2026 07:48:46 | C10: 02-09-2026 07:48:46 | D10: Business Buy Goods at 177545 - DONHOLM TOTAL S.S1 via API REF Bill Payment 1586202 to 177749 | E10: Completed | G10: -97486 | H10: 28532640 | I10: true | J10: Business Buy Goods via API | K10: 177545 - DONHOLM TOTAL S.S1 | P10: 1586202 | Q10: purity - Twiddle Pips | R10: Limited Personal Wallet | T10: Transaction Out | U10: 97486 | V10: =G10+U10 -> 0 | W10: 0 | X10: 15 | Y10: 15 | Z10: 0 | AA10: 0 | AB10: 3455 | AC10: 46267 | AD10: SWEJ7U8NKTMRLE3 | AE10: UI2SB4WHX9 | AI10: SasaPay | AJ10: ThirdPartyBillPayment | AK10: 1586202 | AM10: Safaricom | AN10: W13842697 | AO10: RZV9HXBQ | AP10: 46267.325 | AQ10: Not Reversed | AS10: SUCCESS | AT10: SP00000 | AU10: Transaction completed successfully
A11: UI2SB4WIRN | B11: 02-09-2026 09:39:12 | C11: 02-09-2026 09:39:10 | D11: Business Pay Bill via API to 485111 - Rubis Energy Kenya PLc Acc. 6500090405 | E11: Completed | G11: -2700 | H11: 28503098 | I11: true | J11: Business Pay Bill via API | K11: 485111 - Rubis Energy Kenya PLc | M11: 6500090405 | O11: 756756 | P11: 1625943 | Q11: Kennedy - Kennedy waithaka mburu | R11: Biashara Wallet | T11: Transaction Out | U11: 2700 | V11: =G11+U11 -> 0 | W11: 0 | X11: 40 | Y11: 0 | Z11: 0 | AA11: 0 | AB11: 1305.23 | AC11: 46267 | AD11: SWEJ7U8NTKW9JJ2 | AE11: UI2SB4WIRN | AH11: Rubis Energy Kenya PLc | AI11: SasaPay | AJ11: ThirdPartyBillPayment | AK11: 485111 | AL11: Rubis Energy Kenya PLc | AM11: Safaricom | AN11: W13843860 | AO11: 6500090405 | AP11: 46267.402 | AQ11: Not Reversed | AR11: user_app | AS11: SUCCESS | AT11: SP00000 | AU11: Transaction completed successfully
A12: UI2SB4WJ6V | B12: 02-09-2026 08:38:08 | C12: 02-09-2026 08:38:08 | D12: Business Buy Goods at 8561779 - FELIX ONYANGO ODUOR via API REF Bill Payment 254797413147 to 6721699 | E12: Completed | G12: -140 | H12: 28530867 | I12: true | J12: Business Buy Goods via API | K12: 8561779 - FELIX ONYANGO ODUOR | O12: 756756 | P12: 254797413147 | Q12: FELIX ODUOR | R12: Limited Personal Wallet | T12: Transaction Out | U12: 140 | V12: =G12+U12 -> 0 | W12: 0 | X12: 10 | Y12: 0 | Z12: 0 | AA12: 0 | AB12: 351 | AC12: 46267 | AD12: SWEJ7U8NOXUAGUH | AE12: UI2SB4WJ6V | AI12: SasaPay | AJ12: ThirdPartyBillPayment | AK12: 6721699 | AM12: Safaricom | AN12: W13843086 | AO12: W13843086 | AP12: 46267.36 | AQ12: Not Reversed | AR12: user_app | AS12: SUCCESS | AT12: SP00000 | AU12: Transaction completed successfully
A13: UI2SB4WK05 | B13: 02-09-2026 10:18:32 | C13: 02-09-2026 10:18:32 | D13: Business Buy Goods at 6569648 - SHELL MIREMA 1 via API REF Bill Payment 254711592002 to 5555550 | E13: Completed | G13: -1500 | H13: 28478091 | I13: true | J13: Business Buy Goods via API | K13: 6569648 - SHELL MIREMA 1 | O13: 756756 | P13: 254711592002 | Q13: Leonard Gitachu | R13: Limited Personal Wallet | T13: Transaction Out | U13: 1500 | V13: =G13+U13 -> 0 | W13: 0 | X13: 10 | Y13: 0 | Z13: 0 | AA13: 0 | AB13: 11723 | AC13: 46267 | AD13: SWEJ7U8NW7XCO14 | AE13: UI2SB4WK05 | AI13: SasaPay | AJ13: ThirdPartyBillPayment | AK13: 5555550 | AM13: Safaricom | AN13: W13844375 | AO13: W13844375 | AP13: 46267.429 | AQ13: Not Reversed | AR13: user_app | AS13: SUCCESS | AT13: SP00000 | AU13: Transaction completed successfully
A14: UI2SB4WK79 | B14: 02-09-2026 10:42:04 | C14: 02-09-2026 10:42:03 | D14: Business Pay Bill via API to 247247 - Equity Paybill Account Acc. 0766660011 | E14: Completed | G14: -15900 | H14: 28462105 | I14: true | J14: Business Pay Bill via API | K14: 247247 - Equity Paybill Account | M14: 0766660011 | P14: 1552342 | Q14: Monica jematia chemuna | R14: Limited Personal Wallet | T14: Transaction Out | U14: 15900 | V14: =G14+U14 -> 0 | W14: 0 | X14: 82 | Y14: 18 | Z14: 0 | AA14: 0 | AB14: 50 | AC14: 46267 | AD14: SWEJ7U8NYA5FJ4W | AE14: UI2SB4WK79 | AH14: Equity Paybill Account | AI14: SasaPay | AJ14: ThirdPartyBillPayment | AK14: 1552342 | AL14: Equity Paybill Account | AM14: Safaricom | AN14: W13844676 | AO14: N5H4LRSL | AP14: 46267.446 | AQ14: Not Reversed | AS14: SUCCESS | AT14: SP00000 | AU14: Transaction completed successfully
A15: UI2SB4WKRW | B15: 02-09-2026 08:56:48 | C15: 02-09-2026 08:56:48 | D15: Business Pay Bill via API to 600900 - DAVIS AND SHIRTLIFF LIMITED Acc. 355286 | E15: Completed | G15: -7363 | H15: 28523496 | I15: true | J15: Business Pay Bill via API | K15: 600900 - DAVIS AND SHIRTLIFF LIMITED | M15: 355286 | P15: 293009 | Q15: Adeline Munguti | R15: Till | T15: Transaction Out | U15: 7363 | V15: =G15+U15 -> 0 | W15: 0 | X15: 57 | Y15: 0 | Z15: 0 | AA15: 0 | AB15: 389832 | AC15: 46267 | AD15: SWEJ7U8NPR9X7CR | AE15: UI2SB4WKRW | AH15: DAVIS AND SHIRTLIFF LIMITED | AI15: SasaPay | AJ15: ThirdPartyBillPayment | AK15: 293009 | AL15: DAVIS AND SHIRTLIFF LIMITED | AM15: Safaricom | AN15: W13843325 | AO15: a499805a-4877-47ee-8311-9d2500b53dbd | AP15: 46267.372 | AQ15: Not Reversed | AS15: SUCCESS | AT15: SP00000 | AU15: Transaction completed successfully
A16: UI2SB4WKYX | B16: 02-09-2026 09:23:49 | C16: 02-09-2026 09:23:48 | D16: Business Pay Bill via API to 522522 - KCB Paybill AC Acc. 1107630282 | E16: Completed | G16: -1500 | H16: 28515900 | I16: true | J16: Business Pay Bill via API | K16: 522522 - KCB Paybill AC | M16: 1107630282 | P16: 414936 | Q16: John Slater | R16: Limited Personal Wallet | T16: Transaction Out | U16: 1500 | V16: =G16+U16 -> 0 | W16: 0 | X16: 25 | Y16: 2 | Z16: 0 | AA16: 0 | AB16: 21326 | AC16: 46267 | AD16: SWEJ7U8NSU29DL3 | AE16: UI2SB4WKYX | AH16: KCB Paybill AC | AI16: SasaPay | AJ16: ThirdPartyBillPayment | AK16: 414936 | AL16: KCB Paybill AC | AM16: Safaricom | AN16: W13843684 | AO16: ACWTGA9V | AP16: 46267.391 | AQ16: Not Reversed | AS16: SUCCESS | AT16: SP00000 | AU16: Transaction completed successfully
A17: UI2SB4WMJ0 | B17: 02-09-2026 10:15:20 | C17: 02-09-2026 10:15:20 | D17: Business Pay Bill via API to 714888 - LOOP BIZ Acc. 380605 | E17: Completed | G17: -22500 | H17: 28479665 | I17: true | J17: Business Pay Bill via API | K17: 714888 - LOOP BIZ | M17: 380605 | P17: 458445 | Q17: BUYSIMU TECHNOLOGIES LIMITED | R17: Till | S17: Organisation | T17: Transaction Out | U17: 22500 | V17: =G17+U17 -> 0 | W17: 0 | X17: 87 | Y17: 0 | Z17: 1 | AA17: 0 | AB17: 810922.69 | AC17: 46267 | AD17: SWEJ7U8NW2RW18S | AE17: UI2SB4WMJ0 | AH17: LOOP BIZ | AI17: SasaPay | AJ17: ThirdPartyBillPayment | AK17: 714888 | AL17: LOOP BIZ | AM17: Safaricom | AN17: W13844344 | AO17: 18738 | AP17: 46267.427 | AQ17: Not Reversed | AR17: api | AS17: SUCCESS | AT17: SP00000 | AU17: Transaction completed successfully
A18: UI2SB4WMW0 | B18: 02-09-2026 10:57:54 | C18: 02-09-2026 10:57:54 | D18: Business Buy Goods at 7267296 - JISTY FOOD via API REF Bill Payment 1326697 to 9242717 | E18: Completed | G18: -60 | H18: 28462045 | I18: true | J18: Business Buy Goods via API | K18: 7267296 - JISTY FOOD | P18: 1326697 | Q18: Kenneth Njoroge Nganga | R18: Limited Personal Wallet | T18: Transaction Out | U18: 60 | V18: =G18+U18 -> 0 | W18: 0 | X18: 0 | Y18: 0 | Z18: 0 | AA18: 0 | AB18: 13461 | AC18: 46267 | AD18: SWEJ7U8NY0SR33K | AE18: UI2SB4WMW0 | AI18: SasaPay | AJ18: ThirdPartyBillPayment | AK18: 1326697 | AM18: Safaricom | AN18: W13844799 | AO18: I0VE48YU | AP18: 46267.456 | AQ18: Not Reversed | AS18: SUCCESS | AT18: SP00000 | AU18: Transaction completed successfully
A19: UI2SB4WMXS | B19: 02-09-2026 11:02:38 | C19: 02-09-2026 11:02:38 | D19: Business Buy Goods at 331547 - TOWER GOLD PACKAGING VENTURES. via API REF Bill Payment 276585 to 331711 | E19: Completed | G19: -650 | H19: 28423646 | I19: true | J19: Business Buy Goods via API | K19: 331547 - TOWER GOLD PACKAGING VENTURES. | P19: 276585 | Q19: HEAVENLY WINGS FOODS LIMITED | R19: Till | S19: Organisation | T19: Transaction Out | U19: 650 | V19: =G19+U19 -> 0 | W19: 0 | X19: 10 | Y19: 0 | Z19: 1 | AA19: 0 | AB19: 13108.36 | AC19: 46267 | AD19: SWEJ7U8N02X9DQO | AE19: UI2SB4WMXS | AI19: SasaPay | AJ19: ThirdPartyBillPayment | AK19: 331711 | AM19: Safaricom | AN19: W13844880 | AO19: Purchase of packaging bags | AP19: 46267.46 | AQ19: Not Reversed | AS19: SUCCESS | AT19: SP00000 | AU19: Transaction completed successfully
A20: UI2SB4WN6Z | B20: 02-09-2026 11:36:50 | C20: 02-09-2026 11:36:50 | D20: Business Buy Goods at 6041758 - CENTRE MAX ONE TRADERS via API REF Bill Payment 254708619405 to 9981521 | E20: Completed | G20: -150 | H20: 28415825 | I20: true | J20: Business Buy Goods via API | K20: 6041758 - CENTRE MAX ONE TRADERS | O20: 756756 | P20: 254708619405 | Q20: Dennis Mwangi | R20: Wallet-Personal | T20: Transaction Out | U20: 150 | V20: =G20+U20 -> 0 | W20: 0 | X20: 10 | Y20: 0 | Z20: 0 | AA20: 0 | AB20: 1272 | AC20: 46267 | AD20: SWEJ7U8N2NDOM1Y | AE20: UI2SB4WN6Z | AI20: SasaPay | AJ20: ThirdPartyBillPayment | AK20: 9981521 | AM20: Safaricom | AN20: W13845341 | AO20: W13845341 | AP20: 46267.483 | AQ20: Not Reversed | AR20: user_app | AS20: SUCCESS | AT20: SP00000 | AU20: Transaction completed successfully
A21: UI2SB4WN9Q | B21: 02-09-2026 11:43:11 | C21: 02-09-2026 11:43:11 | D21: Business Buy Goods at 7045653 - KANGUNDO ROAD TOTAL PETROL STATION via API REF Bill Payment 205756 to 5047675 | E21: Completed | G21: -100 | H21: 28415717 | I21: true | J21: Business Buy Goods via API | K21: 7045653 - KANGUNDO ROAD TOTAL PETROL STATION | O21: 756756 | P21: 205756 | Q21: Erick - erick | R21: Biashara Wallet | T21: Transaction Out | U21: 100 | V21: =G21+U21 -> 0 | W21: 0 | X21: 0 | Y21: 0 | Z21: 0 | AA21: 0 | AB21: 364.59 | AC21: 46267 | AD21: SWEJ7U8N2YBIDU7 | AE21: UI2SB4WN9Q | AI21: SasaPay | AJ21: ThirdPartyBillPayment | AK21: 5047675 | AM21: Safaricom | AN21: W13845433 | AO21: W13845433 | AP21: 46267.488 | AQ21: Not Reversed | AR21: user_app | AS21: SUCCESS | AT21: SP00000 | AU21: Transaction completed successfully
A22: UI2SB4WNKB | B22: 02-09-2026 12:22:53 | C22: 02-09-2026 12:22:52 | D22: Business Pay Bill via API to 910200 - Guaranty Trust Bank Ltd Acc. 2210003653 | E22: Completed | G22: -20000 | H22: 28300870 | I22: true | J22: Business Pay Bill via API | K22: 910200 - Guaranty Trust Bank Ltd | M22: 2210003653 | P22: 110311 | Q22: Bag Ware Limited | R22: PayBill-CustomerOption | S22: Organisation | T22: Transaction Out | U22: 20000 | V22: =G22+U22 -> 0 | W22: 0 | X22: 80 | Y22: 0 | Z22: 1 | AA22: 0 | AB22: 828713 | AC22: 46267 | AD22: SWEJ7U8N6LMWRA1 | AE22: UI2SB4WNKB | AH22: Guaranty Trust Bank Ltd | AI22: SasaPay | AJ22: ThirdPartyBillPayment | AK22: 910200 | AL22: Guaranty Trust Bank Ltd | AM22: Safaricom | AN22: W13846110 | AO22: 2210003653 | AP22: 46267.515 | AQ22: Not Reversed | AS22: SUCCESS | AT22: SP00000 | AU22: Transaction completed successfully
A23: UI2SB4WOXB | B23: 02-09-2026 12:27:50 | C23: 02-09-2026 12:27:50 | D23: Business Pay Bill via API to 639498 - GDC SACCO SOCIETY LTD Acc. 4929856 | E23: Completed | G23: -3288 | H23: 28087883 | I23: true | J23: Business Pay Bill via API | K23: 639498 - GDC SACCO SOCIETY LTD | M23: 4929856 | P23: 9235 | Q23: Wimssy | R23: Till | S23: Organisation | T23: Transaction Out | U23: 3288 | V23: =G23+U23 -> 0 | W23: 0 | X23: 40 | Y23: 0 | Z23: 1 | AA23: 0 | AB23: 111280.4 | AC23: 46267 | AD23: SWEJ7U8N6TU5X4X | AE23: UI2SB4WOXB | AH23: GDC SACCO SOCIETY LTD | AI23: SasaPay | AJ23: ThirdPartyBillPayment | AK23: 639498 | AL23: GDC SACCO SOCIETY LTD | AM23: Safaricom | AN23: W13846198 | AO23: PRcP88t6cLRq4Qe69TF9 | AP23: 46267.519 | AQ23: Not Reversed | AR23: api | AS23: SUCCESS | AT23: SP00000 | AU23: Transaction completed successfully
A24: UI2SB4WOXC | B24: 02-09-2026 12:27:51 | C24: 02-09-2026 12:27:51 | D24: Business Pay Bill via API to 639498 - GDC SACCO SOCIETY LTD Acc. 876996574 | E24: Completed | G24: -372 | H24: 28048178 | I24: true | J24: Business Pay Bill via API | K24: 639498 - GDC SACCO SOCIETY LTD | M24: 876996574 | P24: 9235 | Q24: Wimssy | R24: Till | S24: Organisation | T24: Transaction Out | U24: 372 | V24: =G24+U24 -> 0 | W24: 0 | X24: 10 | Y24: 0 | Z24: 1 | AA24: 0 | AB24: 63629.6 | AC24: 46267 | AD24: SWEJ7U8N6TVNO6P | AE24: UI2SB4WOXC | AH24: GDC SACCO SOCIETY LTD | AI24: SasaPay | AJ24: ThirdPartyBillPayment | AK24: 639498 | AL24: GDC SACCO SOCIETY LTD | AM24: Safaricom | AN24: W13846211 | AO24: iJfvkuKnuCgnb4qQhTtl | AP24: 46267.519 | AQ24: Not Reversed | AR24: api | AS24: SUCCESS | AT24: SP00000 | AU24: Transaction completed successfully
A25: UI2SB4WOXE | B25: 02-09-2026 12:27:52 | C25: 02-09-2026 12:27:52 | D25: Business Pay Bill via API to 639498 - GDC SACCO SOCIETY LTD Acc. 28481045 | E25: Completed | G25: -2763 | H25: 28021948 | I25: true | J25: Business Pay Bill via API | K25: 639498 - GDC SACCO SOCIETY LTD | M25: 28481045 | P25: 9235 | Q25: Wimssy | R25: Till | S25: Organisation | T25: Transaction Out | U25: 2763 | V25: =G25+U25 -> 0 | W25: 0 | X25: 40 | Y25: 0 | Z25: 1 | AA25: 0 | AB25: 31245.6 | AC25: 46267 | AD25: SWEJ7U8N6TWVFDV | AE25: UI2SB4WOXE | AH25: GDC SACCO SOCIETY LTD | AI25: SasaPay | AJ25: ThirdPartyBillPayment | AK25: 639498 | AL25: GDC SACCO SOCIETY LTD | AM25: Safaricom | AN25: W13846212 | AO25: Ay8wdAWUfcAIvILjmR7r | AP25: 46267.519 | AQ25: Not Reversed | AR25: api | AS25: SUCCESS | AT25: SP00000 | AU25: Transaction completed successfully
A26: UI2SB4WOZA | B26: 02-09-2026 12:33:12 | C26: 02-09-2026 12:33:12 | D26: Business Buy Goods at 7213359 - VEROSHIMA TRADERS KAHAWA via API REF Bill Payment 1483 to 5228737 | E26: Completed | G26: -5920 | H26: 28000630 | I26: true | J26: Business Buy Goods via API | K26: 7213359 - VEROSHIMA TRADERS KAHAWA | P26: 1483 | Q26: VLC-PROPERTY PETTY CASH | R26: Till | S26: Organisation | T26: Transaction Out | U26: 5920 | V26: =G26+U26 -> 0 | W26: 0 | X26: 15 | Y26: 0 | Z26: 1 | AA26: 0 | AB26: 19695.578 | AC26: 46267 | AD26: SWEJ7U8N625YWZZ | AE26: UI2SB4WOZA | AI26: SasaPay | AJ26: ThirdPartyBillPayment | AK26: 5228737 | AM26: Safaricom | AN26: W13846323 | AO26: Purchase of construction materials - Richland Pointe | AP26: 46267.523 | AQ26: Not Reversed | AS26: SUCCESS | AT26: SP00000 | AU26: Transaction completed successfully
A27: UI2SB4WP5U | B27: 02-09-2026 09:44:23 | C27: 02-09-2026 09:44:23 | D27: Business Pay Bill via API to 247247 - Equity Paybill Account Acc. 116700 | E27: Completed | G27: -900 | H27: 28502198 | I27: true | J27: Business Pay Bill via API | K27: 247247 - Equity Paybill Account | M27: 116700 | P27: 1484 | Q27: VLC- OFFICE PETTY CASH | R27: Till | S27: Organisation | T27: Transaction Out | U27: 900 | V27: =G27+U27 -> 0 | W27: 0 | X27: 20 | Y27: 0 | Z27: 1 | AA27: 0 | AB27: 1328.674 | AC27: 46267 | AD27: SWEJ7U8NTTD3W0C | AE27: UI2SB4WP5U | AH27: Equity Paybill Account | AI27: SasaPay | AJ27: ThirdPartyBillPayment | AK27: 247247 | AL27: Equity Paybill Account | AM27: Safaricom | AN27: W13843926 | AO27: 116700 | AP27: 46267.406 | AQ27: Not Reversed | AS27: SUCCESS | AT27: SP00000 | AU27: Transaction completed successfully
A28: UI2SB4WPQ8 | B28: 02-09-2026 10:58:54 | C28: 02-09-2026 10:58:54 | D28: Business Buy Goods at 4321579 - SUNFALL GENERAL TRADERS LTD via API REF Bill Payment 276585 to 3586381 | E28: Completed | G28: -9450 | H28: 28452592 | I28: true | J28: Business Buy Goods via API | K28: 4321579 - SUNFALL GENERAL TRADERS LTD | P28: 276585 | Q28: HEAVENLY WINGS FOODS LIMITED | R28: Till | S28: Organisation | T28: Transaction Out | U28: 9450 | V28: =G28+U28 -> 0 | W28: 0 | X28: 15 | Y28: 0 | Z28: 1 | AA28: 0 | AB28: 23525.36 | AC28: 46267 | AD28: SWEJ7U8NY2FVS9C | AE28: UI2SB4WPQ8 | AI28: SasaPay | AJ28: ThirdPartyBillPayment | AK28: 3586381 | AM28: Safaricom | AN28: W13844809 | AO28: Dry Goods purchase | AP28: 46267.457 | AQ28: Not Reversed | AS28: SUCCESS | AT28: SP00000 | AU28: Transaction completed successfully
A29: UI2SB4WPR0 | B29: 02-09-2026 11:00:51 | C29: 02-09-2026 11:00:51 | D29: Business Pay Bill via API to 525900 - Africastalking Ltd Acc. ASFASMS | E29: Completed | G29: -20000 | H29: 28424364 | I29: true | J29: Business Pay Bill via API | K29: 525900 - Africastalking Ltd | M29: ASFASMS | P29: 458445 | Q29: BUYSIMU TECHNOLOGIES LIMITED | R29: Till | S29: Organisation | T29: Transaction Out | U29: 20000 | V29: =G29+U29 -> 0 | W29: 0 | X29: 82 | Y29: 0 | Z29: 1 | AA29: 0 | AB29: 761775.69 | AC29: 46267 | AD29: SWEJ7U8N0ZU2KWQ | AE29: UI2SB4WPR0 | AH29: Africastalking Ltd | AI29: SasaPay | AJ29: ThirdPartyBillPayment | AK29: 525900 | AL29: Africastalking Ltd | AM29: Safaricom | AN29: W13844863 | AO29: ASFASMS | AP29: 46267.458 | AQ29: Not Reversed | AS29: SUCCESS | AT29: SP00000 | AU29: Transaction completed successfully
A30: UI2SB4WQ67 | B30: 02-09-2026 11:48:58 | C30: 02-09-2026 11:48:58 | D30: Business Buy Goods at 6518431 - BLEJOMA SUPPLIES VIA NCBA via API REF Bill Payment 1606341 to 8811560 | E30: Completed | G30: -675 | H30: 28364601 | I30: true | J30: Business Buy Goods via API | K30: 6518431 - BLEJOMA SUPPLIES VIA NCBA | P30: 1606341 | Q30: Beldina - Beldina | R30: Limited Personal Wallet | T30: Transaction Out | U30: 675 | V30: =G30+U30 -> 0 | W30: 0 | X30: 10 | Y30: 2 | Z30: 0 | AA30: 0 | AB30: 312 | AC30: 46267 | AD30: SWEJ7U8N27CT8EP | AE30: UI2SB4WQ67 | AI30: SasaPay | AJ30: ThirdPartyBillPayment | AK30: 1606341 | AM30: Safaricom | AN30: W13845498 | AO30: NRNYDA0Q | AP30: 46267.492 | AQ30: Not Reversed | AS30: SUCCESS | AT30: SP00000 | AU30: Transaction completed successfully
A31: UI2SB4WQDX | B31: 02-09-2026 12:18:43 | C31: 02-09-2026 12:18:43 | D31: Business Buy Goods at 6707263 - SHELL TECO SERVICE STATION_Pump 5 via API REF Bill Payment 1116456 to 4106574 | E31: Completed | G31: -500 | H31: 28320946 | I31: true | J31: Business Buy Goods via API | K31: 6707263 - SHELL TECO SERVICE STATION_Pump 5 | O31: 756756 | P31: 1116456 | Q31: SIMON - SIMON KATUMO MUTINDA | R31: Biashara Wallet | T31: Transaction Out | U31: 500 | V31: =G31+U31 -> 0 | W31: 0 | X31: 10 | Y31: 0 | Z31: 0 | AA31: 0 | AB31: 61160.02 | AC31: 46267 | AD31: SWEJ7U8N6EVPUST | AE31: UI2SB4WQDX | AI31: SasaPay | AJ31: ThirdPartyBillPayment | AK31: 4106574 | AM31: Safaricom | AN31: W13846034 | AO31: W13846034 | AP31: 46267.512 | AQ31: Not Reversed | AR31: user_app | AS31: SUCCESS | AT31: SP00000 | AU31: Transaction completed successfully
A32: UI2SB4WQHH | B32: 02-09-2026 12:27:49 | C32: 02-09-2026 12:27:49 | D32: Business Pay Bill via API to 639498 - GDC SACCO SOCIETY LTD Acc. 10975802 | E32: Completed | G32: -1500 | H32: 28106496 | I32: true | J32: Business Pay Bill via API | K32: 639498 - GDC SACCO SOCIETY LTD | M32: 10975802 | P32: 9235 | Q32: Wimssy | R32: Till | S32: Organisation | T32: Transaction Out | U32: 1500 | V32: =G32+U32 -> 0 | W32: 0 | X32: 25 | Y32: 0 | Z32: 1 | AA32: 0 | AB32: 158004.8 | AC32: 46267 | AD32: SWEJ7U8N6TUK4W6 | AE32: UI2SB4WQHH | AH32: GDC SACCO SOCIETY LTD | AI32: SasaPay | AJ32: ThirdPartyBillPayment | AK32: 639498 | AL32: GDC SACCO SOCIETY LTD | AM32: Safaricom | AN32: W13846196 | AO32: ST0FAxhf7QzUIJPjvRkd | AP32: 46267.519 | AQ32: Not Reversed | AR32: api | AS32: SUCCESS | AT32: SP00000 | AU32: Transaction completed successfully
A33: UI2SB4WQIS | B33: 02-09-2026 12:32:26 | C33: 02-09-2026 12:32:26 | D33: Business Buy Goods at 113322 - SCOOBY ENTREPRISES LIMITED via API REF Bill Payment 1391815 to 113522 | E33: Completed | G33: -15300 | H33: 28006618 | I33: true | J33: Business Buy Goods via API | K33: 113322 - SCOOBY ENTREPRISES LIMITED | P33: 1391815 | Q33: MORINE ONGERI | R33: Limited Personal Wallet | T33: Transaction Out | U33: 15300 | V33: =G33+U33 -> 0 | W33: 0 | X33: 15 | Y33: 18 | Z33: 0 | AA33: 0 | AB33: 49549.18 | AC33: 46267 | AD33: SWEJ7U8N61QWISS | AE33: UI2SB4WQIS | AI33: SasaPay | AJ33: ThirdPartyBillPayment | AK33: 1391815 | AM33: Safaricom | AN33: W13846311 | AO33: GAWOCJ4B | AP33: 46267.522 | AQ33: Not Reversed | AS33: SUCCESS | AT33: SP00000 | AU33: Transaction completed successfully
A34: UI2SB4WQSQ | B34: 02-09-2026 10:00:14 | C34: 02-09-2026 10:00:14 | D34: Business Pay Bill via API to 4131085 - Pharmaplus Pharmaceuticals_23 Acc. n | E34: Completed | G34: -20 | H34: 28502165 | I34: true | J34: Business Pay Bill via API | K34: 4131085 - Pharmaplus Pharmaceuticals_23 | M34: n | O34: 756756 | P34: 254795093834 | Q34: Victor Omondi | R34: Limited Personal Wallet | T34: Transaction Out | U34: 20 | V34: =G34+U34 -> 0 | W34: 0 | X34: 0 | Y34: 0 | Z34: 0 | AA34: 0 | AB34: 56 | AC34: 46267 | AD34: SWEJ7U8NWDUY7OU | AE34: UI2SB4WQSQ | AH34: Pharmaplus Pharmaceuticals_23 | AI34: SasaPay | AJ34: ThirdPartyBillPayment | AK34: 4131085 | AL34: Pharmaplus Pharmaceuticals_23 | AM34: Safaricom | AN34: W13844095 | AO34: n | AP34: 46267.417 | AQ34: Not Reversed | AR34: user_app | AS34: SUCCESS | AT34: SP00000 | AU34: Transaction completed successfully
A35: UI2SB4WRFJ | B35: 02-09-2026 11:19:29 | C35: 02-09-2026 11:19:28 | D35: Business Pay Bill via API to 4107991 - HAWKERS PRIDE ENTERPRISES LIMITED Acc. 3 | E35: Completed | G35: -3720 | H35: 28419913 | I35: true | J35: Business Pay Bill via API | K35: 4107991 - HAWKERS PRIDE ENTERPRISES LIMITED | M35: 3 | O35: 756756 | P35: 358222 | Q35: Dunwell - TUMAINI SHOP | R35: Matatu | T35: Transaction Out | U35: 3720 | V35: =G35+U35 -> 0 | W35: 0 | X35: 49 | Y35: 0 | Z35: 0 | AA35: 0 | AB35: 850.22 | AC35: 46267 | AD35: SWEJ7U8N1UWPKWF | AE35: UI2SB4WRFJ | AH35: HAWKERS PRIDE ENTERPRISES LIMITED | AI35: SasaPay | AJ35: ThirdPartyBillPayment | AK35: 4107991 | AL35: HAWKERS PRIDE ENTERPRISES LIMITED | AM35: Safaricom | AN35: W13845063 | AO35: 3 | AP35: 46267.472 | AQ35: Not Reversed | AR35: user_app | AS35: SUCCESS | AT35: SP00000 | AU35: Transaction completed successfully
A36: UI2SB4WS0S | B36: 02-09-2026 12:27:48 | C36: 02-09-2026 12:27:47 | D36: Business Pay Bill via API to 639498 - GDC SACCO SOCIETY LTD Acc. 21442179 | E36: Completed | G36: -7408 | H36: 28131347 | I36: true | J36: Business Pay Bill via API | K36: 639498 - GDC SACCO SOCIETY LTD | M36: 21442179 | P36: 9235 | Q36: Wimssy | R36: Till | S36: Organisation | T36: Transaction Out | U36: 7408 | V36: =G36+U36 -> 0 | W36: 0 | X36: 57 | Y36: 0 | Z36: 1 | AA36: 0 | AB36: 188066.8 | AC36: 46267 | AD36: SWEJ7U8N6TT24GB | AE36: UI2SB4WS0S | AH36: GDC SACCO SOCIETY LTD | AI36: SasaPay | AJ36: ThirdPartyBillPayment | AK36: 639498 | AL36: GDC SACCO SOCIETY LTD | AM36: Safaricom | AN36: W13846191 | AO36: Bov4xnQYTVKJpZ9cI0lG | AP36: 46267.519 | AQ36: Not Reversed | AR36: api | AS36: SUCCESS | AT36: SP00000 | AU36: Transaction completed successfully
A37: UI2SB4WSPF | B37: 02-09-2026 11:00:44 | C37: 02-09-2026 11:00:44 | D37: Business Buy Goods at 7752793 - IBRAHIM FARMERS CHOICE STOCKISTS via API REF Bill Payment 276585 to 5775191 | E37: Completed | G37: -8120 | H37: 28444418 | I37: true | J37: Business Buy Goods via API | K37: 7752793 - IBRAHIM FARMERS CHOICE STOCKISTS | P37: 276585 | Q37: HEAVENLY WINGS FOODS LIMITED | R37: Till | S37: Organisation | T37: Transaction Out | U37: 8120 | V37: =G37+U37 -> 0 | W37: 0 | X37: 15 | Y37: 0 | Z37: 1 | AA37: 0 | AB37: 13769.36 | AC37: 46267 | AD37: SWEJ7U8N0ZQK5EZ | AE37: UI2SB4WSPF | AI37: SasaPay | AJ37: ThirdPartyBillPayment | AK37: 5775191 | AM37: Safaricom | AN37: W13844860 | AO37: Purchase of sausages, bacon | AP37: 46267.458 | AQ37: Not Reversed | AS37: SUCCESS | AT37: SP00000 | AU37: Transaction completed successfully
A38: UI2SB4WSYZ | B38: 02-09-2026 11:34:38 | C38: 02-09-2026 11:34:38 | D38: Business Pay Bill via API to 583674 - GURU NANAK RAMGARHIA SIKH HOSPITAL Acc. sarah | E38: Completed | G38: -3860 | H38: 28416014 | I38: true | J38: Business Pay Bill via API | K38: 583674 - GURU NANAK RAMGARHIA SIKH HOSPITAL | M38: sarah | P38: 1003020 | Q38: Stephen - Viewtech Afya | R38: Till-CustomerOption | T38: Transaction Out | U38: 3860 | V38: =G38+U38 -> 0 | W38: 0 | X38: 49 | Y38: 38.6 | Z38: 0 | AA38: 0 | AB38: 41918.93 | AC38: 46267 | AD38: SWEJ7U8N2JVF3NG | AE38: UI2SB4WSYZ | AH38: GURU NANAK RAMGARHIA SIKH HOSPITAL | AI38: SasaPay | AJ38: ThirdPartyBillPayment | AK38: 1003020 | AL38: GURU NANAK RAMGARHIA SIKH HOSPITAL | AM38: Safaricom | AN38: W13845310 | AO38: MF166661 | AP38: 46267.482 | AQ38: Not Reversed | AS38: SUCCESS | AT38: SP00000 | AU38: Transaction completed successfully
A39: UI2SB4WT29 | B39: 02-09-2026 11:44:11 | C39: 02-09-2026 11:44:11 | D39: Business Pay Bill via API to 522533 - Lipa na KCB Acc. 7881524 | E39: Completed | G39: -960 | H39: 28365289 | I39: true | J39: Business Pay Bill via API | K39: 522533 - Lipa na KCB | M39: 7881524 | P39: 118594 | Q39: Petty Cash | R39: Till | S39: Financial and Insurance activities | T39: Transaction Out | U39: 960 | V39: =G39+U39 -> 0 | W39: 0 | X39: 20 | Y39: 0 | Z39: 1 | AA39: 0 | AB39: 42846.58 | AC39: 46267 | AD39: SWEJ7U8N2ZYXT3W | AE39: UI2SB4WT29 | AH39: Lipa na KCB | AI39: SasaPay | AJ39: ThirdPartyBillPayment | AK39: 522533 | AL39: Lipa na KCB | AM39: Safaricom | AN39: W13845447 | AO39: 7881524 | AP39: 46267.489 | AQ39: Not Reversed | AS39: SUCCESS | AT39: SP00000 | AU39: Transaction completed successfully
A40: UI2SB4WTFF | B40: 02-09-2026 12:27:48 | C40: 02-09-2026 12:27:48 | D40: Business Pay Bill via API to 639498 - GDC SACCO SOCIETY LTD Acc. 9376383 | E40: Completed | G40: -7503 | H40: 28115174 | I40: true | J40: Business Pay Bill via API | K40: 639498 - GDC SACCO SOCIETY LTD | M40: 9376383 | P40: 9235 | Q40: Wimssy | R40: Till | S40: Organisation | T40: Transaction Out | U40: 7503 | V40: =G40+U40 -> 0 | W40: 0 | X40: 63 | Y40: 0 | Z40: 1 | AA40: 0 | AB40: 166664.8 | AC40: 46267 | AD40: SWEJ7U8N6TUCYEA | AE40: UI2SB4WTFF | AH40: GDC SACCO SOCIETY LTD | AI40: SasaPay | AJ40: ThirdPartyBillPayment | AK40: 639498 | AL40: GDC SACCO SOCIETY LTD | AM40: Safaricom | AN40: W13846194 | AO40: aYPl6RiHfXN2vruqgLUT | AP40: 46267.519 | AQ40: Not Reversed | AR40: api | AS40: SUCCESS | AT40: SP00000 | AU40: Transaction completed successfully
A41: UI2SB4WTFG | B41: 02-09-2026 12:27:48 | C41: 02-09-2026 12:27:48 | D41: Business Pay Bill via API to 639498 - GDC SACCO SOCIETY LTD Acc. 11115552 | E41: Completed | G41: -6784 | H41: 28122725 | I41: true | J41: Business Pay Bill via API | K41: 639498 - GDC SACCO SOCIETY LTD | M41: 11115552 | P41: 9235 | Q41: Wimssy | R41: Till | S41: Organisation | T41: Transaction Out | U41: 6784 | V41: =G41+U41 -> 0 | W41: 0 | X41: 57 | Y41: 0 | Z41: 1 | AA41: 0 | AB41: 174231.8 | AC41: 46267 | AD41: SWEJ7U8N6TT9QK3 | AE41: UI2SB4WTFG | AH41: GDC SACCO SOCIETY LTD | AI41: SasaPay | AJ41: ThirdPartyBillPayment | AK41: 639498 | AL41: GDC SACCO SOCIETY LTD | AM41: Safaricom | AN41: W13846195 | AO41: H0b5UCAKY0DjhQoLS5KT | AP41: 46267.519 | AQ41: Not Reversed | AR41: api | AS41: SUCCESS | AT41: SP00000 | AU41: Transaction completed successfully
A42: UI2SB4WTP5 | B42: 02-09-2026 12:58:00 | C42: 02-09-2026 12:57:58 | D42: Business Pay Bill via API to 247247 - Equity Paybill Account Acc. 0710658542 | E42: Completed | G42: -100 | H42: 6033245.6 | I42: true | J42: Business Pay Bill via API | K42: 247247 - Equity Paybill Account | M42: 0710658542 | P42: 1662340 | Q42: Alex - Alex enterprise | R42: Limited Personal Wallet | T42: Transaction Out | U42: 100 | V42: =G42+U42 -> 0 | W42: 0 | X42: 0 | Y42: 0 | Z42: 0 | AA42: 0 | AB42: 7 | AC42: 46267 | AD42: SWEJ7U8N77MJ9AF | AE42: UI2SB4WTP5 | AH42: Equity Paybill Account | AI42: SasaPay | AJ42: ThirdPartyBillPayment | AK42: 1662340 | AL42: Equity Paybill Account | AM42: Safaricom | AN42: W13846707 | AO42: AWR9BCPJ | AP42: 46267.54 | AQ42: Not Reversed | AS42: SUCCESS | AT42: SP00000 | AU42: Transaction completed successfully
A43: UI2SB4WTQ8 | B43: 02-09-2026 13:01:19 | C43: 02-09-2026 13:01:18 | D43: Business Pay Bill via API to 400200 - Co-operative Bank Money Transfer Acc. 797900 | E43: Completed | G43: -4000 | H43: 6027181.6 | I43: true | J43: Business Pay Bill via API | K43: 400200 - Co-operative Bank Money Transfer | M43: 797900 | P43: 36302 | Q43: Genem international Holdings Limited | R43: Till | S43: Organisation | T43: Transaction Out | U43: 4000 | V43: =G43+U43 -> 0 | W43: 0 | X43: 49 | Y43: 0 | Z43: 1 | AA43: 0 | AB43: 319551 | AC43: 46267 | AD43: SWEJ7U8N97PS7WK | AE43: UI2SB4WTQ8 | AH43: Co | AI43: SasaPay | AJ43: ThirdPartyBillPayment | AK43: 400200 | AL43: Co | AM43: Safaricom | AN43: W13846766 | AO43: 797900 | AP43: 46267.542 | AQ43: Not Reversed | AS43: SUCCESS | AT43: SP00000 | AU43: Transaction completed successfully
A44: UI2SB4WTY4 | B44: 02-09-2026 11:43:47 | C44: 02-09-2026 11:43:47 | D44: Business Buy Goods at 7009701 - VERB EDUCATION LIMITED. via API REF Bill Payment 520420 to 7009703 | E44: Completed | G44: -49350 | H44: 28366364 | I44: true | J44: Business Buy Goods via API | K44: 7009701 - VERB EDUCATION LIMITED. | P44: 520420 | Q44: Cynthia Tiany | R44: Limited Personal Wallet | T44: Transaction Out | U44: 49350 | V44: =G44+U44 -> 0 | W44: 0 | X44: 15 | Y44: 15 | Z44: 0 | AA44: 0 | AB44: 90985.224 | AC44: 46267 | AD44: SWEJ7U8N2YWPBE6 | AE44: UI2SB4WTY4 | AI44: SasaPay | AJ44: ThirdPartyBillPayment | AK44: 520420 | AM44: Safaricom | AN44: W13845440 | AO44: JL1H1FGF | AP44: 46267.488 | AQ44: Not Reversed | AS44: SUCCESS | AT44: SP00000 | AU44: Transaction completed successfully
A45: UI2SB4WU5B | B45: 02-09-2026 12:07:07 | C45: 02-09-2026 12:07:05 | D45: Business Pay Bill via API to 400200 - Co-operative Bank Money Transfer Acc. 01116560460900 | E45: Completed | G45: -18000 | H45: 28346588 | I45: true | J45: Business Pay Bill via API | K45: 400200 - Co-operative Bank Money Transfer | M45: 01116560460900 | O45: 756756 | P45: 254742451519 | Q45: Bethwel Ogot | R45: Limited Personal Wallet | T45: Transaction Out | U45: 18000 | V45: =G45+U45 -> 0 | W45: 0 | X45: 80 | Y45: 0 | Z45: 0 | AA45: 0 | AB45: 49363 | AC45: 46267 | AD45: SWEJ7U8N5V19CC9 | AE45: UI2SB4WU5B | AH45: Co | AI45: SasaPay | AJ45: ThirdPartyBillPayment | AK45: 400200 | AL45: Co | AM45: Safaricom | AN45: W13845825 | AO45: 01116560460900 | AP45: 46267.505 | AQ45: Not Reversed | AR45: user_app | AS45: SUCCESS | AT45: SP00000 | AU45: Transaction completed successfully
A46: UI2SB4WU5V | B46: 02-09-2026 12:10:46 | C46: 02-09-2026 12:10:46 | D46: Business Pay Bill via API to 823244 - Stima SACCO Society ltd Acc. 801047054501 | E46: Completed | G46: -25000 | H46: 28321520 | I46: true | J46: Business Pay Bill via API | K46: 823244 - Stima SACCO Society ltd | M46: 801047054501 | O46: 756756 | P46: 254742451519 | Q46: Bethwel Ogot | R46: Limited Personal Wallet | T46: Transaction Out | U46: 25000 | V46: =G46+U46 -> 0 | W46: 0 | X46: 87 | Y46: 0 | Z46: 0 | AA46: 0 | AB46: 21756 | AC46: 46267 | AD46: SWEJ7U8N51OWDOF | AE46: UI2SB4WU5V | AH46: Stima SACCO Society ltd | AI46: SasaPay | AJ46: ThirdPartyBillPayment | AK46: 823244 | AL46: Stima SACCO Society ltd | AM46: Safaricom | AN46: W13845914 | AO46: 801047054501 | AP46: 46267.507 | AQ46: Not Reversed | AR46: user_app | AS46: SUCCESS | AT46: SP00000 | AU46: Transaction completed successfully
A47: UI2SB4WUA6 | B47: 02-09-2026 12:27:45 | C47: 02-09-2026 12:27:45 | D47: Business Pay Bill via API to 639498 - GDC SACCO SOCIETY LTD Acc. 12525060 | E47: Completed | G47: -6290 | H47: 28286158 | I47: true | J47: Business Pay Bill via API | K47: 639498 - GDC SACCO SOCIETY LTD | M47: 12525060 | P47: 9235 | Q47: Wimssy | R47: Till | S47: Organisation | T47: Transaction Out | U47: 6290 | V47: =G47+U47 -> 0 | W47: 0 | X47: 57 | Y47: 0 | Z47: 1 | AA47: 0 | AB47: 353969 | AC47: 46267 | AD47: SWEJ7U8N6TSEIWI | AE47: UI2SB4WUA6 | AH47: GDC SACCO SOCIETY LTD | AI47: SasaPay | AJ47: ThirdPartyBillPayment | AK47: 639498 | AL47: GDC SACCO SOCIETY LTD | AM47: Safaricom | AN47: W13846184 | AO47: Sv2NxYr0cf9zwrcrcIxh | AP47: 46267.519 | AQ47: Not Reversed | AR47: api | AS47: SUCCESS | AT47: SP00000 | AU47: Transaction completed successfully
A48: UI2SB4WUA7 | B48: 02-09-2026 12:27:51 | C48: 02-09-2026 12:27:50 | D48: Business Pay Bill via API to 639498 - GDC SACCO SOCIETY LTD Acc. 7247746 | E48: Completed | G48: -32230 | H48: 28048640 | I48: true | J48: Business Pay Bill via API | K48: 639498 - GDC SACCO SOCIETY LTD | M48: 7247746 | P48: 9235 | Q48: Wimssy | R48: Till | S48: Organisation | T48: Transaction Out | U48: 32230 | V48: =G48+U48 -> 0 | W48: 0 | X48: 105 | Y48: 0 | Z48: 1 | AA48: 0 | AB48: 64012.6 | AC48: 46267 | AD48: SWEJ7U8N6TVJSN3 | AE48: UI2SB4WUA7 | AH48: GDC SACCO SOCIETY LTD | AI48: SasaPay | AJ48: ThirdPartyBillPayment | AK48: 639498 | AL48: GDC SACCO SOCIETY LTD | AM48: Safaricom | AN48: W13846209 | AO48: fgo8QFiIlJtafTaBocx6 | AP48: 46267.519 | AQ48: Not Reversed | AR48: api | AS48: SUCCESS | AT48: SP00000 | AU48: Transaction completed successfully
A49: UI2SB4WUA8 | B49: 02-09-2026 12:27:51 | C49: 02-09-2026 12:27:51 | D49: Business Pay Bill via API to 639498 - GDC SACCO SOCIETY LTD Acc. 9267377 | E49: Completed | G49: -4219 | H49: 28040150 | I49: true | J49: Business Pay Bill via API | K49: 639498 - GDC SACCO SOCIETY LTD | M49: 9267377 | P49: 9235 | Q49: Wimssy | R49: Till | S49: Organisation | T49: Transaction Out | U49: 4219 | V49: =G49+U49 -> 0 | W49: 0 | X49: 49 | Y49: 0 | Z49: 1 | AA49: 0 | AB49: 55296.6 | AC49: 46267 | AD49: SWEJ7U8N6TV1PBE | AE49: UI2SB4WUA8 | AH49: GDC SACCO SOCIETY LTD | AI49: SasaPay | AJ49: ThirdPartyBillPayment | AK49: 639498 | AL49: GDC SACCO SOCIETY LTD | AM49: Safaricom | AN49: W13846205 | AO49: LcLgcTF4re9fHEIjneE0 | AP49: 46267.519 | AQ49: Not Reversed | AR49: api | AS49: SUCCESS | AT49: SP00000 | AU49: Transaction completed successfully
A50: UI2SB4WVP2 | B50: 02-09-2026 12:26:41 | C50: 02-09-2026 12:26:41 | D50: Business Buy Goods at 7716558 - RUTH NYABONYE via API REF Bill Payment 453498 to 9670109 | E50: Completed | G50: -300 | H50: 28300570 | I50: true | J50: Business Buy Goods via API | K50: 7716558 - RUTH NYABONYE | P50: 453498 | Q50: Alex ian Madara | R50: Limited Personal Wallet | T50: Transaction Out | U50: 300 | V50: =G50+U50 -> 0 | W50: 0 | X50: 10 | Y50: 2 | Z50: 0 | AA50: 0 | AB50: 10003 | AC50: 46267 | AD50: SWEJ7U8N6R2KDGU | AE50: UI2SB4WVP2 | AI50: SasaPay | AJ50: ThirdPartyBillPayment | AK50: 453498 | AM50: Safaricom | AN50: W13846166 | AO50: C7K5CXRC | AP50: 46267.518 | AQ50: Not Reversed | AS50: SUCCESS | AT50: SP00000 | AU50: Transaction completed successfully
A51: UI2SB4WVPJ | B51: 02-09-2026 12:27:45 | C51: 02-09-2026 12:27:44 | D51: Business Pay Bill via API to 639498 - GDC SACCO SOCIETY LTD Acc. 22159541 | E51: Completed | G51: -8060 | H51: 28292502 | I51: true | J51: Business Pay Bill via API | K51: 639498 - GDC SACCO SOCIETY LTD | M51: 22159541 | P51: 9235 | Q51: Wimssy | R51: Till | S51: Organisation | T51: Transaction Out | U51: 8060 | V51: =G51+U51 -> 0 | W51: 0 | X51: 63 | Y51: 0 | Z51: 1 | AA51: 0 | AB51: 360317 | AC51: 46267 | AD51: SWEJ7U8N6TSA69H | AE51: UI2SB4WVPJ | AH51: GDC SACCO SOCIETY LTD | AI51: SasaPay | AJ51: ThirdPartyBillPayment | AK51: 639498 | AL51: GDC SACCO SOCIETY LTD | AM51: Safaricom | AN51: W13846185 | AO51: HtAZvGWUlerLT6OI40kr | AP51: 46267.519 | AQ51: Not Reversed | AR51: api | AS51: SUCCESS | AT51: SP00000 | AU51: Transaction completed successfully
A52: UI2SB4WVPL | B52: 02-09-2026 12:27:47 | C52: 02-09-2026 12:27:47 | D52: Business Pay Bill via API to 639498 - GDC SACCO SOCIETY LTD Acc. 3096601 | E52: Completed | G52: -13927 | H52: 28189678 | I52: true | J52: Business Pay Bill via API | K52: 639498 - GDC SACCO SOCIETY LTD | M52: 3096601 | P52: 9235 | Q52: Wimssy | R52: Till | S52: Organisation | T52: Transaction Out | U52: 13927 | V52: =G52+U52 -> 0 | W52: 0 | X52: 72 | Y52: 0 | Z52: 1 | AA52: 0 | AB52: 210407.8 | AC52: 46267 | AD52: SWEJ7U8N6TTD9GG | AE52: UI2SB4WVPL | AH52: GDC SACCO SOCIETY LTD | AI52: SasaPay | AJ52: ThirdPartyBillPayment | AK52: 639498 | AL52: GDC SACCO SOCIETY LTD | AM52: Safaricom | AN52: W13846190 | AO52: gFf7DYaKyKI8oYukw1Hd | AP52: 46267.519 | AQ52: Not Reversed | AR52: api | AS52: SUCCESS | AT52: SP00000 | AU52: Transaction completed successfully
A53: UI2SB4WVPM | B53: 02-09-2026 12:27:47 | C53: 02-09-2026 12:27:47 | D53: Business Pay Bill via API to 639498 - GDC SACCO SOCIETY LTD Acc. 14686451 | E53: Completed | G53: -13001 | H53: 28176614 | I53: true | J53: Business Pay Bill via API | K53: 639498 - GDC SACCO SOCIETY LTD | M53: 14686451 | P53: 9235 | Q53: Wimssy | R53: Till | S53: Organisation | T53: Transaction Out | U53: 13001 | V53: =G53+U53 -> 0 | W53: 0 | X53: 72 | Y53: 0 | Z53: 1 | AA53: 0 | AB53: 195532.8 | AC53: 46267 | AD53: SWEJ7U8N6TTZMHA | AE53: UI2SB4WVPM | AH53: GDC SACCO SOCIETY LTD | AI53: SasaPay | AJ53: ThirdPartyBillPayment | AK53: 639498 | AL53: GDC SACCO SOCIETY LTD | AM53: Safaricom | AN53: W13846192 | AO53: GgRwl2pVCk6GNtmoEZyX | AP53: 46267.519 | AQ53: Not Reversed | AR53: api | AS53: SUCCESS | AT53: SP00000 | AU53: Transaction completed successfully
A54: UI2SB4WVPN | B54: 02-09-2026 12:27:48 | C54: 02-09-2026 12:27:48 | D54: Business Pay Bill via API to 639498 - GDC SACCO SOCIETY LTD Acc. 9861337 | E54: Completed | G54: -7076 | H54: 28108044 | I54: true | J54: Business Pay Bill via API | K54: 639498 - GDC SACCO SOCIETY LTD | M54: 9861337 | P54: 9235 | Q54: Wimssy | R54: Till | S54: Organisation | T54: Transaction Out | U54: 7076 | V54: =G54+U54 -> 0 | W54: 0 | X54: 57 | Y54: 0 | Z54: 1 | AA54: 0 | AB54: 159530.8 | AC54: 46267 | AD54: SWEJ7U8N6TUF9BL | AE54: UI2SB4WVPN | AH54: GDC SACCO SOCIETY LTD | AI54: SasaPay | AJ54: ThirdPartyBillPayment | AK54: 639498 | AL54: GDC SACCO SOCIETY LTD | AM54: Safaricom | AN54: W13846197 | AO54: ynZSqMJlSM3O6dQQ9xxi | AP54: 46267.519 | AQ54: Not Reversed | AR54: api | AS54: SUCCESS | AT54: SP00000 | AU54: Transaction completed successfully
A55: UI2SB4WVPO | B55: 02-09-2026 12:27:49 | C55: 02-09-2026 12:27:49 | D55: Business Pay Bill via API to 639498 - GDC SACCO SOCIETY LTD Acc. 4242139 | E55: Completed | G55: -15239 | H55: 28091239 | I55: true | J55: Business Pay Bill via API | K55: 639498 - GDC SACCO SOCIETY LTD | M55: 4242139 | P55: 9235 | Q55: Wimssy | R55: Till | S55: Organisation | T55: Transaction Out | U55: 15239 | V55: =G55+U55 -> 0 | W55: 0 | X55: 82 | Y55: 0 | Z55: 1 | AA55: 0 | AB55: 142682.8 | AC55: 46267 | AD55: SWEJ7U8N6TUOLEQ | AE55: UI2SB4WVPO | AH55: GDC SACCO SOCIETY LTD | AI55: SasaPay | AJ55: ThirdPartyBillPayment | AK55: 639498 | AL55: GDC SACCO SOCIETY LTD | AM55: Safaricom | AN55: W13846200 | AO55: bxcvV3YF1JrYDUrzaghP | AP55: 46267.519 | AQ55: Not Reversed | AR55: api | AS55: SUCCESS | AT55: SP00000 | AU55: Transaction completed successfully
A56: UI2SB4WVPP | B56: 02-09-2026 12:27:50 | C56: 02-09-2026 12:27:49 | D56: Business Pay Bill via API to 644700 - TAI SACCO SOCIETY LIMITED Acc. 001007888801 | E56: Completed | G56: -6935 | H56: 28080870 | I56: true | J56: Business Pay Bill via API | K56: 644700 - TAI SACCO SOCIETY LIMITED | M56: 001007888801 | P56: 9235 | Q56: Wimssy | R56: Till | S56: Organisation | T56: Transaction Out | U56: 6935 | V56: =G56+U56 -> 0 | W56: 0 | X56: 57 | Y56: 0 | Z56: 1 | AA56: 0 | AB56: 181073.8 | AC56: 46267 | AD56: SWEJ7U8N6TT55R3 | AE56: UI2SB4WVPP | AH56: TAI SACCO SOCIETY LIMITED | AI56: SasaPay | AJ56: ThirdPartyBillPayment | AK56: 644700 | AL56: TAI SACCO SOCIETY LIMITED | AM56: Safaricom | AN56: W13846193 | AO56: E6BrJP3lKWBF1dLtC8Lf | AP56: 46267.519 | AQ56: Not Reversed | AR56: api | AS56: SUCCESS | AT56: SP00000 | AU56: Transaction completed successfully
A57: UI2SB4WVPQ | B57: 02-09-2026 12:27:51 | C57: 02-09-2026 12:27:51 | D57: Business Pay Bill via API to 639498 - GDC SACCO SOCIETY LTD Acc. 23614427 | E57: Completed | G57: -3762 | H57: 28044408 | I57: true | J57: Business Pay Bill via API | K57: 639498 - GDC SACCO SOCIETY LTD | M57: 23614427 | P57: 9235 | Q57: Wimssy | R57: Till | S57: Organisation | T57: Transaction Out | U57: 3762 | V57: =G57+U57 -> 0 | W57: 0 | X57: 49 | Y57: 0 | Z57: 1 | AA57: 0 | AB57: 59726.6 | AC57: 46267 | AD57: SWEJ7U8N6TVU4VS | AE57: UI2SB4WVPQ | AH57: GDC SACCO SOCIETY LTD | AI57: SasaPay | AJ57: ThirdPartyBillPayment | AK57: 639498 | AL57: GDC SACCO SOCIETY LTD | AM57: Safaricom | AN57: W13846213 | AO57: UfxK8yA9KNdAR1wSvdlg | AP57: 46267.519 | AQ57: Not Reversed | AR57: api | AS57: SUCCESS | AT57: SP00000 | AU57: Transaction completed successfully
A58: UI2SB4WVPS | B58: 02-09-2026 12:27:52 | C58: 02-09-2026 12:27:52 | D58: Business Pay Bill via API to 639498 - GDC SACCO SOCIETY LTD Acc. 20807788 | E58: Completed | G58: -15332 | H58: 28024779 | I58: true | J58: Business Pay Bill via API | K58: 639498 - GDC SACCO SOCIETY LTD | M58: 20807788 | P58: 9235 | Q58: Wimssy | R58: Till | S58: Organisation | T58: Transaction Out | U58: 15332 | V58: =G58+U58 -> 0 | W58: 0 | X58: 82 | Y58: 0 | Z58: 1 | AA58: 0 | AB58: 37462 | AC58: 46267 | AD58: SWEJ7U8N6TV9WO6 | AE58: UI2SB4WVPS | AH58: GDC SACCO SOCIETY LTD | AI58: SasaPay | AJ58: ThirdPartyBillPayment | AK58: 639498 | AL58: GDC SACCO SOCIETY LTD | AM58: Safaricom | AN58: W13846208 | AO58: JPBjAHrB8zUwAAQnZCZa | AP58: 46267.519 | AQ58: Not Reversed | AR58: api | AS58: SUCCESS | AT58: SP00000 | AU58: Transaction completed successfully
A59: UI2SB4WW8H | B59: 02-09-2026 13:26:50 | C59: 02-09-2026 13:26:50 | D59: Business Buy Goods at 7526458 - Quick Mart Outering 2 via API REF Bill Payment 110311 to 9481425 | E59: Completed | G59: -17688 | H59: 6009425.6 | I59: true | J59: Business Buy Goods via API | K59: 7526458 - Quick Mart Outering 2 | P59: 110311 | Q59: Bag Ware Limited | R59: PayBill-CustomerOption | S59: Organisation | T59: Transaction Out | U59: 17688 | V59: =G59+U59 -> 0 | W59: 0 | X59: 15 | Y59: 0 | Z59: 1 | AA59: 0 | AB59: 627712 | AC59: 46267 | AD59: SWEJ7U8OBDLNR96 | AE59: UI2SB4WW8H | AI59: SasaPay | AJ59: ThirdPartyBillPayment | AK59: 9481425 | AM59: Safaricom | AN59: W13847227 | AO59: GENERAL SUPPLIES-W/SHOP SHOPPING | AP59: 46267.56 | AQ59: Not Reversed | AS59: SUCCESS | AT59: SP00000 | AU59: Transaction completed successfully
A60: UI2SB4WWNG | B60: 02-09-2026 14:16:35 | C60: 02-09-2026 14:16:35 | D60: Business Buy Goods at 7248058 - RUBIS KOMAROCK via API REF Bill Payment 80417 to 9246253 | E60: Completed | G60: -3900 | H60: 5961709.6 | I60: true | J60: Business Buy Goods via API | K60: 7248058 - RUBIS KOMAROCK | P60: 80417 | Q60: KBQ 188C | R60: Matatu | S60: Organisation | T60: Transaction Out | U60: 3900 | V60: =G60+U60 -> 0 | W60: 0 | X60: 15 | Y60: 0 | Z60: 1 | AA60: 0 | AB60: 3013.814 | AC60: 46267 | AD60: SWEJ7U8OFH7I1GQ | AE60: UI2SB4WWNG | AI60: SasaPay | AJ60: ThirdPartyBillPayment | AK60: 9246253 | AM60: Safaricom | AN60: W13847836 | AO60: Fuel | AP60: 46267.594 | AQ60: Not Reversed | AS60: SUCCESS | AT60: SP00000 | AU60: Transaction completed successfully
A61: UI2SB4WWT1 | B61: 02-09-2026 14:31:58 | C61: 02-09-2026 14:31:58 | D61: Business Pay Bill via API to 222111 - Family Bank Pesa Pap Acc. 2314672 | E61: Completed | G61: -6500 | H61: 5867952.6 | I61: true | J61: Business Pay Bill via API | K61: 222111 - Family Bank Pesa Pap | M61: 2314672 | P61: 1592688 | Q61: EVERLYN TIANY | R61: Limited Personal Wallet | T61: Transaction Out | U61: 6500 | V61: =G61+U61 -> 0 | W61: 0 | X61: 57 | Y61: 16 | Z61: 0 | AA61: 0 | AB61: 457 | AC61: 46267 | AD61: SWEJ7U8OF7D21VV | AE61: UI2SB4WWT1 | AH61: Family Bank Pesa Pap | AI61: SasaPay | AJ61: ThirdPartyBillPayment | AK61: 1592688 | AL61: Family Bank Pesa Pap | AM61: Safaricom | AN61: W13848025 | AO61: WGGXZA1P | AP61: 46267.605 | AQ61: Not Reversed | AS61: SUCCESS | AT61: SP00000 | AU61: Transaction completed successfully
A62: UI2SB4WWVH | B62: 02-09-2026 12:27:45 | C62: 02-09-2026 12:27:45 | D62: Business Pay Bill via API to 639498 - GDC SACCO SOCIETY LTD Acc. 4924978 | E62: Completed | G62: -82390 | H62: 28203720 | I62: true | J62: Business Pay Bill via API | K62: 639498 - GDC SACCO SOCIETY LTD | M62: 4924978 | P62: 9235 | Q62: Wimssy | R62: Till | S62: Organisation | T62: Transaction Out | U62: 82390 | V62: =G62+U62 -> 0 | W62: 0 | X62: 136 | Y62: 0 | Z62: 1 | AA62: 0 | AB62: 262223.8 | AC62: 46267 | AD62: SWEJ7U8N6TSR19K | AE62: UI2SB4WWVH | AH62: GDC SACCO SOCIETY LTD | AI62: SasaPay | AJ62: ThirdPartyBillPayment | AK62: 639498 | AL62: GDC SACCO SOCIETY LTD | AM62: Safaricom | AN62: W13846187 | AO62: VWDgWMUYuIvypd6DXdl1 | AP62: 46267.519 | AQ62: Not Reversed | AR62: api | AS62: SUCCESS | AT62: SP00000 | AU62: Transaction completed successfully
A63: UI2SB4WWVI | B63: 02-09-2026 12:27:47 | C63: 02-09-2026 12:27:47 | D63: Business Pay Bill via API to 639498 - GDC SACCO SOCIETY LTD Acc. 34274749 | E63: Completed | G63: -37690 | H63: 28138861 | I63: true | J63: Business Pay Bill via API | K63: 639498 - GDC SACCO SOCIETY LTD | M63: 34274749 | P63: 9235 | Q63: Wimssy | R63: Till | S63: Organisation | T63: Transaction Out | U63: 37690 | V63: =G63+U63 -> 0 | W63: 0 | X63: 125 | Y63: 0 | Z63: 1 | AA63: 0 | AB63: 224407.8 | AC63: 46267 | AD63: SWEJ7U8N6TSVOOP | AE63: UI2SB4WWVI | AH63: GDC SACCO SOCIETY LTD | AI63: SasaPay | AJ63: ThirdPartyBillPayment | AK63: 639498 | AL63: GDC SACCO SOCIETY LTD | AM63: Safaricom | AN63: W13846189 | AO63: OQaJazMHW4yAGHd61wIa | AP63: 46267.519 | AQ63: Not Reversed | AR63: api | AS63: SUCCESS | AT63: SP00000 | AU63: Transaction completed successfully
A64: UI2SB4WWVJ | B64: 02-09-2026 12:27:48 | C64: 02-09-2026 12:27:48 | D64: Business Pay Bill via API to 639498 - GDC SACCO SOCIETY LTD Acc. 27205040 | E64: Completed | G64: -1765 | H64: 28129534 | I64: true | J64: Business Pay Bill via API | K64: 639498 - GDC SACCO SOCIETY LTD | M64: 27205040 | P64: 9235 | Q64: Wimssy | R64: Till | S64: Organisation | T64: Transaction Out | U64: 1765 | V64: =G64+U64 -> 0 | W64: 0 | X64: 35 | Y64: 0 | Z64: 1 | AA64: 0 | AB64: 208606.8 | AC64: 46267 | AD64: SWEJ7U8N6TTWH4M | AE64: UI2SB4WWVJ | AH64: GDC SACCO SOCIETY LTD | AI64: SasaPay | AJ64: ThirdPartyBillPayment | AK64: 639498 | AL64: GDC SACCO SOCIETY LTD | AM64: Safaricom | AN64: W13846188 | AO64: ejaa1UcYSqsPKEBROinM | AP64: 46267.519 | AQ64: Not Reversed | AR64: api | AS64: SUCCESS | AT64: SP00000 | AU64: Transaction completed successfully
A65: UI2SB4WX5P | B65: 02-09-2026 12:58:23 | C65: 02-09-2026 12:58:23 | D65: Business Buy Goods at 5473986 - SLIM ENERGY LIMITED via API REF Bill Payment 36302 to 4961328 | E65: Completed | G65: -2000 | H65: 6031245.6 | I65: true | J65: Business Buy Goods via API | K65: 5473986 - SLIM ENERGY LIMITED | P65: 36302 | Q65: Genem international Holdings Limited | R65: Till | S65: Organisation | T65: Transaction Out | U65: 2000 | V65: =G65+U65 -> 0 | W65: 0 | X65: 10 | Y65: 0 | Z65: 1 | AA65: 0 | AB65: 323601 | AC65: 46267 | AD65: SWEJ7U8N78O2BJW | AE65: UI2SB4WX5P | AI65: SasaPay | AJ65: ThirdPartyBillPayment | AK65: 4961328 | AM65: Safaricom | AN65: W13846714 | AO65: nyeri van fuel | AP65: 46267.54 | AQ65: Not Reversed | AS65: SUCCESS | AT65: SP00000 | AU65: Transaction completed successfully
A66: UI2SB4WXB3 | B66: 02-09-2026 13:14:19 | C66: 02-09-2026 13:14:19 | D66: Business Buy Goods at 6010044 - Jesro cafe via Kopo Kopo via API REF Bill Payment 413570 to 9921299 | E66: Completed | G66: -65 | H66: 6027116.6 | I66: true | J66: Business Buy Goods via API | K66: 6010044 - Jesro cafe via Kopo Kopo | P66: 413570 | Q66: Sheldon Onzere | R66: Limited Personal Wallet | T66: Transaction Out | U66: 65 | V66: =G66+U66 -> 0 | W66: 0 | X66: 0 | Y66: 0 | Z66: 0 | AA66: 0 | AB66: 121 | AC66: 46267 | AD66: SWEJ7U8OAS8PSI1 | AE66: UI2SB4WXB3 | AI66: SasaPay | AJ66: ThirdPartyBillPayment | AK66: 413570 | AM66: Safaricom | AN66: W13847021 | AO66: ZYV2VOLH | AP66: 46267.551 | AQ66: Not Reversed | AS66: SUCCESS | AT66: SP00000 | AU66: Transaction completed successfully
A67: UI2SB4WXT7 | B67: 02-09-2026 14:11:29 | C67: 02-09-2026 14:11:29 | D67: Business Pay Bill via API to 583674 - GURU NANAK RAMGARHIA SIKH HOSPITAL Acc. sarah | E67: Completed | G67: -1000 | H67: 5965622.6 | I67: true | J67: Business Pay Bill via API | K67: 583674 - GURU NANAK RAMGARHIA SIKH HOSPITAL | M67: sarah | P67: 1003020 | Q67: Stephen - Viewtech Afya | R67: Till-CustomerOption | T67: Transaction Out | U67: 1000 | V67: =G67+U67 -> 0 | W67: 0 | X67: 20 | Y67: 10 | Z67: 0 | AA67: 0 | AB67: 40888.93 | AC67: 46267 | AD67: SWEJ7U8OE9T6GNB | AE67: UI2SB4WXT7 | AH67: GURU NANAK RAMGARHIA SIKH HOSPITAL | AI67: SasaPay | AJ67: ThirdPartyBillPayment | AK67: 1003020 | AL67: GURU NANAK RAMGARHIA SIKH HOSPITAL | AM67: Safaricom | AN67: W13847792 | AO67: MF750834 | AP67: 46267.591 | AQ67: Not Reversed | AS67: SUCCESS | AT67: SP00000 | AU67: Transaction completed successfully
A68: UI2SB4WYS1 | B68: 02-09-2026 13:32:55 | C68: 02-09-2026 13:32:55 | D68: Business Pay Bill via API to 714777 - LOOP C2B Acc. 0757455384 | E68: Completed | G68: -450 | H68: 6008907.6 | I68: true | J68: Business Pay Bill via API | K68: 714777 - LOOP C2B | M68: 0757455384 | O68: 756756 | P68: 254757455384 | Q68: John Wasonga | R68: Limited Personal Wallet | T68: Transaction Out | U68: 450 | V68: =G68+U68 -> 0 | W68: 0 | X68: 10 | Y68: 0 | Z68: 0 | AA68: 0 | AB68: 23 | AC68: 46267 | AD68: SWEJ7U8OBNLYLPT | AE68: UI2SB4WYS1 | AH68: LOOP C2B | AI68: SasaPay | AJ68: ThirdPartyBillPayment | AK68: 714777 | AL68: LOOP C2B | AM68: Safaricom | AN68: W13847347 | AO68: 0757455384 | AP68: 46267.564 | AQ68: Not Reversed | AR68: user_app | AS68: SUCCESS | AT68: SP00000 | AU68: Transaction completed successfully
A69: UI2SB4WYTQ | B69: 02-09-2026 13:37:34 | C69: 02-09-2026 13:37:33 | D69: Business Buy Goods at 4256547 - JAMES MWANIKI NJUNGE via API REF Bill Payment 164621 to 3510637 | E69: Completed | G69: -80 | H69: 6008819.6 | I69: true | J69: Business Buy Goods via API | K69: 4256547 - JAMES MWANIKI NJUNGE | O69: 756756 | P69: 164621 | Q69: Faith - Tasty treats | R69: Biashara Wallet | T69: Transaction Out | U69: 80 | V69: =G69+U69 -> 0 | W69: 0 | X69: 0 | Y69: 0 | Z69: 0 | AA69: 0 | AB69: 7235.94 | AC69: 46267 | AD69: SWEJ7U8OBVITCVQ | AE69: UI2SB4WYTQ | AI69: SasaPay | AJ69: ThirdPartyBillPayment | AK69: 3510637 | AM69: Safaricom | AN69: W13847411 | AO69: W13847411 | AP69: 46267.567 | AQ69: Not Reversed | AR69: user_app | AS69: SUCCESS | AT69: SP00000 | AU69: Transaction completed successfully
A70: UI2SB4WZ35 | B70: 02-09-2026 14:08:07 | C70: 02-09-2026 14:08:07 | D70: Business Buy Goods at 5342630 - CARREFOUR RUNDA MALL 04 via API REF Bill Payment 469005 to 4699876 | E70: Completed | G70: -2176 | H70: 5966647.6 | I70: true | J70: Business Buy Goods via API | K70: 5342630 - CARREFOUR RUNDA MALL 04 | P70: 469005 | Q70: German Experts- Petty cash | R70: Till | S70: Organisation | T70: Transaction Out | U70: 2176 | V70: =G70+U70 -> 0 | W70: 0 | X70: 10 | Y70: 0 | Z70: 1 | AA70: 0 | AB70: 3283.2 | AC70: 46267 | AD70: SWEJ7U8OE4IFA0V | AE70: UI2SB4WZ35 | AI70: SasaPay | AJ70: ThirdPartyBillPayment | AK70: 4699876 | AM70: Safaricom | AN70: W13847742 | AO70: W13847742 | AP70: 46267.589 | AQ70: Not Reversed | AR70: merchant_portal | AS70: SUCCESS | AT70: SP00000 | AU70: Transaction completed successfully
A71: UI2SB4WZQJ | B71: 02-09-2026 15:29:40 | C71: 02-09-2026 15:29:40 | D71: Business Buy Goods at 7293737 - TANGO REPUBLIK via API REF Bill Payment 254795390620 to 5291253 | E71: Completed | G71: -600 | H71: 5547988.6 | I71: true | J71: Business Buy Goods via API | K71: 7293737 - TANGO REPUBLIK | O71: 756756 | P71: 254795390620 | Q71: Caleb Wekesa | R71: Wallet-Personal | T71: Transaction Out | U71: 600 | V71: =G71+U71 -> 0 | W71: 0 | X71: 10 | Y71: 0 | Z71: 0 | AA71: 0 | AB71: 28619 | AC71: 46267 | AD71: SWEJ7U8OKO5NYAV | AE71: UI2SB4WZQJ | AI71: SasaPay | AJ71: ThirdPartyBillPayment | AK71: 5291253 | AM71: Safaricom | AN71: W13848758 | AO71: W13848758 | AP71: 46267.645 | AQ71: Not Reversed | AR71: user_app | AS71: SUCCESS | AT71: SP00000 | AU71: Transaction completed successfully
A72: UI2SB4X15B | B72: 02-09-2026 15:13:14 | C72: 02-09-2026 15:13:14 | D72: Business Pay Bill via API to 4004309 - CASH N CARRY ESSENTIALS LIMITED Acc. C | E72: Completed | G72: -500 | H72: 5854644.6 | I72: true | J72: Business Pay Bill via API | K72: 4004309 - CASH N CARRY ESSENTIALS LIMITED | M72: C | O72: 756756 | P72: 70737 | Q72: Savings | R72: Personal Sub Wallet | T72: Transaction Out | U72: 500 | V72: =G72+U72 -> 0 | W72: 0 | X72: 10 | Y72: 0 | Z72: 0 | AA72: 0 | AB72: 4875 | AC72: 46267 | AD72: SWEJ7U8OJX9UHO4 | AE72: UI2SB4X15B | AH72: CASH N CARRY ESSENTIALS LIMITED | AI72: SasaPay | AJ72: ThirdPartyBillPayment | AK72: 4004309 | AL72: CASH N CARRY ESSENTIALS LIMITED | AM72: Safaricom | AN72: W13848523 | AO72: C | AP72: 46267.634 | AQ72: Not Reversed | AR72: user_app | AS72: SUCCESS | AT72: SP00000 | AU72: Transaction completed successfully
A73: UI2SB4X18B | B73: 02-09-2026 15:25:42 | C73: 02-09-2026 15:25:42 | D73: Business Buy Goods at 7288641 - RUBIS KAKAMEGA ROAD via API REF Bill Payment 520420 to 527874 | E73: Completed | G73: -6000 | H73: 5848636.6 | I73: true | J73: Business Buy Goods via API | K73: 7288641 - RUBIS KAKAMEGA ROAD | P73: 520420 | Q73: Cynthia Tiany | R73: Limited Personal Wallet | T73: Transaction Out | U73: 6000 | V73: =G73+U73 -> 0 | W73: 0 | X73: 15 | Y73: 16 | Z73: 0 | AA73: 0 | AB73: 82419.224 | AC73: 46267 | AD73: SWEJ7U8OKIKW4NF | AE73: UI2SB4X18B | AI73: SasaPay | AJ73: ThirdPartyBillPayment | AK73: 520420 | AM73: Safaricom | AN73: W13848706 | AO73: KKWCGKN0 | AP73: 46267.642 | AQ73: Not Reversed | AS73: SUCCESS | AT73: SP00000 | AU73: Transaction completed successfully
A74: UI2SB4X23C | B74: 02-09-2026 14:07:24 | C74: 02-09-2026 14:07:22 | D74: Business Pay Bill via API to 400200 - Co-operative Bank Money Transfer Acc. 40056003 | E74: Completed | G74: -38999 | H74: 5968929.6 | I74: true | J74: Business Pay Bill via API | K74: 400200 - Co-operative Bank Money Transfer | M74: 40056003 | P74: 379411 | Q74: XWIFT | R74: Till | T74: Transaction Out | U74: 38999 | V74: =G74+U74 -> 0 | W74: 0 | X74: 125 | Y74: 0 | Z74: 1 | AA74: 0 | AB74: 176460.87 | AC74: 46267 | AD74: SWEJ7U8OE23VSQ4 | AE74: UI2SB4X23C | AH74: Co | AI74: SasaPay | AJ74: ThirdPartyBillPayment | AK74: 400200 | AL74: Co | AM74: Safaricom | AN74: W13847738 | AO74: f538e064-b42b-4f5b-bf17-5230e9543bcb | AP74: 46267.588 | AQ74: Not Reversed | AR74: api | AS74: SUCCESS | AT74: SP00000 | AU74: Transaction completed successfully
A75: UI2SB4X2HV | B75: 02-09-2026 14:56:16 | C75: 02-09-2026 14:56:13 | D75: Business Pay Bill via API to 852648 - FORTUNE SACCO C2B Acc. 66950 | E75: Completed | G75: -1170 | H75: 5856662.6 | I75: true | J75: Business Pay Bill via API | K75: 852648 - FORTUNE SACCO C2B | M75: 66950 | O75: 756756 | P75: 254706564824 | Q75: Nicholas Omondi | R75: Limited Personal Wallet | T75: Transaction Out | U75: 1170 | V75: =G75+U75 -> 0 | W75: 0 | X75: 25 | Y75: 0 | Z75: 0 | AA75: 0 | AB75: 52892 | AC75: 46267 | AD75: SWEJ7U8OHBZXOI4 | AE75: UI2SB4X2HV | AH75: FORTUNE SACCO C2B | AI75: SasaPay | AJ75: ThirdPartyBillPayment | AK75: 852648 | AL75: FORTUNE SACCO C2B | AM75: Safaricom | AN75: W13848260 | AO75: 66950 | AP75: 46267.622 | AQ75: Not Reversed | AR75: user_app | AS75: SUCCESS | AT75: SP00000 | AU75: Transaction completed successfully
A76: UI2SB4X2M3 | B76: 02-09-2026 15:10:45 | C76: 02-09-2026 15:10:45 | D76: Business Buy Goods at 6818183 - Galana Energies Station - Runda Mall via API REF Bill Payment 469005 to 4293700 | E76: Completed | G76: -1500 | H76: 5855162.6 | I76: true | J76: Business Buy Goods via API | K76: 6818183 - Galana Energies Station - Runda Mall | P76: 469005 | Q76: German Experts- Petty cash | R76: Till | S76: Organisation | T76: Transaction Out | U76: 1500 | V76: =G76+U76 -> 0 | W76: 0 | X76: 10 | Y76: 0 | Z76: 1 | AA76: 0 | AB76: 1772.2 | AC76: 46267 | AD76: SWEJ7U8OJTTVY99 | AE76: UI2SB4X2M3 | AI76: SasaPay | AJ76: ThirdPartyBillPayment | AK76: 4293700 | AM76: Safaricom | AN76: W13848498 | AO76: W13848498 | AP76: 46267.632 | AQ76: Not Reversed | AR76: merchant_portal | AS76: SUCCESS | AT76: SP00000 | AU76: Transaction completed successfully
A77: UI2SB4X2RH | B77: 02-09-2026 15:29:17 | C77: 02-09-2026 15:29:17 | D77: Business Buy Goods at 518025 - SAMCHI TELCOM-MTWAPA via API REF Bill Payment 706931 to 519025 | E77: Completed | G77: -200000 | H77: 5648588.6 | I77: true | J77: Business Buy Goods via API | K77: 518025 - SAMCHI TELCOM-MTWAPA | P77: 706931 | Q77: Forward Airtime Limited | R77: Till | S77: Organisation | T77: Transaction Out | U77: 200000 | V77: =G77+U77 -> 0 | W77: 0 | X77: 15 | Y77: 0 | Z77: 1 | AA77: 0 | AB77: 195628.96 | AC77: 46267 | AD77: SWEJ7U8OKOR1SKU | AE77: UI2SB4X2RH | AI77: SasaPay | AJ77: ThirdPartyBillPayment | AK77: 519025 | AM77: Safaricom | AN77: W13848751 | AO77: lines | AP77: 46267.645 | AQ77: Not Reversed | AS77: SUCCESS | AT77: SP00000 | AU77: Transaction completed successfully
A78: UI2SB4X2UU | B78: 02-09-2026 15:39:39 | C78: 02-09-2026 15:39:39 | D78: Business Buy Goods at 5383424 - THE LAUNDRY ROOM via API REF Bill Payment 254746383172 to 4788768 | E78: Completed | G78: -1500 | H78: 5534912.6 | I78: true | J78: Business Buy Goods via API | K78: 5383424 - THE LAUNDRY ROOM | O78: 756756 | P78: 254746383172 | Q78: Esther Nganga | R78: Limited Personal Wallet | T78: Transaction Out | U78: 1500 | V78: =G78+U78 -> 0 | W78: 0 | X78: 10 | Y78: 0 | Z78: 0 | AA78: 0 | AB78: 15179 | AC78: 46267 | AD78: SWEJ7U8OK5OJN1I | AE78: UI2SB4X2UU | AI78: SasaPay | AJ78: ThirdPartyBillPayment | AK78: 4788768 | AM78: Safaricom | AN78: W13848918 | AO78: W13848918 | AP78: 46267.652 | AQ78: Not Reversed | AR78: user_app | AS78: SUCCESS | AT78: SP00000 | AU78: Transaction completed successfully
A79: UI2SB4X3BX | B79: 02-09-2026 13:39:14 | C79: 02-09-2026 13:39:14 | D79: Business Buy Goods at 7400718 - DIVINE MINIMART 02 via API REF Bill Payment 164621 to 9362497 | E79: Completed | G79: -875 | H79: 6007941.6 | I79: true | J79: Business Buy Goods via API | K79: 7400718 - DIVINE MINIMART 02 | O79: 756756 | P79: 164621 | Q79: Faith - Tasty treats | R79: Biashara Wallet | T79: Transaction Out | U79: 875 | V79: =G79+U79 -> 0 | W79: 0 | X79: 10 | Y79: 0 | Z79: 0 | AA79: 0 | AB79: 6350.94 | AC79: 46267 | AD79: SWEJ7U8OBYIG965 | AE79: UI2SB4X3BX | AI79: SasaPay | AJ79: ThirdPartyBillPayment | AK79: 9362497 | AM79: Safaricom | AN79: W13847439 | AO79: W13847439 | AP79: 46267.569 | AQ79: Not Reversed | AR79: user_app | AS79: SUCCESS | AT79: SP00000 | AU79: Transaction completed successfully
A80: UI2SB4X3NJ | B80: 02-09-2026 14:20:44 | C80: 02-09-2026 14:20:44 | D80: Business Buy Goods at 9709200 - JOSEPH MURIUNGI M'KACHIUKI via API REF Bill Payment 254748897486 to 3253086 | E80: Completed | G80: -100 | H80: 5961570.6 | I80: true | J80: Business Buy Goods via API | K80: 9709200 - JOSEPH MURIUNGI M'KACHIUKI | O80: 756756 | P80: 254748897486 | Q80: Moses Otieno | R80: Limited Personal Wallet | T80: Transaction Out | U80: 100 | V80: =G80+U80 -> 0 | W80: 0 | X80: 0 | Y80: 0 | Z80: 0 | AA80: 0 | AB80: 100 | AC80: 46267 | AD80: SWEJ7U8OFOYLWNK | AE80: UI2SB4X3NJ | AI80: SasaPay | AJ80: ThirdPartyBillPayment | AK80: 3253086 | AM80: Safaricom | AN80: W13847903 | AO80: W13847903 | AP80: 46267.597 | AQ80: Not Reversed | AR80: user_app | AS80: SUCCESS | AT80: SP00000 | AU80: Transaction completed successfully
A81: UI2SB4X3QM | B81: 02-09-2026 14:29:07 | C81: 02-09-2026 14:29:05 | D81: Business Pay Bill via API to 303030 - Absa Bank Kenya PLC Acc. H9QB# | E81: Completed | G81: -87000 | H81: 5874452.6 | I81: true | J81: Business Pay Bill via API | K81: 303030 - Absa Bank Kenya PLC | M81: H9QB# | P81: 458445 | Q81: BUYSIMU TECHNOLOGIES LIMITED | R81: Till | S81: Organisation | T81: Transaction Out | U81: 87000 | V81: =G81+U81 -> 0 | W81: 0 | X81: 136 | Y81: 0 | Z81: 1 | AA81: 0 | AB81: 308219.69 | AC81: 46267 | AD81: SWEJ7U8OF27J3PQ | AE81: UI2SB4X3QM | AH81: Absa Bank Kenya PLC | AI81: SasaPay | AJ81: ThirdPartyBillPayment | AK81: 303030 | AL81: Absa Bank Kenya PLC | AM81: Safaricom | AN81: W13847982 | AO81: 18757 | AP81: 46267.603 | AQ81: Not Reversed | AR81: api | AS81: SUCCESS | AT81: SP00000 | AU81: Transaction completed successfully
A82: UI2SB4X4NK | B82: 02-09-2026 14:41:04 | C82: 02-09-2026 14:41:04 | D82: Business Buy Goods at 3538119 - ALPHIS INVESTMENT COMPANY LIMITED 1 via API REF Bill Payment 414936 to 5663432 | E82: Completed | G82: -10000 | H82: 5857904.6 | I82: true | J82: Business Buy Goods via API | K82: 3538119 - ALPHIS INVESTMENT COMPANY LIMITED 1 | P82: 414936 | Q82: John Slater | R82: Limited Personal Wallet | T82: Transaction Out | U82: 10000 | V82: =G82+U82 -> 0 | W82: 0 | X82: 15 | Y82: 22 | Z82: 0 | AA82: 0 | AB82: 11289 | AC82: 46267 | AD82: SWEJ7U8OGM0UAAH | AE82: UI2SB4X4NK | AI82: SasaPay | AJ82: ThirdPartyBillPayment | AK82: 414936 | AM82: Safaricom | AN82: W13848119 | AO82: F6FWVFSR | AP82: 46267.612 | AQ82: Not Reversed | AS82: SUCCESS | AT82: SP00000 | AU82: Transaction completed successfully
A83: UI2SB4X5L3 | B83: 02-09-2026 16:25:26 | C83: 02-09-2026 16:25:26 | D83: Business Pay Bill via API to 765244 - Bingwa Sacco Society Ltd C2B Acc. 22552661 | E83: Completed | G83: -10346 | H83: 5372951.6 | I83: true | J83: Business Pay Bill via API | K83: 765244 - Bingwa Sacco Society Ltd C2B | M83: 22552661 | P83: 395390 | Q83: Rwama FCS | R83: Till | S83: Organisation | T83: Transaction Out | U83: 10346 | V83: =G83+U83 -> 0 | W83: 0 | X83: 72 | Y83: 0 | Z83: 0 | AA83: 0 | AB83: 4281723 | AC83: 46267 | AD83: SWEJ7U8OO3J3GLE | AE83: UI2SB4X5L3 | AH83: Bingwa Sacco Society Ltd C2B | AI83: SasaPay | AJ83: ThirdPartyBillPayment | AK83: 765244 | AL83: Bingwa Sacco Society Ltd C2B | AM83: Safaricom | AN83: W13849942 | AO83: 9iiakyQAHJKcMM5U7SGh | AP83: 46267.684 | AQ83: Not Reversed | AR83: api | AS83: SUCCESS | AT83: SP00000 | AU83: Transaction completed successfully
A84: UI2SB4X5L5 | B84: 02-09-2026 16:25:30 | C84: 02-09-2026 16:25:30 | D84: Business Pay Bill via API to 765244 - Bingwa Sacco Society Ltd C2B Acc. 4343194 | E84: Completed | G84: -13682 | H84: 5359206.6 | I84: true | J84: Business Pay Bill via API | K84: 765244 - Bingwa Sacco Society Ltd C2B | M84: 4343194 | P84: 395390 | Q84: Rwama FCS | R84: Till | S84: Organisation | T84: Transaction Out | U84: 13682 | V84: =G84+U84 -> 0 | W84: 0 | X84: 72 | Y84: 0 | Z84: 0 | AA84: 0 | AB84: 4250270 | AC84: 46267 | AD84: SWEJ7U8OO3KZODI | AE84: UI2SB4X5L5 | AH84: Bingwa Sacco Society Ltd C2B | AI84: SasaPay | AJ84: ThirdPartyBillPayment | AK84: 765244 | AL84: Bingwa Sacco Society Ltd C2B | AM84: Safaricom | AN84: W13849941 | AO84: BtZC1QJIgtnpOY0Dq1z5 | AP84: 46267.684 | AQ84: Not Reversed | AR84: api | AS84: SUCCESS | AT84: SP00000 | AU84: Transaction completed successfully
A85: UI2SB4X5L8 | B85: 02-09-2026 16:25:45 | C85: 02-09-2026 16:25:45 | D85: Business Pay Bill via API to 350050 - SPOTCASH Acc. 2924809 | E85: Completed | G85: -712 | H85: 5320031.6 | I85: true | J85: Business Pay Bill via API | K85: 350050 - SPOTCASH | M85: 2924809 | P85: 395390 | Q85: Rwama FCS | R85: Till | S85: Organisation | T85: Transaction Out | U85: 712 | V85: =G85+U85 -> 0 | W85: 0 | X85: 20 | Y85: 0 | Z85: 0 | AA85: 0 | AB85: 4068446.8 | AC85: 46267 | AD85: SWEJ7U8OO3PBBYF | AE85: UI2SB4X5L8 | AH85: SPOTCASH | AI85: SasaPay | AJ85: ThirdPartyBillPayment | AK85: 350050 | AL85: SPOTCASH | AM85: Safaricom | AN85: W13849963 | AO85: B2HXpa8UZwi0yenjAVzV | AP85: 46267.684 | AQ85: Not Reversed | AR85: api | AS85: SUCCESS | AT85: SP00000 | AU85: Transaction completed successfully
A86: UI2SB4X5LE | B86: 02-09-2026 16:26:03 | C86: 02-09-2026 16:26:00 | D86: Business Pay Bill via API to 852648 - FORTUNE SACCO C2B Acc. 21784315 | E86: Completed | G86: -5194 | H86: 5259862.6 | I86: true | J86: Business Pay Bill via API | K86: 852648 - FORTUNE SACCO C2B | M86: 21784315 | P86: 395390 | Q86: Rwama FCS | R86: Till | S86: Organisation | T86: Transaction Out | U86: 5194 | V86: =G86+U86 -> 0 | W86: 0 | X86: 57 | Y86: 0 | Z86: 0 | AA86: 0 | AB86: 3815663.8 | AC86: 46267 | AD86: SWEJ7U8OO3WJD1L | AE86: UI2SB4X5LE | AH86: FORTUNE SACCO C2B | AI86: SasaPay | AJ86: ThirdPartyBillPayment | AK86: 852648 | AL86: FORTUNE SACCO C2B | AM86: Safaricom | AN86: W13850025 | AO86: MIuga7lITsc9jMGQloUp | AP86: 46267.684 | AQ86: Not Reversed | AR86: api | AS86: SUCCESS | AT86: SP00000 | AU86: Transaction completed successfully
A87: UI2SB4X5LK | B87: 02-09-2026 16:26:15 | C87: 02-09-2026 16:26:15 | D87: Business Pay Bill via API to 765244 - Bingwa Sacco Society Ltd C2B Acc. 24375662 | E87: Completed | G87: -4120 | H87: 5254853.6 | I87: true | J87: Business Pay Bill via API | K87: 765244 - Bingwa Sacco Society Ltd C2B | M87: 24375662 | P87: 395390 | Q87: Rwama FCS | R87: Till | S87: Organisation | T87: Transaction Out | U87: 4120 | V87: =G87+U87 -> 0 | W87: 0 | X87: 49 | Y87: 0 | Z87: 0 | AA87: 0 | AB87: 3767871.8 | AC87: 46267 | AD87: SWEJ7U8OO3YPBXS | AE87: UI2SB4X5LK | AH87: Bingwa Sacco Society Ltd C2B | AI87: SasaPay | AJ87: ThirdPartyBillPayment | AK87: 765244 | AL87: Bingwa Sacco Society Ltd C2B | AM87: Safaricom | AN87: W13850050 | AO87: KdyXjMv0wNA7FgJbbmTe | AP87: 46267.684 | AQ87: Not Reversed | AR87: api | AS87: SUCCESS | AT87: SP00000 | AU87: Transaction completed successfully
A88: UI2SB4X5LM | B88: 02-09-2026 16:26:19 | C88: 02-09-2026 16:26:19 | D88: Business Pay Bill via API to 765244 - Bingwa Sacco Society Ltd C2B Acc. 0166878 | E88: Completed | G88: -755 | H88: 5252358.6 | I88: true | J88: Business Pay Bill via API | K88: 765244 - Bingwa Sacco Society Ltd C2B | M88: 0166878 | P88: 395390 | Q88: Rwama FCS | R88: Till | S88: Organisation | T88: Transaction Out | U88: 755 | V88: =G88+U88 -> 0 | W88: 0 | X88: 20 | Y88: 0 | Z88: 0 | AA88: 0 | AB88: 3685513.8 | AC88: 46267 | AD88: SWEJ7U8OO31Y4KO | AE88: UI2SB4X5LM | AH88: Bingwa Sacco Society Ltd C2B | AI88: SasaPay | AJ88: ThirdPartyBillPayment | AK88: 765244 | AL88: Bingwa Sacco Society Ltd C2B | AM88: Safaricom | AN88: W13850066 | AO88: c66PuasJfHprn0jRJkxB | AP88: 46267.684 | AQ88: Not Reversed | AR88: api | AS88: SUCCESS | AT88: SP00000 | AU88: Transaction completed successfully
A89: UI2SB4X5LP | B89: 02-09-2026 16:26:24 | C89: 02-09-2026 16:26:24 | D89: Business Pay Bill via API to 765244 - Bingwa Sacco Society Ltd C2B Acc. 7946079 | E89: Completed | G89: -58 | H89: 5244931.6 | I89: true | J89: Business Pay Bill via API | K89: 765244 - Bingwa Sacco Society Ltd C2B | M89: 7946079 | P89: 395390 | Q89: Rwama FCS | R89: Till | S89: Organisation | T89: Transaction Out | U89: 58 | V89: =G89+U89 -> 0 | W89: 0 | X89: 0 | Y89: 0 | Z89: 0 | AA89: 0 | AB89: 3674366.8 | AC89: 46267 | AD89: SWEJ7U8OO33DD6Q | AE89: UI2SB4X5LP | AH89: Bingwa Sacco Society Ltd C2B | AI89: SasaPay | AJ89: ThirdPartyBillPayment | AK89: 765244 | AL89: Bingwa Sacco Society Ltd C2B | AM89: Safaricom | AN89: W13850095 | AO89: q8QwkjBoLr8Xw494mTpf | AP89: 46267.684 | AQ89: Not Reversed | AR89: api | AS89: SUCCESS | AT89: SP00000 | AU89: Transaction completed successfully
A90: UI2SB4X5M1 | B90: 02-09-2026 16:27:09 | C90: 02-09-2026 16:27:09 | D90: Business Pay Bill via API to 522533 - Lipa na KCB Acc. 9797999 | E90: Completed | G90: -140 | H90: 5244022.6 | I90: true | J90: Business Pay Bill via API | K90: 522533 - Lipa na KCB | M90: 9797999 | P90: 1440382 | Q90: Ian - Holmes | R90: Limited Personal Wallet | T90: Transaction Out | U90: 140 | V90: =G90+U90 -> 0 | W90: 0 | X90: 10 | Y90: 2 | Z90: 0 | AA90: 0 | AB90: 1674 | AC90: 46267 | AD90: SWEJ7U8OO6PZ0JG | AE90: UI2SB4X5M1 | AH90: Lipa na KCB | AI90: SasaPay | AJ90: ThirdPartyBillPayment | AK90: 1440382 | AL90: Lipa na KCB | AM90: Safaricom | AN90: W13850128 | AO90: VE858A8K | AP90: 46267.685 | AQ90: Not Reversed | AS90: SUCCESS | AT90: SP00000 | AU90: Transaction completed successfully
A91: UI2SB4X5OU | B91: 02-09-2026 16:34:39 | C91: 02-09-2026 16:34:34 | D91: Business Pay Bill via API to 982800 - Prime Bank Ltd Acc. 3000222007 | E91: Completed | G91: -20300 | H91: 5210692.6 | I91: true | J91: Business Pay Bill via API | K91: 982800 - Prime Bank Ltd | M91: 3000222007 | P91: 1331783 | Q91: Ahainnovate Ltd | R91: Till | S91: Organisation | T91: Transaction Out | U91: 20300 | V91: =G91+U91 -> 0 | W91: 0 | X91: 87 | Y91: 0 | Z91: 1 | AA91: 0 | AB91: 147678.97 | AC91: 46267 | AD91: SWEJ7U8OPIPXV0F | AE91: UI2SB4X5OU | AH91: Prime Bank Ltd | AI91: SasaPay | AJ91: ThirdPartyBillPayment | AK91: 982800 | AL91: Prime Bank Ltd | AM91: Safaricom | AN91: W13850344 | AO91: 3000222007 | AP91: 46267.69 | AQ91: Not Reversed | AS91: SUCCESS | AT91: SP00000 | AU91: Transaction completed successfully
A92: UI2SB4X5PS | B92: 02-09-2026 16:37:03 | C92: 02-09-2026 16:37:03 | D92: Business Pay Bill via API to 765244 - Bingwa Sacco Society Ltd C2B Acc. 26994742 | E92: Completed | G92: -5286 | H92: 5199245.6 | I92: true | J92: Business Pay Bill via API | K92: 765244 - Bingwa Sacco Society Ltd C2B | M92: 26994742 | P92: 395390 | Q92: Rwama FCS | R92: Till | S92: Organisation | T92: Transaction Out | U92: 5286 | V92: =G92+U92 -> 0 | W92: 0 | X92: 57 | Y92: 0 | Z92: 0 | AA92: 0 | AB92: 3627558.8 | AC92: 46267 | AD92: SWEJ7U8OPM54PQ8 | AE92: UI2SB4X5PS | AH92: Bingwa Sacco Society Ltd C2B | AI92: SasaPay | AJ92: ThirdPartyBillPayment | AK92: 765244 | AL92: Bingwa Sacco Society Ltd C2B | AM92: Safaricom | AN92: W13850392 | AO92: Hio53i8CVRp7TkWQjD6V | AP92: 46267.692 | AQ92: Not Reversed | AR92: api | AS92: SUCCESS | AT92: SP00000 | AU92: Transaction completed successfully
A93: UI2SB4X5PT | B93: 02-09-2026 16:37:04 | C93: 02-09-2026 16:37:04 | D93: Business Pay Bill via API to 765244 - Bingwa Sacco Society Ltd C2B Acc. 8600399 | E93: Completed | G93: -4281 | H93: 5194916.6 | I93: true | J93: Business Pay Bill via API | K93: 765244 - Bingwa Sacco Society Ltd C2B | M93: 8600399 | P93: 395390 | Q93: Rwama FCS | R93: Till | S93: Organisation | T93: Transaction Out | U93: 4281 | V93: =G93+U93 -> 0 | W93: 0 | X93: 49 | Y93: 0 | Z93: 0 | AA93: 0 | AB93: 3618733.8 | AC93: 46267 | AD93: SWEJ7U8OPM6BTR1 | AE93: UI2SB4X5PT | AH93: Bingwa Sacco Society Ltd C2B | AI93: SasaPay | AJ93: ThirdPartyBillPayment | AK93: 765244 | AL93: Bingwa Sacco Society Ltd C2B | AM93: Safaricom | AN93: W13850393 | AO93: ToL8UdoSsfi4eo5XQ50M | AP93: 46267.692 | AQ93: Not Reversed | AR93: api | AS93: SUCCESS | AT93: SP00000 | AU93: Transaction completed successfully
A94: UI2SB4X5PV | B94: 02-09-2026 16:37:09 | C94: 02-09-2026 16:37:09 | D94: Business Pay Bill via API to 765244 - Bingwa Sacco Society Ltd C2B Acc. 27051381 | E94: Completed | G94: -2940 | H94: 5168142.6 | I94: true | J94: Business Pay Bill via API | K94: 765244 - Bingwa Sacco Society Ltd C2B | M94: 27051381 | P94: 395390 | Q94: Rwama FCS | R94: Till | S94: Organisation | T94: Transaction Out | U94: 2940 | V94: =G94+U94 -> 0 | W94: 0 | X94: 40 | Y94: 0 | Z94: 0 | AA94: 0 | AB94: 3476902.8 | AC94: 46267 | AD94: SWEJ7U8OPM8AB3L | AE94: UI2SB4X5PV | AH94: Bingwa Sacco Society Ltd C2B | AI94: SasaPay | AJ94: ThirdPartyBillPayment | AK94: 765244 | AL94: Bingwa Sacco Society Ltd C2B | AM94: Safaricom | AN94: W13850404 | AO94: 3JDeO8U0zH3tK15vJfPj | AP94: 46267.692 | AQ94: Not Reversed | AR94: api | AS94: SUCCESS | AT94: SP00000 | AU94: Transaction completed successfully
A95: UI2SB4X5PW | B95: 02-09-2026 16:37:13 | C95: 02-09-2026 16:37:09 | D95: Business Pay Bill via API to 852648 - FORTUNE SACCO C2B Acc. 13333478 | E95: Completed | G95: -56622 | H95: 5095328.6 | I95: true | J95: Business Pay Bill via API | K95: 852648 - FORTUNE SACCO C2B | M95: 13333478 | P95: 395390 | Q95: Rwama FCS | R95: Till | S95: Organisation | T95: Transaction Out | U95: 56622 | V95: =G95+U95 -> 0 | W95: 0 | X95: 136 | Y95: 0 | Z95: 0 | AA95: 0 | AB95: 3479882.8 | AC95: 46267 | AD95: SWEJ7U8OPM77E86 | AE95: UI2SB4X5PW | AH95: FORTUNE SACCO C2B | AI95: SasaPay | AJ95: ThirdPartyBillPayment | AK95: 852648 | AL95: FORTUNE SACCO C2B | AM95: Safaricom | AN95: W13850403 | AO95: 8shsLIUrfttlwmz8XLIl | AP95: 46267.692 | AQ95: Not Reversed | AR95: api | AS95: SUCCESS | AT95: SP00000 | AU95: Transaction completed successfully
A96: UI2SB4X5Q0 | B96: 02-09-2026 16:37:30 | C96: 02-09-2026 16:37:25 | D96: Business Pay Bill via API to 852648 - FORTUNE SACCO C2B Acc. 27466107 | E96: Completed | G96: -18868 | H96: 4930435.6 | I96: true | J96: Business Pay Bill via API | K96: 852648 - FORTUNE SACCO C2B | M96: 27466107 | P96: 395390 | Q96: Rwama FCS | R96: Till | S96: Organisation | T96: Transaction Out | U96: 18868 | V96: =G96+U96 -> 0 | W96: 0 | X96: 82 | Y96: 0 | Z96: 0 | AA96: 0 | AB96: 3061638.8 | AC96: 46267 | AD96: SWEJ7U8OPNC27E9 | AE96: UI2SB4X5Q0 | AH96: FORTUNE SACCO C2B | AI96: SasaPay | AJ96: ThirdPartyBillPayment | AK96: 852648 | AL96: FORTUNE SACCO C2B | AM96: Safaricom | AN96: W13850440 | AO96: FdODOKnirOm0dWGNv7BE | AP96: 46267.692 | AQ96: Not Reversed | AR96: api | AS96: SUCCESS | AT96: SP00000 | AU96: Transaction completed successfully
A97: UI2SB4X5Q2 | B97: 02-09-2026 16:37:31 | C97: 02-09-2026 16:37:31 | D97: Business Pay Bill via API to 765244 - Bingwa Sacco Society Ltd C2B Acc. 2922415 | E97: Completed | G97: -3561 | H97: 4917172.6 | I97: true | J97: Business Pay Bill via API | K97: 765244 - Bingwa Sacco Society Ltd C2B | M97: 2922415 | P97: 395390 | Q97: Rwama FCS | R97: Till | S97: Organisation | T97: Transaction Out | U97: 3561 | V97: =G97+U97 -> 0 | W97: 0 | X97: 49 | Y97: 0 | Z97: 0 | AA97: 0 | AB97: 2815330.8 | AC97: 46267 | AD97: SWEJ7U8OPNGHVKF | AE97: UI2SB4X5Q2 | AH97: Bingwa Sacco Society Ltd C2B | AI97: SasaPay | AJ97: ThirdPartyBillPayment | AK97: 765244 | AL97: Bingwa Sacco Society Ltd C2B | AM97: Safaricom | AN97: W13850461 | AO97: ll2ITzrltlgGbcSHuzLb | AP97: 46267.692 | AQ97: Not Reversed | AR97: api | AS97: SUCCESS | AT97: SP00000 | AU97: Transaction completed successfully
A98: UI2SB4X5Q4 | B98: 02-09-2026 16:37:36 | C98: 02-09-2026 16:37:35 | D98: Business Pay Bill via API to 350050 - SPOTCASH Acc. 11261989 | E98: Completed | G98: -7603 | H98: 4828146.6 | I98: true | J98: Business Pay Bill via API | K98: 350050 - SPOTCASH | M98: 11261989 | P98: 395390 | Q98: Rwama FCS | R98: Till | S98: Organisation | T98: Transaction Out | U98: 7603 | V98: =G98+U98 -> 0 | W98: 0 | X98: 63 | Y98: 0 | Z98: 0 | AA98: 0 | AB98: 2703065.8 | AC98: 46267 | AD98: SWEJ7U8OPNH628L | AE98: UI2SB4X5Q4 | AH98: SPOTCASH | AI98: SasaPay | AJ98: ThirdPartyBillPayment | AK98: 350050 | AL98: SPOTCASH | AM98: Safaricom | AN98: W13850469 | AO98: q9mSqshUNJNypYtvvm63 | AP98: 46267.692 | AQ98: Not Reversed | AR98: api | AS98: SUCCESS | AT98: SP00000 | AU98: Transaction completed successfully
A99: UI2SB4X5Q7 | B99: 02-09-2026 16:37:40 | C99: 02-09-2026 16:37:40 | D99: Business Pay Bill via API to 765244 - Bingwa Sacco Society Ltd C2B Acc. 13473489 | E99: Completed | G99: -1810 | H99: 4720060.6 | I99: true | J99: Business Pay Bill via API | K99: 765244 - Bingwa Sacco Society Ltd C2B | M99: 13473489 | P99: 395390 | Q99: Rwama FCS | R99: Till | S99: Organisation | T99: Transaction Out | U99: 1810 | V99: =G99+U99 -> 0 | W99: 0 | X99: 35 | Y99: 0 | Z99: 0 | AA99: 0 | AB99: 2345985.8 | AC99: 46267 | AD99: SWEJ7U8OPNMDCKY | AE99: UI2SB4X5Q7 | AH99: Bingwa Sacco Society Ltd C2B | AI99: SasaPay | AJ99: ThirdPartyBillPayment | AK99: 765244 | AL99: Bingwa Sacco Society Ltd C2B | AM99: Safaricom | AN99: W13850505 | AO99: r9KrodVCWvBswIVMyV9F | AP99: 46267.692 | AQ99: Not Reversed | AR99: api | AS99: SUCCESS | AT99: SP00000 | AU99: Transaction completed successfully
A100: UI2SB4X5Q9 | B100: 02-09-2026 16:37:43 | C100: 02-09-2026 16:37:43 | D100: Business Pay Bill via API to 765244 - Bingwa Sacco Society Ltd C2B Acc. 2924863 | E100: Completed | G100: -14782 | H100: 4558788.6 | I100: true | J100: Business Pay Bill via API | K100: 765244 - Bingwa Sacco Society Ltd C2B | M100: 2924863 | P100: 395390 | Q100: Rwama FCS | R100: Till | S100: Organisation | T100: Transaction Out | U100: 14782 | V100: =G100+U100 -> 0 | W100: 0 | X100: 72 | Y100: 0 | Z100: 0 | AA100: 0 | AB100: 2610872.8 | AC100: 46267 | AD100: SWEJ7U8OPNJBKQZ | AE100: UI2SB4X5Q9 | AH100: Bingwa Sacco Society Ltd C2B | AI100: SasaPay | AJ100: ThirdPartyBillPayment | AK100: 765244 | AL100: Bingwa Sacco Society Ltd C2B | AM100: Safaricom | AN100: W13850482 | AO100: SJeqHzJQeeSoVA937V8H | AP100: 46267.692 | AQ100: Not Reversed | AR100: api | AS100: SUCCESS | AT100: SP00000 | AU100: Transaction completed successfully
...

Sheet Funds movement
A1: Receipt No. | B1: Completion Time | C1: Initiation Time | D1: Details | E1: Transaction Status | F1: Paid In | G1: Withdrawn | H1: Balance | I1: Balance Confirmed | J1: Reason Type | K1: Other Party Info | L1: Linked Transaction ID | M1: A/C No. | N1: Currency
A2: UI2SB4XQMD | B2: 02-09-2026 20:59:30 | C2: 02-09-2026 20:59:30 | D2: Funds Transfer from Utility Account to Working Account | E2: Completed | F2: 5000000 | H2: 8527403.6 | I2: true | J2: Business Transfer From Utility Account To MMF Account via API | K2: 756756 - SASA PAY | N2: KES
A3: UI2SB4WUDK | B3: 02-09-2026 12:37:20 | C3: 02-09-2026 12:37:20 | D3: Organization Settlement Account to Organization MMF Account | E3: Completed | F3: 13632763 | H3: 41633346 | I3: true | J3: Organization Settlement Account to Organization MMF Account | K3: 756756 - SASA PAY | N3: KES
F4: =SUM(F2:F3) -> 18632763
H6: Withdrawal to bank
A7: Receipt No. | B7: Completion Time | C7: Initiation Time | D7: Details | E7: Transaction Status | F7: Paid In | G7: Withdrawn | H7: Balance | I7: Balance Confirmed | J7: Reason Type | K7: Other Party Info | L7: Linked Transaction ID | M7: A/C No. | N7: Currency
A8: UI2SB4WX42 | B8: 02-09-2026 12:53:08 | C8: 02-09-2026 12:53:08 | D8: Real Time Withdrawal to 400200 - Co-operative Bank Money Transfer Acc.01192174364400 | E8: Completed | G8: -35600000 | H8: 6033345.6 | I8: true | J8: Real Time Withdrawal | K8: 400200 - Co-operative Bank Money Transfer | M8: 01192174364400 | N8: KES
G9: =SUM(G8) -> -35600000

Sheet Sheet6
A1: 455555 | B1: 343884 | C1: Michael Mboya | D1: Limited Personal Wallet | F1: Transaction Out | G1: 3465 | H1: =Working!G308+G1 -> -22010 | I1: 0 | J1: 10 | K1: 0 | L1: 0 | M1: 0 | N1: 5794 | O1: 46267 | P1: SWEJ7U8NO3GU1SL | Q1: UI2SN2T1MB | U1: SasaPay | V1: ThirdPartyBillPayment | W1: 9053691 | Y1: Safaricom | Z1: W13843135 | AA1: W13843135 | AB1: 46267.362 | AC1: Not Reversed | AD1: user_app | AE1: SUCCESS | AF1: SP00000 | AG1: Transaction completed successfully
A2: 455555 | B2: 334660 | C2: GRACE MBERA | D2: Limited Personal Wallet | F2: Transaction Out | G2: 2400 | H2: =Working!G309+G2 -> -18884 | I2: 0 | J2: 34 | K2: 0 | L2: 0 | M2: 0 | N2: 3509 | O2: 46267 | P2: SWEJ7U8NYY8KFWM | Q2: UI2SN2T4NH | T2: CIC Money Market Fund | U2: SasaPay | V2: ThirdPartyBillPayment | W2: 600118 | X2: CIC Money Market Fund | Y2: Safaricom | Z2: W13844792 | AA2: 182779 | AB2: 46267.456 | AC2: Not Reversed | AD2: user_app | AE2: SUCCESS | AF2: SP00000 | AG2: Transaction completed successfully
A3: 455555 | B3: 314127 | C3: edwin kiptoo | D3: Limited Personal Wallet | F3: Transaction Out | G3: 170 | H3: =Working!G310+G3 -> -3341166 | I3: 0 | J3: 10 | K3: 0 | L3: 0 | M3: 0 | N3: 3868 | O3: 46267 | P3: SWEJ7U8OF0KGXRT | Q3: UI2SN2TE19 | T3: ONFON MEDIA 1. | U3: SasaPay | V3: ThirdPartyBillPayment | W3: 622645 | X3: ONFON MEDIA 1. | Y3: Safaricom | Z3: W13847967 | AA3: 30348505 | AB3: 46267.602 | AC3: Not Reversed | AD3: user_app | AE3: SUCCESS | AF3: SP00000 | AG3: Transaction completed successfully
A4: 455555 | B4: 476599 | C4: JAMES KAHONGE | D4: Wallet-Personal | F4: Transaction Out | G4: 30000 | H4: =Working!G311+G4 -> 30000 | I4: 0 | J4: 92 | K4: 0 | L4: 0 | M4: 0 | N4: 10328 | O4: 46267 | P4: SWEJ7U8O6GHEC8W | Q4: UI2SN2TSRE | T4: NCBA BANK KENYA PLC. | U4: SasaPay | V4: ThirdPartyBillPayment | W4: 880100 | X4: NCBA BANK KENYA PLC. | Y4: Safaricom | Z4: W13854372 | AA4: 1441710028 | AB4: 46267.835 | AC4: Not Reversed | AD4: user_app | AE4: SUCCESS | AF4: SP00000 | AG4: Transaction completed successfully
A5: 455555 | B5: 392688 | C5: Kennedy Kunikina | D5: Limited Personal Wallet | F5: Transaction Out | G5: 170 | H5: =Working!G312+G5 -> 170 | I5: 0 | J5: 10 | K5: 0 | L5: 0 | M5: 0 | N5: 573 | O5: 46267 | P5: SWEJ7U8O20PE9L8 | Q5: UI2SN2TTY1 | U5: SasaPay | V5: ThirdPartyBillPayment | W5: 6281575 | Y5: Safaricom | Z5: W13853836 | AA5: W13853836 | AB5: 46267.811 | AC5: Not Reversed | AD5: user_app | AE5: SUCCESS | AF5: SP00000 | AG5: Transaction completed successfully
A6: 455555 | B6: 896279 | C6: Ursulla Kiniga | D6: Limited Personal Wallet | F6: Transaction Out | G6: 250 | H6: =Working!G313+G6 -> 250 | I6: 0 | J6: 10 | K6: 0 | L6: 0 | M6: 0 | N6: 11248 | O6: 46267 | P6: SWEJ7U8OZN278Y9 | Q6: UI2SN2TV7C | U6: SasaPay | V6: ThirdPartyBillPayment | W6: 3529750 | Y6: Safaricom | Z6: W13853337 | AA6: W13853337 | AB6: 46267.788 | AC6: Not Reversed | AD6: user_app | AE6: SUCCESS | AF6: SP00000 | AG6: Transaction completed successfully
A7: 455555 | B7: 390602 | C7: Fundia David | D7: Limited Personal Wallet | F7: Transaction Out | G7: 3000 | H7: =Working!G314+G7 -> 3000 | I7: 0 | J7: 10 | K7: 0 | L7: 0 | M7: 0 | N7: 47078 | O7: 46267 | P7: SWEJ7U8PCK0U0RG | Q7: UI2SN2U4AD | U7: SasaPay | V7: ThirdPartyBillPayment | W7: 138586 | Y7: Safaricom | Z7: W13855999 | AA7: W13855999 | AB7: 46267.9 | AC7: Not Reversed | AD7: user_app | AE7: SUCCESS | AF7: SP00000 | AG7: Transaction completed successfully
A8: 455555 | B8: 1691107 | C8: George Okeyo | D8: Limited Personal Wallet | F8: Transaction Out | G8: 1050 | H8: =Working!G315+G8 -> 1050 | I8: 0 | J8: 10 | K8: 0 | L8: 0 | M8: 0 | N8: 5902 | O8: 46267 | P8: SWEJ7U8PJ4D7UJY | Q8: UI2SN2U4UR | U8: SasaPay | V8: ThirdPartyBillPayment | W8: 9239183 | Y8: Safaricom | Z8: W13856932 | AA8: W13856932 | AB8: 46267.958 | AC8: Not Reversed | AD8: user_app | AE8: SUCCESS | AF8: SP00000 | AG8: Transaction completed successfully
A9: 455555 | B9: 132186 | C9: Felix Otieno | D9: Limited Personal Wallet | F9: Transaction Out | G9: 750 | H9: =Working!G316+G9 -> 750 | I9: 0 | J9: 20 | K9: 0 | L9: 0 | M9: 0 | N9: 10523 | O9: 46267 | P9: SWEJ7U8PCZV0T7T | Q9: UI2SN2U73M | T9: Co | U9: SasaPay | V9: ThirdPartyBillPayment | W9: 400200 | X9: Co | Y9: Safaricom | Z9: W13856119 | AA9: 1186541 | AB9: 46267.906 | AC9: Not Reversed | AD9: user_app | AE9: SUCCESS | AF9: SP00000 | AG9: Transaction completed successfully

Sheet Charges
A1: Receipt No. | B1: Completion Time | C1: Initiation Time | D1: Details | E1: Transaction Status | F1: Paid In | G1: Withdrawn | H1: Balance | I1: Balance Confirmed | J1: Reason Type | K1: Other Party Info | L1: Linked Transaction ID | M1: A/C No. | N1: Currency
A2: UI2SB4Y11C | B2: 02-09-2026 23:35:58 | C2: 02-09-2026 23:35:58 | D2: Business Buy Goods Charge | E2: Completed | G2: -18 | H2: 8341383.6 | I2: true | J2: Business Buy Goods via API | K2: SP | N2: KES
A3: UI2SB4XZP4 | B3: 02-09-2026 22:11:30 | C3: 02-09-2026 22:11:30 | D3: Business Pay Bill Charge | E3: Completed | G3: -13 | H3: 8342851.6 | I3: true | J3: Business Pay Bill via API | K3: SP | N3: KES
A4: UI2SB4XY6A | B4: 02-09-2026 22:11:16 | C4: 02-09-2026 22:11:16 | D4: Business Buy Goods Charge | E4: Completed | G4: -39 | H4: 8343614.6 | I4: true | J4: Business Buy Goods via API | K4: SP | N4: KES
A5: UI2SB4XV62 | B5: 02-09-2026 22:10:16 | C5: 02-09-2026 22:10:16 | D5: Business Buy Goods Charge | E5: Completed | G5: -39 | H5: 8348653.6 | I5: true | J5: Business Buy Goods via API | K5: SP | N5: KES
A6: UI2SB4XR95 | B6: 02-09-2026 22:09:53 | C6: 02-09-2026 22:09:53 | D6: Business Buy Goods Charge | E6: Completed | G6: -39 | H6: 8353692.6 | I6: true | J6: Business Buy Goods via API | K6: SP | N6: KES
A7: UI2SB4XWNW | B7: 02-09-2026 22:07:39 | C7: 02-09-2026 22:07:39 | D7: Business Buy Goods Charge | E7: Completed | G7: -39 | H7: 8358031.6 | I7: true | J7: Business Buy Goods via API | K7: SP | N7: KES
A8: UI2SB4XZOC | B8: 02-09-2026 22:06:32 | C8: 02-09-2026 22:06:32 | D8: Business Buy Goods Charge | E8: Completed | G8: -39 | H8: 8363070.6 | I8: true | J8: Business Buy Goods via API | K8: SP | N8: KES
A9: UI2SB4XWNB | B9: 02-09-2026 22:05:20 | C9: 02-09-2026 22:05:20 | D9: Business Buy Goods Charge | E9: Completed | G9: -54 | H9: 8368109.6 | I9: true | J9: Business Buy Goods via API | K9: SP | N9: KES
A10: UI2SB4XWKN | B10: 02-09-2026 21:58:43 | C10: 02-09-2026 21:58:43 | D10: Business Pay Bill Charge | E10: Completed | G10: -8 | H10: 8376063.6 | I10: true | J10: Business Pay Bill via API | K10: SP | N10: KES
A11: UI2SB4XUYP | B11: 02-09-2026 21:48:00 | C11: 02-09-2026 21:48:00 | D11: Business Buy Goods Charge | E11: Completed | G11: -48 | H11: 8376221.6 | I11: true | J11: Business Buy Goods via API | K11: SP | N11: KES
A12: UI2SB4XR2E | B12: 02-09-2026 21:45:41 | C12: 02-09-2026 21:45:41 | D12: Business Pay Bill Charge | E12: Completed | G12: -25 | H12: 8381819.6 | I12: true | J12: Business Pay Bill via API | K12: SP | N12: KES
A13: UI2SB4XR0O | B13: 02-09-2026 21:40:13 | C13: 02-09-2026 21:40:13 | D13: Business Buy Goods Charge | E13: Completed | G13: -48 | H13: 8383844.6 | I13: true | J13: Business Buy Goods via API | K13: SP | N13: KES
... A304: UI2SB4VYS8 | B304: 02-09-2026 01:02:30 | C304: 02-09-2026 01:02:30 | D304: Business Buy Goods Charge | E304: Completed | G304: -25 | H304: 28661733 | I304: true | J304: Business Buy Goods via API | K304: SP | N304: KES
G305: =SUM(G2:G304) -> -13582

Sheet reconciliation
A1: M-PESA RECONCILIATION
A2: DATE | B2: 2nd Sept
A3: Opening Balance | B3: =transaction!H622 -> 28663538
A4: Less:Customer Withdrawals | B4: =Working!G310 -> -3341336
A5: Less:charges | B5: =Charges!G305 -> -13582
A6: Add:Float movement(Movement from utility to working account account) | B6: ='Funds movement'!F4 -> 18632763
A7: Add :Reversals | B7: 0
A8: Less:Withdrawal to bank | B8: ='Funds movement'!G9 -> -35600000
A9: Balance c/d | B9: =SUM(B3:B8) -> 8341383.6
A10: Balance as per Mpesa smt | B10: =transaction!H8 -> 8341383.6
A11: Variance
A13: Summary
A14: Withdrawals as per sasapay | B14: =Working!U310 -> 3341336
A15: Withdrawals as per M-pesa | B15: =Working!G310 -> -3341336
A16: Variance
A17: Justification
A18: Transaction on Mpesa only.
A19: Transaction on Sasapay only.
